====================
<code object <module> at 0x104be05b0, file "ck.py", line 1>
====================
code len :  9008
line :   1
              0 JUMP_ABSOLUTE         1552
              3 INPLACE_TRUE_DIVIDE 
              4 LOAD_ATTR            18457
====================
error opcode: 'int' object has no attribute '__getitem__'
--> hasname 18457 <--
====================

              7 SETUP_WITH           27516 (to 27526)

====================
error opcode: 'int' object has no attribute '__getitem__'
--> hasjrel 27516 <--
====================

             10 ROT_TWO             
             11 STOP_CODE           
             12 POP_JUMP_IF_TRUE        36
             15 LOAD_CONST             199 (138616049)
             18 LOAD_FAST                0 (DIVIDER)
             21 COMPARE_OP               2 (==)
             24 POP_JUMP_IF_TRUE        39
             27 LOAD_CONST             163 (2253539484)
             30 LOAD_FAST                0 (DIVIDER)
             33 JUMP_FORWARD          6752 (to 6788)

====================
error opcode: 'int' object has no attribute '__getitem__'
--> hasjrel 6752 <--
====================

        >>   36 JUMP_FORWARD          5075 (to 5114)

====================
error opcode: 'int' object has no attribute '__getitem__'
--> hasjrel 5075 <--
====================

        >>   39 JUMP_FORWARD          5192 (to 5234)

====================
error opcode: 'int' object has no attribute '__getitem__'
--> hasjrel 5192 <--
====================

             42 DUP_TOPX             25720
             45 LIST_APPEND            125
             48 STOP_CODE           
             49 JUMP_ABSOLUTE           79
        >>   52 LOAD_CONST             198 (1582782904)

line :   7
             55 STORE_FAST               0 (DIVIDER)
             58 JUMP_ABSOLUTE           82
        >>   61 LOAD_CONST             199 (138616049)
             64 STORE_FAST               0 (DIVIDER)
             67 JUMP_ABSOLUTE           85
        >>   70 LOAD_CONST             200 (3303908731)
             73 STORE_FAST               0 (DIVIDER)
             76 JUMP_FORWARD          4743 (to 4822)

====================
error opcode: 'int' object has no attribute '__getitem__'
--> hasjrel 4743 <--
====================

        >>   79 JUMP_FORWARD          3777 (to 3859)

====================
error opcode: 'int' object has no attribute '__getitem__'
--> hasjrel 3777 <--
====================

        >>   82 JUMP_FORWARD          3774 (to 3859)

====================
error opcode: 'int' object has no attribute '__getitem__'
--> hasjrel 3774 <--
====================

        >>   85 JUMP_FORWARD          3771 (to 3859)

====================
error opcode: 'int' object has no attribute '__getitem__'
--> hasjrel 3771 <--
====================

             88 RAISE_VARARGS        21647
             91 DELETE_SUBSCR       

line :  10
             92 POP_TOP             
             93 LOAD_FAST            25950
====================
error opcode: 'int' object has no attribute '__getitem__'
--> haslocal 25950 <--
====================

             96 <6>                 

line :  11
             97 STOP_CODE           
             98 LOAD_CONST              14 ('Please input your key(hex string):')
            101 CALL_FUNCTION            1
            104 STORE_GLOBAL             1 (b)
            107 LOAD_CONST              15 (9981)
            110 JUMP_ABSOLUTE          120
        >>  113 POP_TOP             
            114 LOAD_NAME                0 (a)
            117 JUMP_FORWARD          3384 (to 3504)

====================
error opcode: 'int' object has no attribute '__getitem__'
--> hasjrel 3384 <--
====================

        >>  120 JUMP_FORWARD          3001 (to 3124)

====================
error opcode: 'int' object has no attribute '__getitem__'
--> hasjrel 3001 <--
====================

            123 POP_TOP             
        >>  124 SETUP_FINALLY        16972 (to 17099)

====================
error opcode: 'int' object has no attribute '__getitem__'
--> hasjrel 16972 <--
====================

            127 LOAD_CLOSURE         25705
====================
error opcode: 'int' object has no attribute '__getitem__'
--> hasfree 25705 <--
====================

            130 <129>                31744
            133 STOP_CODE           

line :  15
            134 STOP_CODE           
            135 COMPARE_OP               2 (==)
            138 POP_JUMP_IF_TRUE       162
            141 LOAD_CONST              89 (2457746969)
            144 LOAD_FAST                0 (DIVIDER)
            147 COMPARE_OP               2 (==)

line :  17
            150 POP_JUMP_IF_TRUE       165
            153 LOAD_CONST             160 (1556037817)
            156 LOAD_FAST                0 (DIVIDER)
            159 JUMP_FORWARD          8595 (to 8757)

====================
error opcode: 'int' object has no attribute '__getitem__'
--> hasjrel 8595 <--
====================

        >>  162 JUMP_FORWARD          4348 (to 4513)

====================
error opcode: 'int' object has no attribute '__getitem__'
--> hasjrel 4348 <--
====================

        >>  165 JUMP_FORWARD          4539 (to 4707)

====================
error opcode: 'int' object has no attribute '__getitem__'
--> hasjrel 4539 <--
====================

            168 PRINT_EXPR          
            169 RAISE_VARARGS        22614
            172 STORE_DEREF          50801
            175 STOP_CODE           
        >>  176 LOAD_CONST              49 ((1, 2))
            179 STORE_NAME              23 (args)
            182 BUILD_MAP                1
            185 LOAD_CONST               9 (2)

line :  21
            188 JUMP_ABSOLUTE          201
        >>  191 POP_TOP             
            192 LOAD_NAME                0 (a)
            195 JUMP_FORWARD          4298 (to 4496)

====================
error opcode: 'int' object has no attribute '__getitem__'
--> hasjrel 4298 <--
====================


line :  22
            198 JUMP_FORWARD          2444 (to 2645)

====================
error opcode: 'int' object has no attribute '__getitem__'
--> hasjrel 2444 <--
====================

        >>  201 JUMP_FORWARD          6941 (to 7145)

====================
error opcode: 'int' object has no attribute '__getitem__'
--> hasjrel 6941 <--
====================

            204 LOAD_NAME            18219
====================
error opcode: 'int' object has no attribute '__getitem__'
--> hasname 18219 <--
====================

            207 POP_JUMP_IF_TRUE     33643
            210 CALL_FUNCTION        23140
            213 STOP_CODE           
            214 LOAD_FAST                0 (DIVIDER)
            217 COMPARE_OP               2 (==)
            220 POP_JUMP_IF_TRUE       244

line :  24
            223 LOAD_CONST              52 (3638048434)
            226 LOAD_FAST                0 (DIVIDER)
            229 COMPARE_OP               2 (==)
            232 POP_JUMP_IF_TRUE       247
            235 LOAD_CONST             138 (2232366503)
            238 LOAD_FAST                0 (DIVIDER)
            241 JUMP_FORWARD          3128 (to 3372)

====================
error opcode: 'int' object has no attribute '__getitem__'
--> hasjrel 3128 <--
====================

        >>  244 JUMP_FORWARD          5876 (to 6123)

====================
error opcode: 'int' object has no attribute '__getitem__'
--> hasjrel 5876 <--
====================

        >>  247 JUMP_FORWARD          2487 (to 2737)

====================
error opcode: 'int' object has no attribute '__getitem__'
--> hasjrel 2487 <--
====================

            250 STORE_MAP           
            251 JUMP_FORWARD         14880 (to 15134)

====================
error opcode: 'int' object has no attribute '__getitem__'
--> hasjrel 14880 <--
====================


line :  26
            254 SLICE+3             
            255 MAP_ADD               6264
            258 STOP_CODE           
            259 JUMP_ABSOLUTE          286
        >>  262 JUMP_ABSOLUTE          289
        >>  265 JUMP_FORWARD            24 (to 292)

====================
error opcode: 'int' object has no attribute '__getitem__'
--> hasjrel 24 <--
====================

            268 JUMP_ABSOLUTE          295
        >>  271 JUMP_ABSOLUTE          298
        >>  274 END_FINALLY         
            275 JUMP_ABSOLUTE          301
        >>  278 BINARY_XOR          

line :  28
            279 POP_TOP             
            280 JUMP_FORWARD          5370 (to 5653)

====================
error opcode: 'int' object has no attribute '__getitem__'
--> hasjrel 5370 <--
====================


line :  29
            283 JUMP_ABSOLUTE          262
        >>  286 JUMP_FORWARD          2881 (to 3170)

====================
error opcode: 'int' object has no attribute '__getitem__'
--> hasjrel 2881 <--
====================

        >>  289 JUMP_FORWARD          6908 (to 7200)

====================
error opcode: 'int' object has no attribute '__getitem__'
--> hasjrel 6908 <--
====================

        >>  292 JUMP_ABSOLUTE          271
        >>  295 JUMP_FORWARD          7081 (to 7379)

====================
error opcode: 'int' object has no attribute '__getitem__'
--> hasjrel 7081 <--
====================

        >>  298 JUMP_FORWARD          7078 (to 7379)

====================
error opcode: 'int' object has no attribute '__getitem__'
--> hasjrel 7078 <--
====================

        >>  301 JUMP_FORWARD           612 (to 916)

====================
error opcode: 'int' object has no attribute '__getitem__'
--> hasjrel 612 <--
====================

            304 INPLACE_RSHIFT      
            305 BINARY_ADD          
            306 EXTENDED_ARG         28169
            309 STORE_GLOBAL         1846107445L
====================
error opcode: 'long' object has no attribute '__getitem__'
--> hasname 1846107445 <--
====================

        >>  312 LOAD_CONST             194 (825242903)
            315 LOAD_FAST                0 (DIVIDER)

line :  33
            318 COMPARE_OP               2 (==)
            321 POP_JUMP_IF_TRUE       339
            324 LOAD_CONST              53 (3202849204)
            327 LOAD_FAST                0 (DIVIDER)

line :  34
            330 COMPARE_OP               2 (==)
            333 POP_JUMP_IF_TRUE       342
            336 JUMP_FORWARD          5433 (to 5772)

====================
error opcode: 'int' object has no attribute '__getitem__'
--> hasjrel 5433 <--
====================

        >>  339 JUMP_FORWARD          6067 (to 6409)

====================
error opcode: 'int' object has no attribute '__getitem__'
--> hasjrel 6067 <--
====================

        >>  342 JUMP_FORWARD           868 (to 1213)

====================
error opcode: 'int' object has no attribute '__getitem__'
--> hasjrel 868 <--
====================

            345 LIST_APPEND           4893
            348 SET_ADD                619
            351 STOP_CODE           
            352 POP_JUMP_IF_TRUE       382
            355 LOAD_CONST              84 (3599662753)
            358 LOAD_FAST                0 (DIVIDER)
            361 COMPARE_OP               2 (==)
            364 POP_JUMP_IF_TRUE       385
            367 LOAD_CONST             152 (2380049738)

line :  38
            370 LOAD_FAST                0 (DIVIDER)
            373 COMPARE_OP               2 (==)
            376 POP_JUMP_IF_TRUE       388
            379 JUMP_FORWARD          7497 (to 7879)

====================
error opcode: 'int' object has no attribute '__getitem__'
--> hasjrel 7497 <--
====================

        >>  382 JUMP_FORWARD          5578 (to 5963)

====================
error opcode: 'int' object has no attribute '__getitem__'
--> hasjrel 5578 <--
====================

        >>  385 JUMP_FORWARD          1051 (to 1439)

====================
error opcode: 'int' object has no attribute '__getitem__'
--> hasjrel 1051 <--
====================

        >>  388 JUMP_FORWARD           997 (to 1388)

====================
error opcode: 'int' object has no attribute '__getitem__'
--> hasjrel 997 <--
====================

            391 BINARY_TRUE_DIVIDE  

line :  40
            392 YIELD_VALUE         
            393 COMPARE_OP           29329
====================
error opcode: 'int' object has no attribute '__getitem__'
--> hascompare 29329 <--
====================

        >>  396 JUMP_ABSOLUTE          426
        >>  399 LOAD_CONST             116 (2205336485)

line :  41
            402 STORE_FAST               0 (DIVIDER)
            405 JUMP_ABSOLUTE          429
        >>  408 LOAD_CONST             117 (1750546855)
            411 STORE_FAST               0 (DIVIDER)
            414 JUMP_ABSOLUTE          432
        >>  417 LOAD_CONST             118 (935379986)
            420 STORE_FAST               0 (DIVIDER)
            423 JUMP_FORWARD          5934 (to 6360)

====================
error opcode: 'int' object has no attribute '__getitem__'
--> hasjrel 5934 <--
====================

        >>  426 JUMP_FORWARD          3430 (to 3859)

====================
error opcode: 'int' object has no attribute '__getitem__'
--> hasjrel 3430 <--
====================

        >>  429 JUMP_FORWARD          3427 (to 3859)

====================
error opcode: 'int' object has no attribute '__getitem__'
--> hasjrel 3427 <--
====================

        >>  432 JUMP_FORWARD          3424 (to 3859)

====================
error opcode: 'int' object has no attribute '__getitem__'
--> hasjrel 3424 <--
====================

            435 INPLACE_XOR         
            436 POP_BLOCK           
            437 RAISE_VARARGS        20087
            440 SETUP_EXCEPT         29073 (to 29516)

====================
error opcode: 'int' object has no attribute '__getitem__'
--> hasjrel 29073 <--
====================

            443 <212>                28929
            446 <215>                22273
            449 JUMP_ABSOLUTE          474
        >>  452 CALL_FUNCTION            2
            455 GET_ITER            
            456 JUMP_ABSOLUTE          477
        >>  459 STORE_NAME               0 (a)
            462 LOAD_CONST              36 (<code object a at 0x104be01b0, file "ck.py", line 190>)
            465 JUMP_FORWARD          3348 (to 3816)

====================
error opcode: 'int' object has no attribute '__getitem__'
--> hasjrel 3348 <--
====================

            468 JUMP_FORWARD          5901 (to 6372)

====================
error opcode: 'int' object has no attribute '__getitem__'
--> hasjrel 5901 <--
====================

            471 JUMP_FORWARD           567 (to 1041)

====================
error opcode: 'int' object has no attribute '__getitem__'
--> hasjrel 567 <--
====================

        >>  474 JUMP_FORWARD          6723 (to 7200)

====================
error opcode: 'int' object has no attribute '__getitem__'
--> hasjrel 6723 <--
====================

        >>  477 JUMP_FORWARD          6784 (to 7264)

====================
error opcode: 'int' object has no attribute '__getitem__'
--> hasjrel 6784 <--
====================

            480 BUILD_MAP             2662
            483 STORE_SLICE+0       
            484 PRINT_ITEM          

line :  48
            485 ROT_TWO             
            486 PRINT_NEWLINE_TO    
            487 LIST_APPEND          25733
            490 <195>                31744
            493 STOP_CODE           
            494 STOP_CODE           
            495 COMPARE_OP               2 (==)

line :  49
            498 POP_JUMP_IF_TRUE       522
            501 LOAD_CONST             159 (3698725459)
            504 LOAD_FAST                0 (DIVIDER)
            507 COMPARE_OP               2 (==)
            510 POP_JUMP_IF_TRUE       525
            513 LOAD_CONST              88 (1734941752)
            516 LOAD_FAST                0 (DIVIDER)
            519 JUMP_FORWARD          5366 (to 5888)

====================
error opcode: 'int' object has no attribute '__getitem__'
--> hasjrel 5366 <--
====================

        >>  522 JUMP_FORWARD          6824 (to 7349)

====================
error opcode: 'int' object has no attribute '__getitem__'
--> hasjrel 6824 <--
====================

        >>  525 JUMP_FORWARD          7664 (to 8192)

====================
error opcode: 'int' object has no attribute '__getitem__'
--> hasjrel 7664 <--
====================

            528 JUMP_FORWARD           853 (to 1384)

====================
error opcode: 'int' object has no attribute '__getitem__'
--> hasjrel 853 <--
====================

            531 SETUP_EXCEPT         29572 (to 30106)

====================
error opcode: 'int' object has no attribute '__getitem__'
--> hasjrel 29572 <--
====================

            534 <48>                
            535 ROT_TWO             
            536 LOAD_CONST             114 (1478027868)

line :  61
            539 LOAD_FAST                0 (DIVIDER)
            542 COMPARE_OP               2 (==)
            545 POP_JUMP_IF_TRUE       563
            548 LOAD_CONST             115 (299054134)
            551 LOAD_FAST                0 (DIVIDER)
            554 COMPARE_OP               2 (==)
            557 JUMP_FORWARD          2285 (to 2845)

====================
error opcode: 'int' object has no attribute '__getitem__'
--> hasjrel 2285 <--
====================

            560 JUMP_FORWARD          2052 (to 2615)

====================
error opcode: 'int' object has no attribute '__getitem__'
--> hasjrel 2052 <--
====================

        >>  563 JUMP_FORWARD          5097 (to 5663)

====================
error opcode: 'int' object has no attribute '__getitem__'
--> hasjrel 5097 <--
====================

            566 DELETE_ATTR           2926
====================
error opcode: 'int' object has no attribute '__getitem__'
--> hasname 2926 <--
====================


line :  64
            569 UNARY_POSITIVE      
            570 BINARY_SUBSCR       
            571 INPLACE_RSHIFT      
            572 BINARY_POWER        
            573 SETUP_WITH           23665 (to 24241)

====================
error opcode: 'int' object has no attribute '__getitem__'
--> hasjrel 23665 <--
====================

            576 ROT_TWO             
        >>  577 LOAD_CONST              84 (3599662753)
            580 STORE_FAST               0 (DIVIDER)
            583 JUMP_ABSOLUTE          607
        >>  586 LOAD_CONST              85 (2977686067)
            589 STORE_FAST               0 (DIVIDER)
            592 JUMP_ABSOLUTE          610
        >>  595 LOAD_CONST              86 (620738832)
            598 STORE_FAST               0 (DIVIDER)
            601 JUMP_FORWARD           425 (to 1029)

====================
error opcode: 'int' object has no attribute '__getitem__'
--> hasjrel 425 <--
====================

            604 JUMP_FORWARD          3252 (to 3859)

====================
error opcode: 'int' object has no attribute '__getitem__'
--> hasjrel 3252 <--
====================

        >>  607 JUMP_FORWARD          3249 (to 3859)

====================
error opcode: 'int' object has no attribute '__getitem__'
--> hasjrel 3249 <--
====================

        >>  610 JUMP_FORWARD          3246 (to 3859)

====================
error opcode: 'int' object has no attribute '__getitem__'
--> hasjrel 3246 <--
====================

            613 BINARY_RSHIFT       
            614 DUP_TOPX             26650
            617 SETUP_FINALLY          267 (to 887)

====================
error opcode: 'int' object has no attribute '__getitem__'
--> hasjrel 267 <--
====================

            620 JUMP_ABSOLUTE          647
        >>  623 BUILD_LIST               0
            626 LOAD_NAME                9 (xrange)
            629 LOAD_CONST               2 (0)
            632 JUMP_ABSOLUTE          650
        >>  635 LOAD_CONST               8 (1)
            638 BUILD_LIST               1
            641 LOAD_NAME                0 (a)

line :  75
            644 JUMP_FORWARD          5940 (to 6587)

====================
error opcode: 'int' object has no attribute '__getitem__'
--> hasjrel 5940 <--
====================

        >>  647 JUMP_FORWARD           300 (to 950)

====================
error opcode: 'int' object has no attribute '__getitem__'
--> hasjrel 300 <--
====================

        >>  650 JUMP_FORWARD          5499 (to 6152)

====================
error opcode: 'int' object has no attribute '__getitem__'
--> hasjrel 5499 <--
====================

            653 WITH_CLEANUP        
            654 JUMP_ABSOLUTE         5436
            657 CALL_FUNCTION_VAR    45171
            660 ROT_TWO             
            661 LOAD_CONST             105 (4015874589)
            664 LOAD_FAST                0 (DIVIDER)
            667 COMPARE_OP               2 (==)
            670 POP_JUMP_IF_TRUE       691
            673 LOAD_CONST             196 (3700268313)
            676 LOAD_FAST                0 (DIVIDER)
            679 COMPARE_OP               2 (==)
            682 POP_JUMP_IF_TRUE       694
            685 JUMP_FORWARD          2994 (to 3682)

====================
error opcode: 'int' object has no attribute '__getitem__'
--> hasjrel 2994 <--
====================

            688 JUMP_FORWARD          2608 (to 3299)

====================
error opcode: 'int' object has no attribute '__getitem__'
--> hasjrel 2608 <--
====================

        >>  691 JUMP_FORWARD            21 (to 715)

====================
error opcode: 'int' object has no attribute '__getitem__'
--> hasjrel 21 <--
====================


line :  81
        >>  694 JUMP_FORWARD          2074 (to 2771)

====================
error opcode: 'int' object has no attribute '__getitem__'
--> hasjrel 2074 <--
====================

            697 IMPORT_NAME          15420
====================
error opcode: 'int' object has no attribute '__getitem__'
--> hasname 15420 <--
====================

            700 INPLACE_XOR         
            701 MAKE_CLOSURE         25456
            704 ROT_TWO             
            705 STOP_CODE           
            706 BINARY_SUBSCR       
            707 LOAD_CONST               8 (1)
            710 INPLACE_POWER       
            711 ROT_THREE           
            712 JUMP_ABSOLUTE          727
        >>  715 STORE_NAME              22 (f)
            718 LOAD_CONST              39 (<code object a at 0x104be03b0, file "ck.py", line 203>)
            721 MAKE_FUNCTION            0
            724 JUMP_FORWARD          6863 (to 7590)

====================
error opcode: 'int' object has no attribute '__getitem__'
--> hasjrel 6863 <--
====================

        >>  727 JUMP_FORWARD          3741 (to 4471)

====================
error opcode: 'int' object has no attribute '__getitem__'
--> hasjrel 3741 <--
====================


line :  83
            730 INPLACE_MODULO      
            731 FOR_ITER             34936 (to 35670)

====================
error opcode: 'int' object has no attribute '__getitem__'
--> hasjrel 34936 <--
====================

            734 DUP_TOP             
            735 SETUP_LOOP           32094 (to 32832)

====================
error opcode: 'int' object has no attribute '__getitem__'
--> hasjrel 32094 <--
====================

            738 STOP_CODE           

line :  84
            739 STOP_CODE           
            740 JUMP_ABSOLUTE          770
        >>  743 LOAD_CONST              90 (4265507034)
            746 STORE_FAST               0 (DIVIDER)
            749 JUMP_ABSOLUTE          773
        >>  752 LOAD_CONST              91 (3707959493)
            755 STORE_FAST               0 (DIVIDER)
            758 JUMP_ABSOLUTE          776
        >>  761 LOAD_CONST              92 (2311562147)
            764 STORE_FAST               0 (DIVIDER)
            767 JUMP_FORWARD          4102 (to 4872)

====================
error opcode: 'int' object has no attribute '__getitem__'
--> hasjrel 4102 <--
====================

        >>  770 JUMP_FORWARD          3086 (to 3859)

====================
error opcode: 'int' object has no attribute '__getitem__'
--> hasjrel 3086 <--
====================

        >>  773 JUMP_FORWARD          3083 (to 3859)

====================
error opcode: 'int' object has no attribute '__getitem__'
--> hasjrel 3083 <--
====================

        >>  776 JUMP_FORWARD          3080 (to 3859)

====================
error opcode: 'int' object has no attribute '__getitem__'
--> hasjrel 3080 <--
====================

            779 UNARY_POSITIVE      
            780 EXEC_STMT           
            781 BINARY_LSHIFT       
            782 LOAD_GLOBAL          31237
====================
error opcode: 'int' object has no attribute '__getitem__'
--> hasname 31237 <--
====================


line :  93
        >>  785 LOAD_CONST               8 (1)
            788 BINARY_MULTIPLY     

line :  94
            789 POP_TOP             
            790 JUMP_ABSOLUTE          811
        >>  793 CALL_FUNCTION            1

line :  95
            796 STORE_NAME              18 (c)
            799 LOAD_CONST              31 (<code object a at 0x104bbdf30, file "ck.py", line 125>)
            802 MAKE_FUNCTION            0
            805 STORE_NAME               0 (a)
            808 JUMP_FORWARD          5680 (to 6491)

====================
error opcode: 'int' object has no attribute '__getitem__'
--> hasjrel 5680 <--
====================


line :  98
        >>  811 JUMP_FORWARD           759 (to 1573)

====================
error opcode: 'int' object has no attribute '__getitem__'
--> hasjrel 759 <--
====================

            814 INPLACE_XOR         
            815 RAISE_VARARGS        32391
            818 MAKE_FUNCTION        27539
            821 ROT_TWO             
            822 STOP_CODE           
            823 POP_JUMP_IF_TRUE       853
            826 LOAD_CONST              96 (1993617135)
            829 LOAD_FAST                0 (DIVIDER)
            832 COMPARE_OP               2 (==)
            835 POP_JUMP_IF_TRUE       856
            838 LOAD_CONST              56 (3286049750)
            841 LOAD_FAST                0 (DIVIDER)
            844 COMPARE_OP               2 (==)

line : 103
            847 POP_JUMP_IF_TRUE       859
            850 JUMP_FORWARD          1661 (to 2514)

====================
error opcode: 'int' object has no attribute '__getitem__'
--> hasjrel 1661 <--
====================

        >>  853 JUMP_FORWARD          4269 (to 5125)

====================
error opcode: 'int' object has no attribute '__getitem__'
--> hasjrel 4269 <--
====================

        >>  856 JUMP_FORWARD          7160 (to 8019)

====================
error opcode: 'int' object has no attribute '__getitem__'
--> hasjrel 7160 <--
====================


line : 104
        >>  859 JUMP_FORWARD          6107 (to 6969)

====================
error opcode: 'int' object has no attribute '__getitem__'
--> hasjrel 6107 <--
====================

            862 BREAK_LOOP          
            863 FOR_ITER               852 (to 1718)

====================
error opcode: 'int' object has no attribute '__getitem__'
--> hasjrel 852 <--
====================

            866 UNARY_NOT           
            867 STORE_DEREF          35096
        >>  870 COMPARE_OP               2 (==)
            873 POP_JUMP_IF_TRUE       897
            876 LOAD_CONST             178 (1136472242)
            879 LOAD_FAST                0 (DIVIDER)
            882 COMPARE_OP               2 (==)
            885 POP_JUMP_IF_TRUE       900
            888 LOAD_CONST             161 (3030036581)
            891 LOAD_FAST                0 (DIVIDER)

line : 108
            894 JUMP_FORWARD          3003 (to 3900)

====================
error opcode: 'int' object has no attribute '__getitem__'
--> hasjrel 3003 <--
====================

        >>  897 JUMP_FORWARD          4797 (to 5697)

====================
error opcode: 'int' object has no attribute '__getitem__'
--> hasjrel 4797 <--
====================

        >>  900 JUMP_FORWARD          8046 (to 8949)

====================
error opcode: 'int' object has no attribute '__getitem__'
--> hasjrel 8046 <--
====================

            903 BINARY_SUBSCR       

line : 110
            904 POP_JUMP_IF_FALSE    29287
        >>  907 LOAD_CONST              98 (1359232345)
            910 STORE_FAST               0 (DIVIDER)

line : 115
            913 JUMP_ABSOLUTE          937
        >>  916 LOAD_CONST              99 (409037964)
            919 STORE_FAST               0 (DIVIDER)

line : 119
            922 JUMP_ABSOLUTE          940
        >>  925 LOAD_CONST             100 (2394748892)
            928 STORE_FAST               0 (DIVIDER)
            931 JUMP_ABSOLUTE          943

line : 120
            934 JUMP_FORWARD          5724 (to 6661)

====================
error opcode: 'int' object has no attribute '__getitem__'
--> hasjrel 5724 <--
====================

        >>  937 JUMP_FORWARD          2919 (to 3859)

====================
error opcode: 'int' object has no attribute '__getitem__'
--> hasjrel 2919 <--
====================


line : 121
        >>  940 JUMP_FORWARD          2916 (to 3859)

====================
error opcode: 'int' object has no attribute '__getitem__'
--> hasjrel 2916 <--
====================


line : 122
        >>  943 JUMP_FORWARD          2913 (to 3859)

====================
error opcode: 'int' object has no attribute '__getitem__'
--> hasjrel 2913 <--
====================

            946 SLICE+1             
            947 DUP_TOP             
            948 DELETE_SUBSCR       

line : 123
            949 LOAD_ATTR            35940
====================
error opcode: 'int' object has no attribute '__getitem__'
--> hasname 35940 <--
====================


line : 124
            952 STOP_CODE           
            953 STORE_FAST               0 (DIVIDER)
            956 JUMP_ABSOLUTE          977
        >>  959 LOAD_CONST             141 (3211071570)
            962 STORE_FAST               0 (DIVIDER)
            965 JUMP_ABSOLUTE          980
        >>  968 LOAD_CONST             142 (2115624883)
            971 STORE_FAST               0 (DIVIDER)
            974 JUMP_FORWARD          7612 (to 8589)

====================
error opcode: 'int' object has no attribute '__getitem__'
--> hasjrel 7612 <--
====================

        >>  977 JUMP_FORWARD          2879 (to 3859)

====================
error opcode: 'int' object has no attribute '__getitem__'
--> hasjrel 2879 <--
====================

        >>  980 JUMP_FORWARD          2876 (to 3859)

====================
error opcode: 'int' object has no attribute '__getitem__'
--> hasjrel 2876 <--
====================

            983 LIST_APPEND          24398
            986 YIELD_VALUE         
            987 BUILD_TUPLE          28992
            990 LOAD_ATTR              124
====================
error opcode: 'int' object has no attribute '__getitem__'
--> hasname 124 <--
====================

            993 STOP_CODE           

line : 131
            994 COMPARE_OP               2 (==)
            997 POP_JUMP_IF_TRUE      1018

line : 132
           1000 LOAD_CONST             100 (2394748892)
           1003 LOAD_FAST                0 (DIVIDER)
           1006 COMPARE_OP               2 (==)
           1009 POP_JUMP_IF_TRUE      1021
           1012 LOAD_CONST              62 (737006728)
           1015 JUMP_FORWARD          4797 (to 5815)

====================
error opcode: 'int' object has no attribute '__getitem__'
--> hasjrel 4797 <--
====================

        >> 1018 JUMP_FORWARD          4976 (to 5997)

====================
error opcode: 'int' object has no attribute '__getitem__'
--> hasjrel 4976 <--
====================

        >> 1021 JUMP_FORWARD          6027 (to 7051)

====================
error opcode: 'int' object has no attribute '__getitem__'
--> hasjrel 6027 <--
====================

           1024 PRINT_NEWLINE       

line : 137
           1025 UNARY_INVERT        
           1026 INPLACE_XOR         
           1027 JUMP_IF_FALSE_OR_POP 29050
           1030 SLICE+2             
           1031 DUP_TOP             
        >> 1032 LOAD_CONST              87 (2942560905)
           1035 STORE_FAST               0 (DIVIDER)
           1038 JUMP_ABSOLUTE         1059
        >> 1041 LOAD_CONST              88 (1734941752)
           1044 STORE_FAST               0 (DIVIDER)

line : 138
           1047 JUMP_ABSOLUTE         1062
        >> 1050 LOAD_CONST              89 (2457746969)
           1053 JUMP_ABSOLUTE          737
           1056 JUMP_FORWARD          2800 (to 3859)

====================
error opcode: 'int' object has no attribute '__getitem__'
--> hasjrel 2800 <--
====================

        >> 1059 JUMP_FORWARD          2797 (to 3859)

====================
error opcode: 'int' object has no attribute '__getitem__'
--> hasjrel 2797 <--
====================

        >> 1062 JUMP_FORWARD          2794 (to 3859)

====================
error opcode: 'int' object has no attribute '__getitem__'
--> hasjrel 2794 <--
====================

           1065 MAKE_FUNCTION        13670
           1068 BINARY_XOR          
           1069 CALL_FUNCTION_VAR     2148
           1072 STOP_CODE           
           1073 DUP_TOPX                 2
           1076 JUMP_ABSOLUTE         1095
        >> 1079 STORE_NAME              19 (x)
           1082 LOAD_NAME                0 (a)

line : 144
           1085 LOAD_NAME               19 (x)
           1088 JUMP_ABSOLUTE         1098
        >> 1091 END_FINALLY         
           1092 JUMP_FORWARD          4844 (to 5939)

====================
error opcode: 'int' object has no attribute '__getitem__'
--> hasjrel 4844 <--
====================


line : 149
        >> 1095 JUMP_FORWARD          4213 (to 5311)

====================
error opcode: 'int' object has no attribute '__getitem__'
--> hasjrel 4213 <--
====================

        >> 1098 JUMP_FORWARD          2118 (to 3219)

====================
error opcode: 'int' object has no attribute '__getitem__'
--> hasjrel 2118 <--
====================

           1101 INPLACE_AND         
           1102 BINARY_RSHIFT       
           1103 MAKE_CLOSURE           260
           1106 LOAD_CONST           29574
====================
error opcode: 'int' object has no attribute '__getitem__'
--> hasconst 29574 <--
====================

           1109 POP_JUMP_IF_FALSE    25604
           1112 LOAD_DEREF           31744
           1115 STOP_CODE           
           1116 STOP_CODE           
           1117 COMPARE_OP               2 (==)
           1120 POP_JUMP_IF_TRUE      1141
           1123 LOAD_CONST             139 (3799293923)
           1126 LOAD_FAST                0 (DIVIDER)

line : 194
           1129 COMPARE_OP               2 (==)
           1132 POP_JUMP_IF_TRUE      1144
           1135 JUMP_FORWARD          1667 (to 2805)

====================
error opcode: 'int' object has no attribute '__getitem__'
--> hasjrel 1667 <--
====================


line : 196
           1138 JUMP_FORWARD          5277 (to 6418)

====================
error opcode: 'int' object has no attribute '__getitem__'
--> hasjrel 5277 <--
====================

        >> 1141 JUMP_FORWARD          2464 (to 3608)

====================
error opcode: 'int' object has no attribute '__getitem__'
--> hasjrel 2464 <--
====================

        >> 1144 JUMP_FORWARD          1748 (to 2895)

====================
error opcode: 'int' object has no attribute '__getitem__'
--> hasjrel 1748 <--
====================

           1147 BINARY_OR           
           1148 INPLACE_RSHIFT      
           1149 BINARY_LSHIFT       

line : 197
           1150 BUILD_LIST           35920
           1153 COMPARE_OP           27502
====================
error opcode: 'int' object has no attribute '__getitem__'
--> hascompare 27502 <--
====================

           1156 ROT_TWO             
           1157 STOP_CODE           
           1158 POP_JUMP_IF_TRUE      1185
           1161 LOAD_CONST             137 (3423196735)
           1164 LOAD_FAST                0 (DIVIDER)

line : 198
           1167 COMPARE_OP               2 (==)
           1170 POP_JUMP_IF_TRUE      1188
           1173 LOAD_CONST             116 (2205336485)

line : 203
           1176 LOAD_FAST                0 (DIVIDER)
           1179 COMPARE_OP               2 (==)
           1182 JUMP_FORWARD          2228 (to 3413)

====================
error opcode: 'int' object has no attribute '__getitem__'
--> hasjrel 2228 <--
====================


line : 205
        >> 1185 JUMP_FORWARD          1262 (to 2450)

====================
error opcode: 'int' object has no attribute '__getitem__'
--> hasjrel 1262 <--
====================

        >> 1188 JUMP_FORWARD          5790 (to 6981)

====================
error opcode: 'int' object has no attribute '__getitem__'
--> hasjrel 5790 <--
====================


line : 206
           1191 INPLACE_AND         
           1192 BINARY_POWER        
           1193 INPLACE_MODULO      
           1194 POP_JUMP_IF_TRUE     35853
        >> 1197 LOAD_CONST               8 (1)
           1200 INPLACE_RSHIFT      
           1201 JUMP_ABSOLUTE         1226

line : 207
        >> 1204 LOAD_NAME                0 (a)
           1207 POP_JUMP_IF_FALSE     1229
           1210 JUMP_ABSOLUTE         1232
        >> 1213 LOAD_CONST              22 (99)
           1216 CALL_FUNCTION            2
           1219 GET_ITER            
           1220 JUMP_ABSOLUTE         1235
           1223 JUMP_FORWARD          3474 (to 4700)

====================
error opcode: 'int' object has no attribute '__getitem__'
--> hasjrel 3474 <--
====================

        >> 1226 JUMP_FORWARD          2893 (to 4122)

====================
error opcode: 'int' object has no attribute '__getitem__'
--> hasjrel 2893 <--
====================

        >> 1229 JUMP_FORWARD          3611 (to 4843)

====================
error opcode: 'int' object has no attribute '__getitem__'
--> hasjrel 3611 <--
====================

        >> 1232 JUMP_FORWARD          3590 (to 4825)

====================
error opcode: 'int' object has no attribute '__getitem__'
--> hasjrel 3590 <--
====================

        >> 1235 JUMP_FORWARD          3302 (to 4540)

====================
error opcode: 'int' object has no attribute '__getitem__'
--> hasjrel 3302 <--
====================

           1238 CALL_FUNCTION_VAR    19773
           1241 YIELD_VALUE         
           1242 UNARY_NEGATIVE      
           1243 BINARY_MODULO       
           1244 DUP_TOP             
           1245 CALL_FUNCTION_VAR_KW 22418
           1248 JUMP_ABSOLUTE         1276
        >> 1251 LOAD_CONST              42 (<code object <setcomp> at 0x104be0430, file "ck.py", line 213>)
           1254 MAKE_FUNCTION            0
           1257 LOAD_NAME                9 (xrange)
           1260 JUMP_ABSOLUTE         1279
        >> 1263 POP_TOP             
           1264 LOAD_CONST              45 (<code object u at 0x104be0530, file "ck.py", line 216>)
           1267 MAKE_FUNCTION            0
           1270 STORE_NAME              25 (u)
           1273 JUMP_FORWARD          2500 (to 3776)

====================
error opcode: 'int' object has no attribute '__getitem__'
--> hasjrel 2500 <--
====================

        >> 1276 JUMP_FORWARD          5960 (to 7239)

====================
error opcode: 'int' object has no attribute '__getitem__'
--> hasjrel 5960 <--
====================

        >> 1279 JUMP_FORWARD          2039 (to 3321)

====================
error opcode: 'int' object has no attribute '__getitem__'
--> hasjrel 2039 <--
====================

           1282 BINARY_MULTIPLY     
           1283 ROT_THREE           
           1284 LOAD_GLOBAL          27169
====================
error opcode: 'int' object has no attribute '__getitem__'
--> hasname 27169 <--
====================

        >> 1287 STORE_FAST               0 (DIVIDER)
           1290 JUMP_ABSOLUTE         1317
        >> 1293 LOAD_CONST              63 (2170663152)
           1296 STORE_FAST               0 (DIVIDER)
           1299 JUMP_ABSOLUTE         1320
        >> 1302 LOAD_CONST              64 (2387599675)
           1305 STORE_FAST               0 (DIVIDER)

line : 214
           1308 JUMP_ABSOLUTE         1323
        >> 1311 LOAD_CONST              65 (2036210122)
           1314 JUMP_FORWARD          4201 (to 5518)

====================
error opcode: 'int' object has no attribute '__getitem__'
--> hasjrel 4201 <--
====================

        >> 1317 JUMP_FORWARD          2539 (to 3859)

====================
error opcode: 'int' object has no attribute '__getitem__'
--> hasjrel 2539 <--
====================

        >> 1320 JUMP_FORWARD          2536 (to 3859)

====================
error opcode: 'int' object has no attribute '__getitem__'
--> hasjrel 2536 <--
====================

        >> 1323 JUMP_FORWARD          2533 (to 3859)

====================
error opcode: 'int' object has no attribute '__getitem__'
--> hasjrel 2533 <--
====================

           1326 BINARY_RSHIFT       
           1327 DELETE_FAST           6022
====================
error opcode: 'int' object has no attribute '__getitem__'
--> haslocal 6022 <--
====================

           1330 INPLACE_DIVIDE      
           1331 YIELD_VALUE         
           1332 BUILD_SLICE          29575
           1335 IMPORT_STAR         
           1336 ROT_FOUR            
           1337 LOAD_CONST             162 (701953038)
           1340 LOAD_FAST                0 (DIVIDER)

line : 230
           1343 COMPARE_OP               2 (==)
           1346 POP_JUMP_IF_TRUE      1367
           1349 LOAD_CONST             168 (3750093968)
           1352 LOAD_FAST                0 (DIVIDER)
           1355 COMPARE_OP               2 (==)
           1358 POP_JUMP_IF_TRUE      1370
           1361 JUMP_FORWARD          4117 (to 5481)

====================
error opcode: 'int' object has no attribute '__getitem__'
--> hasjrel 4117 <--
====================

           1364 JUMP_FORWARD          4741 (to 6108)

====================
error opcode: 'int' object has no attribute '__getitem__'
--> hasjrel 4741 <--
====================

        >> 1367 JUMP_ABSOLUTE          265
        >> 1370 JUMP_FORWARD          2137 (to 3510)

====================
error opcode: 'int' object has no attribute '__getitem__'
--> hasjrel 2137 <--
====================

           1373 LOAD_GLOBAL          22084
====================
error opcode: 'int' object has no attribute '__getitem__'
--> hasname 22084 <--
====================

           1376 INPLACE_ADD         
           1377 DELETE_NAME          13851
====================
error opcode: 'int' object has no attribute '__getitem__'
--> hasname 13851 <--
====================

           1380 LOAD_DEREF            2148
           1383 STOP_CODE           
        >> 1384 BINARY_LSHIFT       
           1385 JUMP_ABSOLUTE         1410
        >> 1388 BREAK_LOOP          
           1389 JUMP_ABSOLUTE         1413
           1392 JUMP_ABSOLUTE         1416
        >> 1395 STORE_NAME               0 (a)
           1398 LOAD_CONST               6 (16)
           1401 LOAD_CONST              12 (32)
           1404 BUILD_LIST               2
           1407 JUMP_FORWARD          3366 (to 4776)

====================
error opcode: 'int' object has no attribute '__getitem__'
--> hasjrel 3366 <--
====================

        >> 1410 JUMP_FORWARD          5860 (to 7273)

====================
error opcode: 'int' object has no attribute '__getitem__'
--> hasjrel 5860 <--
====================

        >> 1413 JUMP_FORWARD          7176 (to 8592)

====================
error opcode: 'int' object has no attribute '__getitem__'
--> hasjrel 7176 <--
====================

        >> 1416 JUMP_FORWARD          3424 (to 4843)

====================
error opcode: 'int' object has no attribute '__getitem__'
--> hasjrel 3424 <--
====================

           1419 INPLACE_MODULO      
           1420 INPLACE_TRUE_DIVIDE 
           1421 INPLACE_MODULO      
           1422 BINARY_SUBSCR       
           1423 PRINT_NEWLINE       
           1424 ROT_TWO             
           1425 LOAD_FAST               90
====================
error opcode: 'int' object has no attribute '__getitem__'
--> haslocal 90 <--
====================

           1428 STOP_CODE           
           1429 LOAD_NAME                0 (a)
           1432 LOAD_CONST               8 (1)
           1435 BINARY_POWER        
           1436 JUMP_ABSOLUTE         1445
        >> 1439 POP_TOP             
           1440 POP_TOP             
           1441 POP_TOP             
           1442 JUMP_FORWARD          4577 (to 6022)

====================
error opcode: 'int' object has no attribute '__getitem__'
--> hasjrel 4577 <--
====================

        >> 1445 JUMP_FORWARD          2101 (to 3549)

====================
error opcode: 'int' object has no attribute '__getitem__'
--> hasjrel 2101 <--
====================

           1448 STORE_FAST           33884
====================
error opcode: 'int' object has no attribute '__getitem__'
--> haslocal 33884 <--
====================

           1451 BINARY_SUBSCR       
           1452 SETUP_FINALLY        31879 (to 33334)

====================
error opcode: 'int' object has no attribute '__getitem__'
--> hasjrel 31879 <--
====================

           1455 COMPARE_OP              90
====================
error opcode: 'int' object has no attribute '__getitem__'
--> hascompare 90 <--
====================

           1458 STOP_CODE           
           1459 SETUP_LOOP              25 (to 1487)

====================
error opcode: 'int' object has no attribute '__getitem__'
--> hasjrel 25 <--
====================

           1462 JUMP_ABSOLUTE         1490
        >> 1465 JUMP_ABSOLUTE         1493
        >> 1468 BREAK_LOOP          
           1469 JUMP_ABSOLUTE         1496
           1472 JUMP_ABSOLUTE         1499
        >> 1475 LOAD_CONST              13 (<code object q at 0x104bbdbb0, file "ck.py", line 51>)
           1478 MAKE_FUNCTION            0
           1481 STORE_NAME               5 (q)
           1484 JUMP_FORWARD          1492 (to 2979)

====================
error opcode: 'int' object has no attribute '__getitem__'
--> hasjrel 1492 <--
====================

        >> 1487 JUMP_ABSOLUTE         1465
        >> 1490 JUMP_FORWARD           353 (to 1846)

====================
error opcode: 'int' object has no attribute '__getitem__'
--> hasjrel 353 <--
====================

        >> 1493 JUMP_FORWARD          5743 (to 7239)

====================
error opcode: 'int' object has no attribute '__getitem__'
--> hasjrel 5743 <--
====================

        >> 1496 JUMP_FORWARD          1671 (to 3170)

====================
error opcode: 'int' object has no attribute '__getitem__'
--> hasjrel 1671 <--
====================

        >> 1499 JUMP_FORWARD            62 (to 1564)

====================
error opcode: 'int' object has no attribute '__getitem__'
--> hasjrel 62 <--
====================

           1502 UNARY_POSITIVE      
           1503 POP_BLOCK           
           1504 CALL_FUNCTION        12913
           1507 BUILD_TUPLE          25115
        >> 1510 LOAD_NAME                0 (a)
           1513 LOAD_CONST               8 (1)
           1516 INPLACE_MULTIPLY    
           1517 STORE_NAME               0 (a)
           1520 JUMP_ABSOLUTE         1539
        >> 1523 LOAD_CONST               8 (1)
           1526 INPLACE_ADD         
           1527 STORE_NAME               0 (a)
           1530 JUMP_ABSOLUTE         1542
        >> 1533 MAKE_FUNCTION            0
           1536 JUMP_FORWARD          6467 (to 8006)

====================
error opcode: 'int' object has no attribute '__getitem__'
--> hasjrel 6467 <--
====================

        >> 1539 JUMP_ABSOLUTE           70
        >> 1542 JUMP_FORWARD          5852 (to 7397)

====================
error opcode: 'int' object has no attribute '__getitem__'
--> hasjrel 5852 <--
====================

           1545 RETURN_VALUE        
           1546 BREAK_LOOP          
           1547 DELETE_SLICE+1      
           1548 JUMP_IF_TRUE_OR_POP   2334
           1551 LOAD_CONST            7790
====================
error opcode: 'int' object has no attribute '__getitem__'
--> hasconst 7790 <--
====================

           1554 STOP_CODE           
        >> 1555 LOAD_CONST              50 (4101860005)
           1558 STORE_FAST               0 (DIVIDER)
           1561 JUMP_ABSOLUTE         1588
        >> 1564 LOAD_CONST              51 (527311120)
           1567 STORE_FAST               0 (DIVIDER)
           1570 JUMP_ABSOLUTE         1591
        >> 1573 LOAD_CONST              52 (3638048434)
           1576 STORE_FAST               0 (DIVIDER)
           1579 JUMP_ABSOLUTE         1594
           1582 JUMP_FORWARD          4567 (to 6152)

====================
error opcode: 'int' object has no attribute '__getitem__'
--> hasjrel 4567 <--
====================

           1585 JUMP_FORWARD          6240 (to 7828)

====================
error opcode: 'int' object has no attribute '__getitem__'
--> hasjrel 6240 <--
====================

        >> 1588 JUMP_FORWARD          2268 (to 3859)

====================
error opcode: 'int' object has no attribute '__getitem__'
--> hasjrel 2268 <--
====================

        >> 1591 JUMP_FORWARD          2265 (to 3859)

====================
error opcode: 'int' object has no attribute '__getitem__'
--> hasjrel 2265 <--
====================

        >> 1594 JUMP_FORWARD          2262 (to 3859)

====================
error opcode: 'int' object has no attribute '__getitem__'
--> hasjrel 2262 <--
====================

           1597 LOAD_GLOBAL           7772
====================
error opcode: 'int' object has no attribute '__getitem__'
--> hasname 7772 <--
====================

           1600 INPLACE_XOR         
           1601 MAKE_CLOSURE         29553
           1604 LOAD_CONST           25606
====================
error opcode: 'int' object has no attribute '__getitem__'
--> hasconst 25606 <--
====================

           1607 BUILD_SET            31744
           1610 STOP_CODE           
           1611 STOP_CODE           
           1612 COMPARE_OP               2 (==)
           1615 POP_JUMP_IF_TRUE      1639
           1618 LOAD_CONST             109 (1255663200)
           1621 LOAD_FAST                0 (DIVIDER)
           1624 COMPARE_OP               2 (==)
           1627 POP_JUMP_IF_TRUE      1642
           1630 LOAD_CONST              63 (2170663152)
           1633 JUMP_FORWARD           243 (to 1879)

====================
error opcode: 'int' object has no attribute '__getitem__'
--> hasjrel 243 <--
====================

           1636 JUMP_FORWARD          6856 (to 8495)

====================
error opcode: 'int' object has no attribute '__getitem__'
--> hasjrel 6856 <--
====================

        >> 1639 JUMP_FORWARD          7089 (to 8731)

====================
error opcode: 'int' object has no attribute '__getitem__'
--> hasjrel 7089 <--
====================

        >> 1642 JUMP_FORWARD          3742 (to 5387)

====================
error opcode: 'int' object has no attribute '__getitem__'
--> hasjrel 3742 <--
====================

           1645 IMPORT_STAR         
           1646 DELETE_SLICE+3      
           1647 ROT_FOUR            
           1648 STORE_DEREF          36423
           1651 BINARY_TRUE_DIVIDE  
           1652 DELETE_NAME          53860
====================
error opcode: 'int' object has no attribute '__getitem__'
--> hasname 53860 <--
====================

           1655 STOP_CODE           
           1656 STORE_FAST               0 (DIVIDER)
           1659 JUMP_ABSOLUTE         1683
        >> 1662 LOAD_CONST             211 (3016791946)
           1665 STORE_FAST               0 (DIVIDER)
           1668 JUMP_ABSOLUTE         1686
        >> 1671 LOAD_CONST             212 (3190570824)
           1674 STORE_FAST               0 (DIVIDER)
           1677 JUMP_ABSOLUTE         1689
           1680 JUMP_FORWARD          2176 (to 3859)

====================
error opcode: 'int' object has no attribute '__getitem__'
--> hasjrel 2176 <--
====================

        >> 1683 JUMP_FORWARD          2173 (to 3859)

====================
error opcode: 'int' object has no attribute '__getitem__'
--> hasjrel 2173 <--
====================

        >> 1686 JUMP_FORWARD          2170 (to 3859)

====================
error opcode: 'int' object has no attribute '__getitem__'
--> hasjrel 2170 <--
====================

        >> 1689 JUMP_FORWARD          2167 (to 3859)

====================
error opcode: 'int' object has no attribute '__getitem__'
--> hasjrel 2167 <--
====================

           1692 RAISE_VARARGS        35085
           1695 LOAD_FAST            12926
====================
error opcode: 'int' object has no attribute '__getitem__'
--> haslocal 12926 <--
====================

           1698 UNPACK_SEQUENCE      33636
           1701 STOP_CODE           
           1702 STORE_FAST               0 (DIVIDER)
           1705 JUMP_ABSOLUTE         1732
        >> 1708 LOAD_CONST             132 (3022458678)
           1711 STORE_FAST               0 (DIVIDER)
           1714 JUMP_ABSOLUTE         1735
        >> 1717 LOAD_CONST             133 (639850822)
           1720 STORE_FAST               0 (DIVIDER)
           1723 JUMP_ABSOLUTE         1738
        >> 1726 LOAD_CONST             134 (3060057348)
           1729 JUMP_FORWARD          5526 (to 7258)

====================
error opcode: 'int' object has no attribute '__getitem__'
--> hasjrel 5526 <--
====================

        >> 1732 JUMP_FORWARD          2124 (to 3859)

====================
error opcode: 'int' object has no attribute '__getitem__'
--> hasjrel 2124 <--
====================

        >> 1735 JUMP_FORWARD          2121 (to 3859)

====================
error opcode: 'int' object has no attribute '__getitem__'
--> hasjrel 2121 <--
====================

        >> 1738 JUMP_FORWARD          2118 (to 3859)

====================
error opcode: 'int' object has no attribute '__getitem__'
--> hasjrel 2118 <--
====================

           1741 STORE_SLICE+1       
           1742 BINARY_XOR          
           1743 DELETE_SUBSCR       
           1744 INPLACE_DIVIDE      
           1745 IMPORT_STAR         
           1746 STORE_NAME           23564
====================
error opcode: 'int' object has no attribute '__getitem__'
--> hasname 23564 <--
====================

        >> 1749 LOAD_CONST              66 (2791987114)
           1752 LOAD_FAST                0 (DIVIDER)
           1755 COMPARE_OP               2 (==)
           1758 POP_JUMP_IF_TRUE      1776
           1761 LOAD_CONST             186 (1822186061)
           1764 LOAD_FAST                0 (DIVIDER)
           1767 COMPARE_OP               2 (==)
           1770 POP_JUMP_IF_TRUE      1779
           1773 JUMP_FORWARD          7115 (to 8891)

====================
error opcode: 'int' object has no attribute '__getitem__'
--> hasjrel 7115 <--
====================

        >> 1776 JUMP_FORWARD          2806 (to 4585)

====================
error opcode: 'int' object has no attribute '__getitem__'
--> hasjrel 2806 <--
====================

        >> 1779 JUMP_FORWARD          4288 (to 6070)

====================
error opcode: 'int' object has no attribute '__getitem__'
--> hasjrel 4288 <--
====================

           1782 BUILD_TUPLE          26390
           1785 SETUP_FINALLY        28953 (to 30741)

====================
error opcode: 'int' object has no attribute '__getitem__'
--> hasjrel 28953 <--
====================

           1788 BINARY_SUBSCR       
           1789 <7>                 
        >> 1790 LOAD_NAME                0 (a)
           1793 LOAD_CONST              27 (None)
           1796 LOAD_CONST              27 (None)
           1799 LOAD_CONST              27 (None)
           1802 BUILD_SLICE              3
           1805 JUMP_ABSOLUTE         1820
        >> 1808 LOAD_CONST             170 (3594412375)
           1811 LOAD_FAST                0 (DIVIDER)
           1814 JUMP_ABSOLUTE          870
           1817 JUMP_FORWARD           275 (to 2095)

====================
error opcode: 'int' object has no attribute '__getitem__'
--> hasjrel 275 <--
====================

        >> 1820 JUMP_FORWARD          2203 (to 4026)

====================
error opcode: 'int' object has no attribute '__getitem__'
--> hasjrel 2203 <--
====================

           1823 POP_TOP             
           1824 PRINT_ITEM_TO       
           1825 STOP_CODE           
           1826 MAKE_FUNCTION        14166
           1829 INPLACE_RSHIFT      
           1830 LOAD_CLOSURE           125
           1833 STOP_CODE           
           1834 JUMP_ABSOLUTE         1864
        >> 1837 LOAD_CONST             113 (2841491265)
           1840 STORE_FAST               0 (DIVIDER)
           1843 JUMP_ABSOLUTE         1867
        >> 1846 LOAD_CONST             114 (1478027868)
           1849 STORE_FAST               0 (DIVIDER)
           1852 JUMP_ABSOLUTE         1870
        >> 1855 LOAD_CONST             115 (299054134)
           1858 STORE_FAST               0 (DIVIDER)
           1861 JUMP_ABSOLUTE          396
        >> 1864 JUMP_FORWARD          1992 (to 3859)

====================
error opcode: 'int' object has no attribute '__getitem__'
--> hasjrel 1992 <--
====================

        >> 1867 JUMP_FORWARD          1989 (to 3859)

====================
error opcode: 'int' object has no attribute '__getitem__'
--> hasjrel 1989 <--
====================

        >> 1870 JUMP_FORWARD          1986 (to 3859)

====================
error opcode: 'int' object has no attribute '__getitem__'
--> hasjrel 1986 <--
====================

           1873 CALL_FUNCTION        33387
           1876 BINARY_AND          
           1877 STORE_FAST           31863
====================
error opcode: 'int' object has no attribute '__getitem__'
--> haslocal 31863 <--
====================

           1880 STOP_CODE           
           1881 STOP_CODE           
           1882 COMPARE_OP               2 (==)
           1885 POP_JUMP_IF_TRUE      1909
           1888 LOAD_CONST             174 (764527121)
           1891 LOAD_FAST                0 (DIVIDER)
           1894 COMPARE_OP               2 (==)
           1897 POP_JUMP_IF_TRUE      1912
           1900 LOAD_CONST             180 (707514728)
           1903 LOAD_FAST                0 (DIVIDER)
           1906 JUMP_ABSOLUTE          820
        >> 1909 JUMP_FORWARD           992 (to 2904)

====================
error opcode: 'int' object has no attribute '__getitem__'
--> hasjrel 992 <--
====================

        >> 1912 JUMP_FORWARD          1910 (to 3825)

====================
error opcode: 'int' object has no attribute '__getitem__'
--> hasjrel 1910 <--
====================

           1915 CALL_FUNCTION_KW      2315
           1918 UNARY_NOT           
           1919 BUILD_LIST           30794
        >> 1922 STORE_FAST               0 (DIVIDER)
           1925 JUMP_ABSOLUTE         1955
        >> 1928 LOAD_CONST             149 (1097333569)
           1931 STORE_FAST               0 (DIVIDER)
           1934 JUMP_ABSOLUTE         1958
        >> 1937 LOAD_CONST             150 (156827783)
           1940 STORE_FAST               0 (DIVIDER)
           1943 JUMP_ABSOLUTE         1961
        >> 1946 LOAD_CONST             151 (2180087224)
           1949 STORE_FAST               0 (DIVIDER)
           1952 JUMP_FORWARD           356 (to 2311)

====================
error opcode: 'int' object has no attribute '__getitem__'
--> hasjrel 356 <--
====================

        >> 1955 JUMP_FORWARD          1901 (to 3859)

====================
error opcode: 'int' object has no attribute '__getitem__'
--> hasjrel 1901 <--
====================

        >> 1958 JUMP_FORWARD          1898 (to 3859)

====================
error opcode: 'int' object has no attribute '__getitem__'
--> hasjrel 1898 <--
====================

        >> 1961 JUMP_FORWARD          1895 (to 3859)

====================
error opcode: 'int' object has no attribute '__getitem__'
--> hasjrel 1895 <--
====================

           1964 BUILD_CLASS         
           1965 DUP_TOP             
           1966 INPLACE_AND         
           1967 INPLACE_OR          
           1968 INPLACE_MODULO      
           1969 BINARY_AND          
           1970 SETUP_EXCEPT         27512 (to 29485)

====================
error opcode: 'int' object has no attribute '__getitem__'
--> hasjrel 27512 <--
====================

           1973 ROT_TWO             
           1974 STOP_CODE           
           1975 POP_JUMP_IF_TRUE      2002
           1978 LOAD_CONST              65 (2036210122)
           1981 LOAD_FAST                0 (DIVIDER)
           1984 COMPARE_OP               2 (==)
           1987 POP_JUMP_IF_TRUE      2005
           1990 LOAD_CONST             191 (3514397897)
           1993 LOAD_FAST                0 (DIVIDER)
           1996 COMPARE_OP               2 (==)
           1999 JUMP_ABSOLUTE         1334
        >> 2002 JUMP_FORWARD          1517 (to 3522)

====================
error opcode: 'int' object has no attribute '__getitem__'
--> hasjrel 1517 <--
====================

        >> 2005 JUMP_FORWARD          6244 (to 8252)

====================
error opcode: 'int' object has no attribute '__getitem__'
--> hasjrel 6244 <--
====================

           2008 EXTENDED_ARG         33566
           2011 DUP_TOP             
           2012 STORE_ATTR           2199814965L
====================
error opcode: 'long' object has no attribute '__getitem__'
--> hasname 2199814965 <--
====================

           2015 INPLACE_TRUE_DIVIDE 
           2016 SET_ADD                124
           2019 STOP_CODE           
           2020 COMPARE_OP               2 (==)
           2023 POP_JUMP_IF_TRUE      2044
           2026 LOAD_CONST             166 (194859120)
           2029 LOAD_FAST                0 (DIVIDER)
           2032 COMPARE_OP               2 (==)
           2035 POP_JUMP_IF_TRUE      2047
           2038 LOAD_CONST             140 (3541346917)
           2041 JUMP_FORWARD          2253 (to 4297)

====================
error opcode: 'int' object has no attribute '__getitem__'
--> hasjrel 2253 <--
====================

        >> 2044 JUMP_FORWARD           683 (to 2730)

====================
error opcode: 'int' object has no attribute '__getitem__'
--> hasjrel 683 <--
====================

        >> 2047 JUMP_FORWARD          3349 (to 5399)

====================
error opcode: 'int' object has no attribute '__getitem__'
--> hasjrel 3349 <--
====================

           2050 STORE_SLICE+2       
           2051 RETURN_VALUE        
           2052 INPLACE_AND         
           2053 BUILD_LIST           25714
           2056 <185>                32000
           2059 STOP_CODE           
           2060 STOP_CODE           
           2061 JUMP_ABSOLUTE         2082
        >> 2064 LOAD_CONST             186 (1822186061)
           2067 STORE_FAST               0 (DIVIDER)
           2070 JUMP_ABSOLUTE         2085
        >> 2073 LOAD_CONST             187 (3920111759)
           2076 STORE_FAST               0 (DIVIDER)
           2079 JUMP_FORWARD           479 (to 2561)

====================
error opcode: 'int' object has no attribute '__getitem__'
--> hasjrel 479 <--
====================

        >> 2082 JUMP_FORWARD          1774 (to 3859)

====================
error opcode: 'int' object has no attribute '__getitem__'
--> hasjrel 1774 <--
====================

        >> 2085 JUMP_FORWARD          1771 (to 3859)

====================
error opcode: 'int' object has no attribute '__getitem__'
--> hasjrel 1771 <--
====================

           2088 DELETE_ATTR           7474
====================
error opcode: 'int' object has no attribute '__getitem__'
--> hasname 7474 <--
====================

           2091 STORE_GLOBAL         19825
====================
error opcode: 'int' object has no attribute '__getitem__'
--> hasname 19825 <--
====================

           2094 <8>                 
        >> 2095 LOAD_CONST             182 (2003611733)
           2098 STORE_FAST               0 (DIVIDER)
           2101 JUMP_ABSOLUTE         2128
        >> 2104 LOAD_CONST             183 (3328796971)
           2107 STORE_FAST               0 (DIVIDER)
           2110 JUMP_ABSOLUTE         2131
        >> 2113 LOAD_CONST             184 (2390829607)
           2116 STORE_FAST               0 (DIVIDER)
           2119 JUMP_ABSOLUTE         2134
           2122 JUMP_ABSOLUTE         2055
           2125 JUMP_FORWARD          1731 (to 3859)

====================
error opcode: 'int' object has no attribute '__getitem__'
--> hasjrel 1731 <--
====================

        >> 2128 JUMP_FORWARD          1728 (to 3859)

====================
error opcode: 'int' object has no attribute '__getitem__'
--> hasjrel 1728 <--
====================

        >> 2131 JUMP_FORWARD          1725 (to 3859)

====================
error opcode: 'int' object has no attribute '__getitem__'
--> hasjrel 1725 <--
====================

        >> 2134 JUMP_FORWARD          1722 (to 3859)

====================
error opcode: 'int' object has no attribute '__getitem__'
--> hasjrel 1722 <--
====================

           2137 SLICE+3             
           2138 BINARY_XOR          
           2139 BUILD_SLICE          25688
        >> 2142 POP_JUMP_IF_TRUE      2175
           2145 LOAD_CONST             182 (2003611733)
           2148 LOAD_FAST                0 (DIVIDER)
           2151 COMPARE_OP               2 (==)
           2154 POP_JUMP_IF_TRUE      2178
           2157 LOAD_CONST              97 (353174141)
           2160 LOAD_FAST                0 (DIVIDER)
           2163 COMPARE_OP               2 (==)
           2166 POP_JUMP_IF_TRUE      2181
           2169 LOAD_CONST              72 (319899592)
           2172 JUMP_FORWARD          2817 (to 4992)

====================
error opcode: 'int' object has no attribute '__getitem__'
--> hasjrel 2817 <--
====================

        >> 2175 JUMP_ABSOLUTE         1251
        >> 2178 JUMP_ABSOLUTE          113
        >> 2181 JUMP_FORWARD          4274 (to 6458)

====================
error opcode: 'int' object has no attribute '__getitem__'
--> hasjrel 4274 <--
====================

           2184 BINARY_SUBTRACT     
           2185 SLICE+0             
           2186 INPLACE_LSHIFT      
           2187 DELETE_GLOBAL          372
====================
error opcode: 'int' object has no attribute '__getitem__'
--> hasname 372 <--
====================

           2190 STOP_CODE           
           2191 LOAD_GLOBAL              1 (b)
           2194 LOAD_GLOBAL              1 (b)
           2197 JUMP_ABSOLUTE         2215
        >> 2200 STORE_NAME               0 (a)
           2203 LOAD_NAME                0 (a)
           2206 LOAD_CONST               8 (1)
           2209 JUMP_ABSOLUTE         2218
           2212 JUMP_FORWARD          3172 (to 5387)

====================
error opcode: 'int' object has no attribute '__getitem__'
--> hasjrel 3172 <--
====================

        >> 2215 JUMP_ABSOLUTE         1050
        >> 2218 JUMP_FORWARD          2534 (to 4755)

====================
error opcode: 'int' object has no attribute '__getitem__'
--> hasjrel 2534 <--
====================

           2221 INPLACE_OR          
           2222 DELETE_SLICE+0      
           2223 DUP_TOP             
           2224 STORE_MAP           
           2225 STORE_FAST           10884
====================
error opcode: 'int' object has no attribute '__getitem__'
--> haslocal 10884 <--
====================

           2228 LIST_APPEND            124
           2231 STOP_CODE           
           2232 COMPARE_OP               2 (==)
           2235 POP_JUMP_IF_TRUE      2259
           2238 LOAD_CONST             189 (1705053035)
           2241 LOAD_FAST                0 (DIVIDER)
           2244 COMPARE_OP               2 (==)
           2247 POP_JUMP_IF_TRUE      2262
           2250 LOAD_CONST             172 (751122062)
           2253 LOAD_FAST                0 (DIVIDER)
           2256 JUMP_FORWARD          4650 (to 6909)

====================
error opcode: 'int' object has no attribute '__getitem__'
--> hasjrel 4650 <--
====================

        >> 2259 JUMP_FORWARD          5766 (to 8028)

====================
error opcode: 'int' object has no attribute '__getitem__'
--> hasjrel 5766 <--
====================

        >> 2262 JUMP_FORWARD          2123 (to 4388)

====================
error opcode: 'int' object has no attribute '__getitem__'
--> hasjrel 2123 <--
====================

           2265 LOAD_CLOSURE          1150
           2268 SLICE+1             
           2269 LOAD_CLOSURE         63345
           2272 <8>                 
        >> 2273 JUMP_ABSOLUTE         2298
        >> 2276 INPLACE_ADD         
           2277 STORE_NAME               0 (a)
           2280 JUMP_ABSOLUTE         2301
           2283 JUMP_ABSOLUTE         2304
        >> 2286 LOAD_CONST               9 (2)
           2289 BUILD_LIST               2
           2292 JUMP_ABSOLUTE         1070
           2295 JUMP_ABSOLUTE         1293
        >> 2298 JUMP_FORWARD          5981 (to 8282)

====================
error opcode: 'int' object has no attribute '__getitem__'
--> hasjrel 5981 <--
====================

        >> 2301 JUMP_FORWARD          4917 (to 7221)

====================
error opcode: 'int' object has no attribute '__getitem__'
--> hasjrel 4917 <--
====================

        >> 2304 JUMP_ABSOLUTE          595
           2307 LOAD_DEREF            2700
           2310 CALL_FUNCTION_VAR     9585
           2313 NOP                 
        >> 2314 LOAD_CONST             152 (2380049738)
           2317 STORE_FAST               0 (DIVIDER)
           2320 JUMP_ABSOLUTE         2344
        >> 2323 LOAD_CONST             153 (757045695)
           2326 STORE_FAST               0 (DIVIDER)
           2329 JUMP_ABSOLUTE         2347
        >> 2332 LOAD_CONST             154 (3033067667)
           2335 STORE_FAST               0 (DIVIDER)
           2338 JUMP_FORWARD           857 (to 3198)

====================
error opcode: 'int' object has no attribute '__getitem__'
--> hasjrel 857 <--
====================

           2341 JUMP_FORWARD          1515 (to 3859)

====================
error opcode: 'int' object has no attribute '__getitem__'
--> hasjrel 1515 <--
====================

        >> 2344 JUMP_FORWARD          1512 (to 3859)

====================
error opcode: 'int' object has no attribute '__getitem__'
--> hasjrel 1512 <--
====================

        >> 2347 JUMP_FORWARD          1509 (to 3859)

====================
error opcode: 'int' object has no attribute '__getitem__'
--> hasjrel 1509 <--
====================

           2350 UNARY_POSITIVE      
           2351 SETUP_LOOP           30477 (to 32831)

====================
error opcode: 'int' object has no attribute '__getitem__'
--> hasjrel 30477 <--
====================

        >> 2354 LOAD_CONST              48 (())
           2357 LOAD_CONST              25 (<code object aa at 0x104bbdd30, file "ck.py", line 98>)
           2360 JUMP_ABSOLUTE         2379
        >> 2363 STORE_NAME               0 (a)
           2366 LOAD_NAME                3 (str)
           2369 LOAD_NAME                0 (a)
           2372 JUMP_ABSOLUTE         2382
        >> 2375 BINARY_FLOOR_DIVIDE 
           2376 JUMP_FORWARD          5248 (to 7627)

====================
error opcode: 'int' object has no attribute '__getitem__'
--> hasjrel 5248 <--
====================

        >> 2379 JUMP_ABSOLUTE         2323
        >> 2382 JUMP_FORWARD          2959 (to 5344)

====================
error opcode: 'int' object has no attribute '__getitem__'
--> hasjrel 2959 <--
====================

           2385 JUMP_IF_TRUE_OR_POP   7517
           2388 JUMP_IF_TRUE_OR_POP  29560
           2391 JUMP_ABSOLUTE        25609
           2394 <193>                31744
           2397 STOP_CODE           
           2398 STOP_CODE           
           2399 COMPARE_OP               2 (==)
           2402 POP_JUMP_IF_TRUE      2420
           2405 LOAD_CONST              93 (39021427)
           2408 LOAD_FAST                0 (DIVIDER)
           2411 COMPARE_OP               2 (==)
           2414 JUMP_FORWARD          6552 (to 8969)

====================
error opcode: 'int' object has no attribute '__getitem__'
--> hasjrel 6552 <--
====================

           2417 JUMP_FORWARD          4027 (to 6447)

====================
error opcode: 'int' object has no attribute '__getitem__'
--> hasjrel 4027 <--
====================

        >> 2420 JUMP_ABSOLUTE         1079
           2423 LIST_APPEND          37645
           2426 SLICE+1             
           2427 BINARY_LSHIFT       
           2428 BUILD_TUPLE          39025
           2431 NOP                 
        >> 2432 MAKE_FUNCTION            0
           2435 STORE_NAME               0 (a)
           2438 LOAD_CONST              26 (-1)
           2441 LOAD_CONST              27 (None)
           2444 IMPORT_NAME             17 (marshal)
           2447 JUMP_ABSOLUTE         2459
        >> 2450 LOAD_CONST               8 (1)
           2453 JUMP_ABSOLUTE         1456
           2456 JUMP_ABSOLUTE         1937
        >> 2459 JUMP_FORWARD          4720 (to 7182)

====================
error opcode: 'int' object has no attribute '__getitem__'
--> hasjrel 4720 <--
====================

           2462 CALL_FUNCTION_VAR    18557
           2465 DELETE_FAST          18792
====================
error opcode: 'int' object has no attribute '__getitem__'
--> haslocal 18792 <--
====================

           2468 DUP_TOPX             31840
           2471 STOP_CODE           
           2472 STOP_CODE           
           2473 COMPARE_OP               2 (==)
           2476 POP_JUMP_IF_TRUE      2500
           2479 LOAD_CONST             175 (289120676)
           2482 LOAD_FAST                0 (DIVIDER)
           2485 COMPARE_OP               2 (==)
           2488 POP_JUMP_IF_TRUE      2503
           2491 LOAD_CONST             167 (232569212)
           2494 LOAD_FAST                0 (DIVIDER)
           2497 JUMP_ABSOLUTE         1972
        >> 2500 JUMP_ABSOLUTE         1790
        >> 2503 JUMP_FORWARD          5090 (to 7596)

====================
error opcode: 'int' object has no attribute '__getitem__'
--> hasjrel 5090 <--
====================

           2506 IMPORT_NAME          28236
====================
error opcode: 'int' object has no attribute '__getitem__'
--> hasname 28236 <--
====================

           2509 LOAD_ATTR            26183
====================
error opcode: 'int' object has no attribute '__getitem__'
--> hasname 26183 <--
====================

           2512 INPLACE_XOR         
           2513 SETUP_WITH           37732 (to 40248)

====================
error opcode: 'int' object has no attribute '__getitem__'
--> hasjrel 37732 <--
====================

           2516 STOP_CODE           
           2517 LOAD_FAST                0 (DIVIDER)
           2520 COMPARE_OP               2 (==)
           2523 POP_JUMP_IF_TRUE      2547
           2526 LOAD_CONST             173 (1641571341)
           2529 LOAD_FAST                0 (DIVIDER)
           2532 COMPARE_OP               2 (==)
           2535 POP_JUMP_IF_TRUE      2550
           2538 LOAD_CONST             151 (2180087224)
           2541 LOAD_FAST                0 (DIVIDER)
           2544 JUMP_FORWARD          5159 (to 7706)

====================
error opcode: 'int' object has no attribute '__getitem__'
--> hasjrel 5159 <--
====================

        >> 2547 JUMP_ABSOLUTE          176
        >> 2550 JUMP_FORWARD          5951 (to 8504)

====================
error opcode: 'int' object has no attribute '__getitem__'
--> hasjrel 5951 <--
====================

           2553 SLICE+2             
           2554 DELETE_SLICE+2      
           2555 INPLACE_ADD         
           2556 DELETE_FAST             91
====================
error opcode: 'int' object has no attribute '__getitem__'
--> haslocal 91 <--
====================

           2559 DELETE_SUBSCR       
           2560 LOAD_ATTR             8049
====================
error opcode: 'int' object has no attribute '__getitem__'
--> hasname 8049 <--
====================

           2563 UNARY_POSITIVE      
        >> 2564 LOAD_CONST             188 (261538107)
           2567 STORE_FAST               0 (DIVIDER)
           2570 JUMP_ABSOLUTE         2594
        >> 2573 LOAD_CONST             189 (1705053035)
           2576 STORE_FAST               0 (DIVIDER)
           2579 JUMP_ABSOLUTE         2597
        >> 2582 LOAD_CONST             190 (1304264836)
           2585 STORE_FAST               0 (DIVIDER)
           2588 JUMP_FORWARD          1477 (to 4068)

====================
error opcode: 'int' object has no attribute '__getitem__'
--> hasjrel 1477 <--
====================

           2591 JUMP_FORWARD          1265 (to 3859)

====================
error opcode: 'int' object has no attribute '__getitem__'
--> hasjrel 1265 <--
====================

        >> 2594 JUMP_FORWARD          1262 (to 3859)

====================
error opcode: 'int' object has no attribute '__getitem__'
--> hasjrel 1262 <--
====================

        >> 2597 JUMP_FORWARD          1259 (to 3859)

====================
error opcode: 'int' object has no attribute '__getitem__'
--> hasjrel 1259 <--
====================

           2600 BINARY_AND          
           2601 INPLACE_MODULO      
           2602 DELETE_SLICE+3      
           2603 STORE_SLICE+0       
           2604 BINARY_SUBSCR       
           2605 INPLACE_POWER       
           2606 DELETE_ATTR           6490
====================
error opcode: 'int' object has no attribute '__getitem__'
--> hasname 6490 <--
====================

           2609 LOAD_CONST               8 (1)
           2612 JUMP_ABSOLUTE         2629
        >> 2615 BUILD_SET                1
           2618 POP_TOP             
           2619 BUILD_MAP                0
           2622 POP_TOP             
           2623 JUMP_ABSOLUTE         2632
           2626 JUMP_FORWARD          3470 (to 6099)

====================
error opcode: 'int' object has no attribute '__getitem__'
--> hasjrel 3470 <--
====================

        >> 2629 JUMP_FORWARD          1715 (to 4347)

====================
error opcode: 'int' object has no attribute '__getitem__'
--> hasjrel 1715 <--
====================

        >> 2632 JUMP_ABSOLUTE         2073
           2635 MAKE_CLOSURE         33882
           2638 INPLACE_OR          
           2639 JUMP_IF_FALSE_OR_POP 24410
        >> 2642 JUMP_ABSOLUTE         2669
        >> 2645 LOAD_CONST             104 (3865122074)
           2648 STORE_FAST               0 (DIVIDER)
           2651 JUMP_ABSOLUTE         2672
        >> 2654 LOAD_CONST             105 (4015874589)
           2657 STORE_FAST               0 (DIVIDER)
           2660 JUMP_ABSOLUTE         2675
        >> 2663 LOAD_CONST             106 (3339548061)
           2666 JUMP_FORWARD          2669 (to 5338)

====================
error opcode: 'int' object has no attribute '__getitem__'
--> hasjrel 2669 <--
====================

        >> 2669 JUMP_FORWARD          1187 (to 3859)

====================
error opcode: 'int' object has no attribute '__getitem__'
--> hasjrel 1187 <--
====================

        >> 2672 JUMP_FORWARD          1184 (to 3859)

====================
error opcode: 'int' object has no attribute '__getitem__'
--> hasjrel 1184 <--
====================

        >> 2675 JUMP_FORWARD          1181 (to 3859)

====================
error opcode: 'int' object has no attribute '__getitem__'
--> hasjrel 1181 <--
====================

           2678 INPLACE_AND         
           2679 INPLACE_TRUE_DIVIDE 
           2680 BINARY_FLOOR_DIVIDE 
           2681 LOAD_CLOSURE         30553
           2684 BINARY_AND          
           2685 SET_ADD              38769
           2688 UNARY_POSITIVE      
        >> 2689 MAKE_FUNCTION            0
           2692 CALL_FUNCTION            0
           2695 BUILD_CLASS         
           2696 STORE_GLOBAL             8 (aa)
           2699 LOAD_GLOBAL              8 (aa)
           2702 JUMP_ABSOLUTE         2714
        >> 2705 STORE_NAME               0 (a)
           2708 JUMP_FORWARD          3349 (to 6060)

====================
error opcode: 'int' object has no attribute '__getitem__'
--> hasjrel 3349 <--
====================

           2711 JUMP_FORWARD          4507 (to 7221)

====================
error opcode: 'int' object has no attribute '__getitem__'
--> hasjrel 4507 <--
====================

        >> 2714 JUMP_FORWARD           435 (to 3152)

====================
error opcode: 'int' object has no attribute '__getitem__'
--> hasjrel 435 <--
====================

           2717 POP_JUMP_IF_TRUE     28958
           2720 SET_ADD               6258
           2723 SETUP_FINALLY          612 (to 3338)

====================
error opcode: 'int' object has no attribute '__getitem__'
--> hasjrel 612 <--
====================

           2726 STOP_CODE           
           2727 JUMP_ABSOLUTE         2747
        >> 2730 POP_BLOCK           
           2731 LOAD_CONST              27 (None)
           2734 JUMP_ABSOLUTE         2750
        >> 2737 LOAD_NAME                0 (a)
           2740 LOAD_CONST               8 (1)
           2743 BINARY_DIVIDE       
           2744 JUMP_ABSOLUTE         2429
        >> 2747 JUMP_FORWARD           460 (to 3210)

====================
error opcode: 'int' object has no attribute '__getitem__'
--> hasjrel 460 <--
====================

        >> 2750 JUMP_ABSOLUTE         2104
           2753 COMPARE_OP           34385
====================
error opcode: 'int' object has no attribute '__getitem__'
--> hascompare 34385 <--
====================

           2756 POP_BLOCK           
           2757 YIELD_VALUE         
           2758 STORE_MAP           
           2759 BUILD_TUPLE          29011
           2762 <201>                29706
           2765 INPLACE_OR          
           2766 PRINT_EXPR          
           2767 SETUP_EXCEPT         59505 (to 62275)

====================
error opcode: 'int' object has no attribute '__getitem__'
--> hasjrel 59505 <--
====================

           2770 UNARY_POSITIVE      
        >> 2771 LOAD_NAME                0 (a)
           2774 LOAD_CONST               8 (1)
           2777 INPLACE_SUBTRACT    
           2778 STORE_NAME               0 (a)
           2781 JUMP_ABSOLUTE         2795
        >> 2784 LOAD_NAME                0 (a)
           2787 UNARY_NOT           
           2788 POP_TOP             
           2789 JUMP_FORWARD          2316 (to 5108)

====================
error opcode: 'int' object has no attribute '__getitem__'
--> hasjrel 2316 <--
====================

           2792 JUMP_FORWARD          1754 (to 4549)

====================
error opcode: 'int' object has no attribute '__getitem__'
--> hasjrel 1754 <--
====================

        >> 2795 JUMP_ABSOLUTE         1699
           2798 FOR_ITER             10499 (to 13300)

====================
error opcode: 'int' object has no attribute '__getitem__'
--> hasjrel 10499 <--
====================

           2801 INPLACE_AND         
           2802 DELETE_FAST          32343
====================
error opcode: 'int' object has no attribute '__getitem__'
--> haslocal 32343 <--
====================

        >> 2805 LOAD_CONST             106 (3339548061)
           2808 LOAD_FAST                0 (DIVIDER)
           2811 COMPARE_OP               2 (==)
           2814 POP_JUMP_IF_TRUE      2835
           2817 LOAD_CONST             133 (639850822)
           2820 LOAD_FAST                0 (DIVIDER)
           2823 COMPARE_OP               2 (==)
           2826 POP_JUMP_IF_TRUE      2838
           2829 LOAD_CONST             201 (454425221)
           2832 JUMP_ABSOLUTE         2229
        >> 2835 JUMP_ABSOLUTE         1475
        >> 2838 JUMP_ABSOLUTE          278
           2841 BINARY_DIVIDE       
           2842 CALL_FUNCTION_VAR_KW 37251
        >> 2845 POP_JUMP_IF_TRUE      2875
           2848 LOAD_CONST              59 (2957893970)
           2851 LOAD_FAST                0 (DIVIDER)
           2854 COMPARE_OP               2 (==)
           2857 POP_JUMP_IF_TRUE      2878
           2860 LOAD_CONST             197 (3063339773)
           2863 LOAD_FAST                0 (DIVIDER)
           2866 COMPARE_OP               2 (==)
           2869 POP_JUMP_IF_TRUE      2881
           2872 JUMP_FORWARD          4871 (to 7746)

====================
error opcode: 'int' object has no attribute '__getitem__'
--> hasjrel 4871 <--
====================

        >> 2875 JUMP_ABSOLUTE          452
        >> 2878 JUMP_FORWARD          2163 (to 5044)

====================
error opcode: 'int' object has no attribute '__getitem__'
--> hasjrel 2163 <--
====================

        >> 2881 JUMP_ABSOLUTE         1468
           2884 ROT_FOUR            
           2885 DELETE_SLICE+0      
           2886 PRINT_ITEM_TO       
           2887 STORE_SLICE+1       
           2888 STORE_FAST            2585
====================
error opcode: 'int' object has no attribute '__getitem__'
--> haslocal 2585 <--
====================

           2891 EXTENDED_ARG         26481
           2894 UNARY_NEGATIVE      
        >> 2895 JUMP_FORWARD         1735458840L (to 1735461738L)

====================
error opcode: 'long' object has no attribute '__getitem__'
--> hasjrel 1735458840 <--
====================

           2898 JUMP_ABSOLUTE         2925
        >> 2901 JUMP_ABSOLUTE         2928
        >> 2904 STORE_NAME              10 (OO00000O0O0OO0OOO)
           2907 LOAD_NAME               10 (OO00000O0O0OO0OOO)
           2910 LIST_APPEND              2
           2913 JUMP_ABSOLUTE         2931
           2916 JUMP_FORWARD          4592 (to 7511)

====================
error opcode: 'int' object has no attribute '__getitem__'
--> hasjrel 4592 <--
====================

           2919 JUMP_FORWARD           239 (to 3161)

====================
error opcode: 'int' object has no attribute '__getitem__'
--> hasjrel 239 <--
====================

        >> 2922 JUMP_ABSOLUTE         2901
        >> 2925 JUMP_FORWARD          3798 (to 6726)

====================
error opcode: 'int' object has no attribute '__getitem__'
--> hasjrel 3798 <--
====================

        >> 2928 JUMP_FORWARD          3795 (to 6726)

====================
error opcode: 'int' object has no attribute '__getitem__'
--> hasjrel 3795 <--
====================

        >> 2931 JUMP_FORWARD          1606 (to 4540)

====================
error opcode: 'int' object has no attribute '__getitem__'
--> hasjrel 1606 <--
====================

           2934 POP_BLOCK           
           2935 DELETE_NAME          24872
====================
error opcode: 'int' object has no attribute '__getitem__'
--> hasname 24872 <--
====================

        >> 2938 COMPARE_OP               2 (==)
           2941 POP_JUMP_IF_TRUE      2968
           2944 LOAD_CONST             155 (304842234)
           2947 LOAD_FAST                0 (DIVIDER)
           2950 COMPARE_OP               2 (==)
           2953 POP_JUMP_IF_TRUE      2971
           2956 LOAD_CONST             209 (4029948115)
           2959 LOAD_FAST                0 (DIVIDER)
           2962 COMPARE_OP               2 (==)
           2965 JUMP_FORWARD          5176 (to 8144)

====================
error opcode: 'int' object has no attribute '__getitem__'
--> hasjrel 5176 <--
====================

        >> 2968 JUMP_ABSOLUTE          191
        >> 2971 JUMP_FORWARD          1283 (to 4257)

====================
error opcode: 'int' object has no attribute '__getitem__'
--> hasjrel 1283 <--
====================

           2974 EXTENDED_ARG         18782
           2977 BINARY_DIVIDE       
           2978 RAISE_VARARGS        1230945905L
           2981 UNARY_NEGATIVE      
        >> 2982 STORE_NAME              17 (marshal)
           2985 LOAD_NAME                7 (True)
           2988 POP_JUMP_IF_FALSE     3009
           2991 JUMP_ABSOLUTE         3012
        >> 2994 LOAD_NAME                9 (xrange)
           2997 LOAD_CONST               8 (1)
           3000 LOAD_CONST              41 (10)
           3003 JUMP_FORWARD          3819 (to 6825)

====================
error opcode: 'int' object has no attribute '__getitem__'
--> hasjrel 3819 <--
====================

           3006 JUMP_FORWARD          2153 (to 5162)

====================
error opcode: 'int' object has no attribute '__getitem__'
--> hasjrel 2153 <--
====================

        >> 3009 JUMP_FORWARD          3714 (to 6726)

====================
error opcode: 'int' object has no attribute '__getitem__'
--> hasjrel 3714 <--
====================

        >> 3012 JUMP_FORWARD          1125 (to 4140)

====================
error opcode: 'int' object has no attribute '__getitem__'
--> hasjrel 1125 <--
====================

           3015 ROT_TWO             
           3016 ROT_FOUR            
           3017 SETUP_FINALLY        18057 (to 21077)

====================
error opcode: 'int' object has no attribute '__getitem__'
--> hasjrel 18057 <--
====================

           3020 UNPACK_SEQUENCE      29533
           3023 <233>                25611
           3026 EXTENDED_ARG         31744
           3029 STOP_CODE           
           3030 STOP_CODE           
           3031 COMPARE_OP           2080374786L
====================
error opcode: 'long' object has no attribute '__getitem__'
--> hascompare 2080374786 <--
====================

           3034 POP_JUMP_IF_TRUE      3052
           3037 LOAD_CONST             126 (3553638271)
           3040 LOAD_FAST                0 (DIVIDER)
           3043 COMPARE_OP               2 (==)
           3046 JUMP_ABSOLUTE          533
           3049 JUMP_FORWARD           593 (to 3645)

====================
error opcode: 'int' object has no attribute '__getitem__'
--> hasjrel 593 <--
====================

        >> 3052 JUMP_FORWARD          3156 (to 6211)

====================
error opcode: 'int' object has no attribute '__getitem__'
--> hasjrel 3156 <--
====================

           3055 UNARY_POSITIVE      
           3056 INPLACE_POWER       
           3057 DELETE_FAST          28040
====================
error opcode: 'int' object has no attribute '__getitem__'
--> haslocal 28040 <--
====================

        >> 3060 LOAD_FAST                0 (DIVIDER)
           3063 COMPARE_OP               2 (==)
           3066 POP_JUMP_IF_TRUE      3093
           3069 LOAD_CONST             125 (1350279058)
           3072 LOAD_FAST                0 (DIVIDER)
           3075 COMPARE_OP               2 (==)
           3078 POP_JUMP_IF_TRUE      3096
           3081 LOAD_CONST             179 (3620421833)
           3084 LOAD_FAST                0 (DIVIDER)
           3087 COMPARE_OP               2 (==)
           3090 JUMP_ABSOLUTE         1603
        >> 3093 JUMP_FORWARD          2156 (to 5252)

====================
error opcode: 'int' object has no attribute '__getitem__'
--> hasjrel 2156 <--
====================

        >> 3096 JUMP_FORWARD          2769 (to 5868)

====================
error opcode: 'int' object has no attribute '__getitem__'
--> hasjrel 2769 <--
====================

           3099 BINARY_XOR          
           3100 EXEC_STMT           
           3101 BINARY_AND          
           3102 MAKE_FUNCTION        16497
           3105 UNARY_NOT           
        >> 3106 LOAD_CONST             170 (3594412375)
           3109 STORE_FAST               0 (DIVIDER)
           3112 JUMP_ABSOLUTE         3139
        >> 3115 LOAD_CONST             171 (2908258129)
           3118 STORE_FAST               0 (DIVIDER)
           3121 JUMP_ABSOLUTE         3142
        >> 3124 LOAD_CONST             172 (751122062)
           3127 STORE_FAST               0 (DIVIDER)
           3130 JUMP_ABSOLUTE         3145
           3133 JUMP_FORWARD          4692 (to 7828)

====================
error opcode: 'int' object has no attribute '__getitem__'
--> hasjrel 4692 <--
====================

           3136 JUMP_FORWARD           720 (to 3859)

====================
error opcode: 'int' object has no attribute '__getitem__'
--> hasjrel 720 <--
====================

        >> 3139 JUMP_FORWARD           717 (to 3859)

====================
error opcode: 'int' object has no attribute '__getitem__'
--> hasjrel 717 <--
====================

        >> 3142 JUMP_FORWARD           714 (to 3859)

====================
error opcode: 'int' object has no attribute '__getitem__'
--> hasjrel 714 <--
====================

        >> 3145 JUMP_FORWARD           711 (to 3859)

====================
error opcode: 'int' object has no attribute '__getitem__'
--> hasjrel 711 <--
====================

           3148 LOAD_ATTR            27757
====================
error opcode: 'int' object has no attribute '__getitem__'
--> hasname 27757 <--
====================

           3151 IMPORT_FROM          19044
====================
error opcode: 'int' object has no attribute '__getitem__'
--> hasname 19044 <--
====================

           3154 STOP_CODE           
           3155 STORE_FAST               0 (DIVIDER)
           3158 JUMP_ABSOLUTE         3185
        >> 3161 LOAD_CONST              75 (847064203)
           3164 STORE_FAST               0 (DIVIDER)
           3167 JUMP_ABSOLUTE         3188
        >> 3170 LOAD_CONST              76 (558516932)
           3173 STORE_FAST               0 (DIVIDER)
           3176 JUMP_ABSOLUTE         3191
        >> 3179 LOAD_CONST              77 (3571241703)
           3182 JUMP_FORWARD          1546 (to 4731)

====================
error opcode: 'int' object has no attribute '__getitem__'
--> hasjrel 1546 <--
====================

        >> 3185 JUMP_FORWARD           671 (to 3859)

====================
error opcode: 'int' object has no attribute '__getitem__'
--> hasjrel 671 <--
====================

        >> 3188 JUMP_FORWARD           668 (to 3859)

====================
error opcode: 'int' object has no attribute '__getitem__'
--> hasjrel 668 <--
====================

        >> 3191 JUMP_FORWARD           665 (to 3859)

====================
error opcode: 'int' object has no attribute '__getitem__'
--> hasjrel 665 <--
====================

           3194 BINARY_OR           
           3195 BUILD_CLASS         
           3196 EXEC_STMT           
           3197 SETUP_LOOP           39281 (to 42481)

====================
error opcode: 'int' object has no attribute '__getitem__'
--> hasjrel 39281 <--
====================

           3200 UNARY_NOT           
        >> 3201 LOAD_CONST             155 (304842234)
           3204 STORE_FAST               0 (DIVIDER)
           3207 JUMP_ABSOLUTE         3228
        >> 3210 LOAD_CONST             156 (1412035677)
           3213 STORE_FAST               0 (DIVIDER)
           3216 JUMP_ABSOLUTE         3231
        >> 3219 LOAD_CONST             157 (3462530290)
           3222 JUMP_FORWARD           795 (to 4020)

====================
error opcode: 'int' object has no attribute '__getitem__'
--> hasjrel 795 <--
====================

           3225 JUMP_FORWARD           631 (to 3859)

====================
error opcode: 'int' object has no attribute '__getitem__'
--> hasjrel 631 <--
====================

        >> 3228 JUMP_FORWARD           628 (to 3859)

====================
error opcode: 'int' object has no attribute '__getitem__'
--> hasjrel 628 <--
====================

        >> 3231 JUMP_FORWARD           625 (to 3859)

====================
error opcode: 'int' object has no attribute '__getitem__'
--> hasjrel 625 <--
====================

           3234 BINARY_FLOOR_DIVIDE 
           3235 LOAD_ATTR            34179
====================
error opcode: 'int' object has no attribute '__getitem__'
--> hasname 34179 <--
====================

           3238 STORE_NAME             350
====================
error opcode: 'int' object has no attribute '__getitem__'
--> hasname 350 <--
====================

           3241 LOAD_CONST              10 ('6')
           3244 JUMP_ABSOLUTE         3265
        >> 3247 LOAD_NAME                7 (True)
           3250 POP_JUMP_IF_FALSE     3268
           3253 JUMP_ABSOLUTE         3271
        >> 3256 LOAD_NAME                2 (int)
           3259 LOAD_CONST              11 ('1024')
           3262 JUMP_FORWARD          3060 (to 6325)

====================
error opcode: 'int' object has no attribute '__getitem__'
--> hasjrel 3060 <--
====================

        >> 3265 JUMP_FORWARD          3886 (to 7154)

====================
error opcode: 'int' object has no attribute '__getitem__'
--> hasjrel 3886 <--
====================

        >> 3268 JUMP_FORWARD          4108 (to 7379)

====================
error opcode: 'int' object has no attribute '__getitem__'
--> hasjrel 4108 <--
====================

        >> 3271 JUMP_FORWARD           955 (to 4229)

====================
error opcode: 'int' object has no attribute '__getitem__'
--> hasjrel 955 <--
====================

           3274 NOP                 
           3275 INPLACE_MODULO      
           3276 ROT_FOUR            
           3277 INPLACE_RSHIFT      
           3278 POP_BLOCK           
           3279 CALL_FUNCTION          869
           3282 STOP_CODE           
           3283 LOAD_NAME                0 (a)
           3286 JUMP_ABSOLUTE         3303
        >> 3289 POP_BLOCK           
           3290 JUMP_ABSOLUTE         3306
        >> 3293 LOAD_NAME               15 (False)
           3296 JUMP_ABSOLUTE         3309
        >> 3299 POP_BLOCK           
           3300 JUMP_FORWARD          3745 (to 7048)

====================
error opcode: 'int' object has no attribute '__getitem__'
--> hasjrel 3745 <--
====================

        >> 3303 JUMP_ABSOLUTE         1662
        >> 3306 JUMP_ABSOLUTE         1726
        >> 3309 JUMP_ABSOLUTE         1032
           3312 POP_TOP             
           3313 SLICE+3             
           3314 INPLACE_MULTIPLY    
           3315 END_FINALLY         
           3316 INPLACE_POWER       
           3317 BUILD_LIST            6001
           3320 UNARY_CONVERT       
        >> 3321 LOAD_CONST             125 (1350279058)
           3324 STORE_FAST               0 (DIVIDER)
           3327 JUMP_ABSOLUTE         3354
        >> 3330 LOAD_CONST             126 (3553638271)
           3333 STORE_FAST               0 (DIVIDER)
           3336 JUMP_ABSOLUTE         3357
        >> 3339 LOAD_CONST             127 (3833384562)
           3342 STORE_FAST               0 (DIVIDER)
           3345 JUMP_ABSOLUTE         3360
           3348 JUMP_FORWARD          4922 (to 8273)

====================
error opcode: 'int' object has no attribute '__getitem__'
--> hasjrel 4922 <--
====================

           3351 JUMP_FORWARD           505 (to 3859)

====================
error opcode: 'int' object has no attribute '__getitem__'
--> hasjrel 505 <--
====================

        >> 3354 JUMP_FORWARD           502 (to 3859)

====================
error opcode: 'int' object has no attribute '__getitem__'
--> hasjrel 502 <--
====================

        >> 3357 JUMP_FORWARD           499 (to 3859)

====================
error opcode: 'int' object has no attribute '__getitem__'
--> hasjrel 499 <--
====================

        >> 3360 JUMP_FORWARD           496 (to 3859)

====================
error opcode: 'int' object has no attribute '__getitem__'
--> hasjrel 496 <--
====================

           3363 BINARY_FLOOR_DIVIDE 
           3364 CALL_FUNCTION_KW     33375
           3367 DELETE_GLOBAL        22885
====================
error opcode: 'int' object has no attribute '__getitem__'
--> hasname 22885 <--
====================

           3370 INPLACE_LSHIFT      
           3371 SETUP_FINALLY          619 (to 3993)

====================
error opcode: 'int' object has no attribute '__getitem__'
--> hasjrel 619 <--
====================

           3374 STOP_CODE           
           3375 POP_JUMP_IF_TRUE      3402
           3378 LOAD_CONST             165 (2763014243)
           3381 LOAD_FAST                0 (DIVIDER)
           3384 COMPARE_OP               2 (==)
           3387 POP_JUMP_IF_TRUE      3405
           3390 LOAD_CONST             185 (3362438832)
           3393 LOAD_FAST                0 (DIVIDER)
           3396 COMPARE_OP               2 (==)
           3399 JUMP_FORWARD          1510 (to 4912)

====================
error opcode: 'int' object has no attribute '__getitem__'
--> hasjrel 1510 <--
====================

        >> 3402 JUMP_FORWARD           387 (to 3792)

====================
error opcode: 'int' object has no attribute '__getitem__'
--> hasjrel 387 <--
====================

        >> 3405 JUMP_FORWARD          4959 (to 8367)

====================
error opcode: 'int' object has no attribute '__getitem__'
--> hasjrel 4959 <--
====================

           3408 BUILD_LIST           31327
           3411 BINARY_AND          
           3412 BUILD_LIST           30323
           3415 UNARY_CONVERT       
           3416 LOAD_CONST             120 (3866484190)
           3419 LOAD_FAST                0 (DIVIDER)
           3422 COMPARE_OP               2 (==)
           3425 POP_JUMP_IF_TRUE      3449
           3428 LOAD_CONST             148 (1418979794)
           3431 LOAD_FAST                0 (DIVIDER)
           3434 COMPARE_OP               2 (==)
           3437 POP_JUMP_IF_TRUE      3452
           3440 LOAD_CONST              80 (7676377)
           3443 JUMP_ABSOLUTE          991
           3446 JUMP_FORWARD           955 (to 4404)

====================
error opcode: 'int' object has no attribute '__getitem__'
--> hasjrel 955 <--
====================

        >> 3449 JUMP_FORWARD          3611 (to 7063)

====================
error opcode: 'int' object has no attribute '__getitem__'
--> hasjrel 3611 <--
====================

        >> 3452 JUMP_FORWARD          4619 (to 8074)

====================
error opcode: 'int' object has no attribute '__getitem__'
--> hasjrel 4619 <--
====================

           3455 YIELD_VALUE         
           3456 INPLACE_RSHIFT      
           3457 BINARY_SUBSCR       
           3458 JUMP_IF_FALSE_OR_POP   619
           3461 STOP_CODE           
           3462 POP_JUMP_IF_TRUE      3489
           3465 LOAD_CONST             103 (3797321274)
           3468 LOAD_FAST                0 (DIVIDER)
           3471 COMPARE_OP               2 (==)
           3474 POP_JUMP_IF_TRUE      3492
           3477 LOAD_CONST             101 (349119919)
           3480 LOAD_FAST                0 (DIVIDER)
           3483 COMPARE_OP               2 (==)
           3486 JUMP_FORWARD          3938 (to 7427)

====================
error opcode: 'int' object has no attribute '__getitem__'
--> hasjrel 3938 <--
====================

        >> 3489 JUMP_ABSOLUTE         2432
        >> 3492 JUMP_ABSOLUTE         3256
           3495 DELETE_SLICE+3      
           3496 CONTINUE_LOOP        24373
           3499 BINARY_MULTIPLY     
           3500 STORE_SUBSCR        
           3501 POP_JUMP_IF_FALSE    24075
        >> 3504 LOAD_CONST               8 (1)
           3507 JUMP_ABSOLUTE         3529
        >> 3510 LOAD_NAME                3 (str)
           3513 LOAD_NAME                0 (a)
           3516 CALL_FUNCTION            1
           3519 JUMP_ABSOLUTE         3532
        >> 3522 POP_TOP             
           3523 LOAD_NAME                0 (a)
           3526 JUMP_ABSOLUTE          785
        >> 3529 JUMP_FORWARD          5069 (to 8601)

====================
error opcode: 'int' object has no attribute '__getitem__'
--> hasjrel 5069 <--
====================

        >> 3532 JUMP_FORWARD          4396 (to 7931)

====================
error opcode: 'int' object has no attribute '__getitem__'
--> hasjrel 4396 <--
====================

           3535 INPLACE_RSHIFT      
           3536 CALL_FUNCTION_VAR    22550
           3539 LOAD_NAME            28992
====================
error opcode: 'int' object has no attribute '__getitem__'
--> hasname 28992 <--
====================

           3542 BUILD_SLICE            125
           3545 STOP_CODE           
           3546 JUMP_ABSOLUTE         3576
        >> 3549 LOAD_CONST             167 (232569212)
           3552 STORE_FAST               0 (DIVIDER)
           3555 JUMP_ABSOLUTE         3579
        >> 3558 LOAD_CONST             168 (3750093968)
           3561 STORE_FAST               0 (DIVIDER)
           3564 JUMP_ABSOLUTE         3582
        >> 3567 LOAD_CONST             169 (4173236901)
           3570 STORE_FAST               0 (DIVIDER)
           3573 JUMP_ABSOLUTE         3103
        >> 3576 JUMP_FORWARD           280 (to 3859)

====================
error opcode: 'int' object has no attribute '__getitem__'
--> hasjrel 280 <--
====================

        >> 3579 JUMP_FORWARD           277 (to 3859)

====================
error opcode: 'int' object has no attribute '__getitem__'
--> hasjrel 277 <--
====================

        >> 3582 JUMP_FORWARD           274 (to 3859)

====================
error opcode: 'int' object has no attribute '__getitem__'
--> hasjrel 274 <--
====================

           3585 MAKE_CLOSURE         17939
           3588 POP_BLOCK           
           3589 UNPACK_SEQUENCE       8817
           3592 <14>                
        >> 3593 LOAD_CONST              10 ('6')
           3596 LOAD_CONST              10 ('6')
           3599 BUILD_LIST               3
           3602 STORE_NAME               0 (a)
           3605 JUMP_ABSOLUTE         3621
        >> 3608 POP_TOP             
           3609 LOAD_NAME                0 (a)
           3612 LOAD_CONST               2 (0)
           3615 JUMP_ABSOLUTE         2608
           3618 JUMP_ABSOLUTE         1555
        >> 3621 JUMP_FORWARD          1520 (to 5144)

====================
error opcode: 'int' object has no attribute '__getitem__'
--> hasjrel 1520 <--
====================

           3624 CALL_FUNCTION_KW     18285
           3627 PRINT_EXPR          
           3628 JUMP_IF_FALSE_OR_POP 36723
           3631 STORE_NAME             130
====================
error opcode: 'int' object has no attribute '__getitem__'
--> hasname 130 <--
====================

           3634 STOP_CODE           
           3635 POP_BLOCK           
           3636 JUMP_FORWARD            22 (to 3661)

====================
error opcode: 'int' object has no attribute '__getitem__'
--> hasjrel 22 <--
====================

           3639 JUMP_ABSOLUTE         3664
        >> 3642 JUMP_ABSOLUTE         3667
        >> 3645 LOAD_ATTR                1 (b)
           3648 POP_TOP             
           3649 LOAD_NAME                0 (a)
           3652 LOAD_NAME                0 (a)
           3655 JUMP_ABSOLUTE         3670
           3658 JUMP_FORWARD          2786 (to 6447)

====================
error opcode: 'int' object has no attribute '__getitem__'
--> hasjrel 2786 <--
====================

        >> 3661 JUMP_ABSOLUTE         3642
        >> 3664 JUMP_ABSOLUTE          577
        >> 3667 JUMP_ABSOLUTE          916
        >> 3670 JUMP_FORWARD          4600 (to 8273)

====================
error opcode: 'int' object has no attribute '__getitem__'
--> hasjrel 4600 <--
====================

           3673 BINARY_RSHIFT       
           3674 BUILD_LIST           28219
           3677 BREAK_LOOP          
           3678 DELETE_SUBSCR       
           3679 UNARY_NOT           
           3680 JUMP_IF_FALSE_OR_POP 25722
           3683 <187>                31744
           3686 STOP_CODE           
           3687 STOP_CODE           
           3688 COMPARE_OP               2 (==)
           3691 POP_JUMP_IF_TRUE      3715
           3694 LOAD_CONST             198 (1582782904)
           3697 LOAD_FAST                0 (DIVIDER)
           3700 COMPARE_OP               2 (==)
           3703 POP_JUMP_IF_TRUE      3718
           3706 LOAD_CONST             111 (515513602)
           3709 LOAD_FAST                0 (DIVIDER)
           3712 JUMP_ABSOLUTE         1155
        >> 3715 JUMP_FORWARD          2503 (to 6221)

====================
error opcode: 'int' object has no attribute '__getitem__'
--> hasjrel 2503 <--
====================

        >> 3718 JUMP_FORWARD          3033 (to 6754)

====================
error opcode: 'int' object has no attribute '__getitem__'
--> hasjrel 3033 <--
====================

           3721 LOAD_LOCALS         
           3722 LOAD_DEREF           33562
           3725 BUILD_TUPLE          32060
        >> 3728 STORE_NAME               0 (a)
           3731 CONTINUE_LOOP         3756
           3734 JUMP_ABSOLUTE         3759
        >> 3737 END_FINALLY         
           3738 JUMP_ABSOLUTE         3762
        >> 3741 STORE_NAME              12 (OO000OOO0O000O00O)
           3744 LOAD_CONST              26 (-1)
           3747 LOAD_CONST              28 (('time',))
           3750 JUMP_ABSOLUTE         3765
           3753 JUMP_FORWARD          4611 (to 8367)

====================
error opcode: 'int' object has no attribute '__getitem__'
--> hasjrel 4611 <--
====================

        >> 3756 JUMP_FORWARD          4833 (to 8592)

====================
error opcode: 'int' object has no attribute '__getitem__'
--> hasjrel 4833 <--
====================

        >> 3759 JUMP_ABSOLUTE          907
        >> 3762 JUMP_ABSOLUTE         2314
        >> 3765 JUMP_FORWARD          4069 (to 7837)

====================
error opcode: 'int' object has no attribute '__getitem__'
--> hasjrel 4069 <--
====================

           3768 STORE_SLICE+3       
           3769 STORE_FAST           28490
====================
error opcode: 'int' object has no attribute '__getitem__'
--> haslocal 28490 <--
====================

           3772 INPLACE_MULTIPLY    
           3773 PRINT_EXPR          
           3774 BUILD_MAP            29073
           3777 <220>                25614
           3780 <8>                 
           3781 STOP_CODE           
           3782 LOAD_NAME                0 (a)
           3785 LOAD_CONST               8 (1)
           3788 STORE_SUBSCR        
           3789 JUMP_ABSOLUTE         3807
        >> 3792 LOAD_NAME                0 (a)
           3795 CALL_FUNCTION            1
           3798 LOAD_CONST               8 (1)
           3801 JUMP_ABSOLUTE         1786
           3804 JUMP_ABSOLUTE          925
        >> 3807 JUMP_FORWARD          3326 (to 7136)

====================
error opcode: 'int' object has no attribute '__getitem__'
--> hasjrel 3326 <--
====================

           3810 INPLACE_TRUE_DIVIDE 
           3811 LOAD_GLOBAL          37719
====================
error opcode: 'int' object has no attribute '__getitem__'
--> hasname 37719 <--
====================

           3814 SETUP_FINALLY        33916 (to 37733)

====================
error opcode: 'int' object has no attribute '__getitem__'
--> hasjrel 33916 <--
====================

           3817 STOP_CODE           
           3818 STOP_CODE           
           3819 STORE_NAME               0 (a)
           3822 JUMP_ABSOLUTE         3844
        >> 3825 IMPORT_NAME             13 (time)
           3828 IMPORT_FROM             13 (time)
           3831 STORE_NAME              14 (OO0OO00O0OO0OO00O)
           3834 POP_TOP             
           3835 JUMP_ABSOLUTE         3847
        >> 3838 STORE_GLOBAL             1 (b)
           3841 JUMP_ABSOLUTE         2188
        >> 3844 JUMP_FORWARD          4075 (to 7922)

====================
error opcode: 'int' object has no attribute '__getitem__'
--> hasjrel 4075 <--
====================

        >> 3847 JUMP_FORWARD          2867 (to 6717)

====================
error opcode: 'int' object has no attribute '__getitem__'
--> hasjrel 2867 <--
====================

           3850 DUP_TOP             
           3851 EXTENDED_ARG         24915
           3854 BINARY_OR           
           3855 DELETE_SLICE+3      
           3856 BINARY_MODULO       
           3857 STORE_SLICE+2       
           3858 EXTENDED_ARG         1632834158L
           3861 STOP_CODE           
        >> 3862 POP_BLOCK           
           3863 JUMP_FORWARD         107009419378705L (to 107009419382571L)

====================
error opcode: 'long' object has no attribute '__getitem__'
--> hasjrel 107009419378705 <--
====================

           3866 JUMP_ABSOLUTE         3886
        >> 3869 JUMP_ABSOLUTE         3889
        >> 3872 CALL_FUNCTION            1
           3875 SLICE+0             
           3876 POP_TOP             
           3877 JUMP_ABSOLUTE         3280
           3880 JUMP_ABSOLUTE         1808
        >> 3883 JUMP_ABSOLUTE         3869
        >> 3886 JUMP_ABSOLUTE         1555
        >> 3889 JUMP_ABSOLUTE         2314
           3892 BINARY_AND          
           3893 DELETE_NAME          24145
====================
error opcode: 'int' object has no attribute '__getitem__'
--> hasname 24145 <--
====================

           3896 JUMP_ABSOLUTE        16668
           3899 SETUP_FINALLY          619 (to 4521)

====================
error opcode: 'int' object has no attribute '__getitem__'
--> hasjrel 619 <--
====================

           3902 STOP_CODE           
           3903 POP_JUMP_IF_TRUE      3927
           3906 LOAD_CONST              76 (558516932)
           3909 LOAD_FAST                0 (DIVIDER)
           3912 COMPARE_OP               2 (==)
           3915 POP_JUMP_IF_TRUE      3930
           3918 LOAD_CONST              67 (663319258)
           3921 LOAD_FAST                0 (DIVIDER)
           3924 JUMP_FORWARD           691 (to 4618)

====================
error opcode: 'int' object has no attribute '__getitem__'
--> hasjrel 691 <--
====================

        >> 3927 JUMP_ABSOLUTE         2705
        >> 3930 JUMP_FORWARD          2166 (to 6099)

====================
error opcode: 'int' object has no attribute '__getitem__'
--> hasjrel 2166 <--
====================

           3933 PRINT_EXPR          
           3934 PRINT_ITEM_TO       
           3935 INPLACE_ADD         
           3936 JUMP_ABSOLUTE        31859
           3939 UNARY_INVERT        
           3940 LOAD_CONST             146 (3573687990)
           3943 LOAD_FAST                0 (DIVIDER)
           3946 COMPARE_OP               2 (==)
           3949 POP_JUMP_IF_TRUE      3967
           3952 LOAD_CONST             134 (3060057348)
           3955 LOAD_FAST                0 (DIVIDER)
           3958 COMPARE_OP               2 (==)
           3961 JUMP_ABSOLUTE         2142
           3964 JUMP_FORWARD          1647 (to 5614)

====================
error opcode: 'int' object has no attribute '__getitem__'
--> hasjrel 1647 <--
====================

        >> 3967 JUMP_FORWARD          4231 (to 8201)

====================
error opcode: 'int' object has no attribute '__getitem__'
--> hasjrel 4231 <--
====================

           3970 PRINT_NEWLINE       
           3971 LOAD_NAME              571
====================
error opcode: 'int' object has no attribute '__getitem__'
--> hasname 571 <--
====================

           3974 SET_ADD              22081
           3977 DELETE_ATTR          29544
====================
error opcode: 'int' object has no attribute '__getitem__'
--> hasname 29544 <--
====================

           3980 <166>                25615
           3983 DELETE_SLICE+1      
           3984 STOP_CODE           
           3985 LOAD_FAST                0 (DIVIDER)
           3988 COMPARE_OP               2 (==)
           3991 POP_JUMP_IF_TRUE      4009
           3994 LOAD_CONST              74 (3657237552)
           3997 LOAD_FAST                0 (DIVIDER)
           4000 COMPARE_OP               2 (==)
           4003 JUMP_ABSOLUTE         3022
           4006 JUMP_FORWARD           424 (to 4433)

====================
error opcode: 'int' object has no attribute '__getitem__'
--> hasjrel 424 <--
====================

        >> 4009 JUMP_ABSOLUTE          448
           4012 IMPORT_NAME           7763
====================
error opcode: 'int' object has no attribute '__getitem__'
--> hasname 7763 <--
====================

           4015 INPLACE_SUBTRACT    
           4016 ROT_THREE           
           4017 STORE_DEREF          34103
        >> 4020 STORE_FAST               0 (DIVIDER)
           4023 JUMP_ABSOLUTE         4050
        >> 4026 LOAD_CONST             158 (2617511990)
           4029 STORE_FAST               0 (DIVIDER)
           4032 JUMP_ABSOLUTE         4053
        >> 4035 LOAD_CONST             159 (3698725459)
           4038 STORE_FAST               0 (DIVIDER)
           4041 JUMP_ABSOLUTE         4056
        >> 4044 LOAD_CONST             160 (1556037817)
           4047 JUMP_FORWARD           164 (to 4214)

====================
error opcode: 'int' object has no attribute '__getitem__'
--> hasjrel 164 <--
====================

        >> 4050 JUMP_ABSOLUTE         3859
        >> 4053 JUMP_ABSOLUTE         3859
        >> 4056 JUMP_ABSOLUTE         3859
           4059 RAISE_VARARGS        16918
           4062 INPLACE_RSHIFT      
           4063 SLICE+1             
           4064 STORE_MAP           
           4065 PRINT_NEWLINE_TO    
           4066 EXEC_STMT           
           4067 STORE_ATTR            1393
====================
error opcode: 'int' object has no attribute '__getitem__'
--> hasname 1393 <--
====================

           4070 <16>                
        >> 4071 LOAD_CONST             191 (3514397897)
           4074 STORE_FAST               0 (DIVIDER)
           4077 JUMP_ABSOLUTE         4104
        >> 4080 LOAD_CONST             192 (3002923223)
           4083 STORE_FAST               0 (DIVIDER)
           4086 JUMP_ABSOLUTE         4107
        >> 4089 LOAD_CONST             193 (1852662022)
           4092 STORE_FAST               0 (DIVIDER)
           4095 JUMP_ABSOLUTE         4110
           4098 JUMP_FORWARD          3278 (to 7379)

====================
error opcode: 'int' object has no attribute '__getitem__'
--> hasjrel 3278 <--
====================

           4101 JUMP_ABSOLUTE         3859
        >> 4104 JUMP_ABSOLUTE         3859
        >> 4107 JUMP_ABSOLUTE         3859
        >> 4110 JUMP_ABSOLUTE         3859
           4113 BINARY_XOR          
           4114 STORE_SLICE+3       
           4115 LOAD_NAME            26983
====================
error opcode: 'int' object has no attribute '__getitem__'
--> hasname 26983 <--
====================

           4118 BINARY_SUBSCR       
           4119 YIELD_VALUE         
           4120 DELETE_SLICE+3      
           4121 JUMP_IF_FALSE_OR_POP 35172
           4124 STOP_CODE           
           4125 STORE_FAST               0 (DIVIDER)
           4128 JUMP_ABSOLUTE         4152
        >> 4131 LOAD_CONST             138 (2232366503)
           4134 STORE_FAST               0 (DIVIDER)
           4137 JUMP_ABSOLUTE         4155
        >> 4140 LOAD_CONST             139 (3799293923)
           4143 STORE_FAST               0 (DIVIDER)
           4146 JUMP_ABSOLUTE         4158
           4149 JUMP_ABSOLUTE          950
        >> 4152 JUMP_ABSOLUTE         3859
        >> 4155 JUMP_ABSOLUTE         3859
        >> 4158 JUMP_ABSOLUTE         3859
           4161 LOAD_CLOSURE         18785
           4164 STORE_NAME             619
====================
error opcode: 'int' object has no attribute '__getitem__'
--> hasname 619 <--
====================

           4167 STOP_CODE           
           4168 POP_JUMP_IF_TRUE      4198
           4171 LOAD_CONST             107 (4225593240)
           4174 LOAD_FAST                0 (DIVIDER)
           4177 COMPARE_OP               2 (==)
           4180 POP_JUMP_IF_TRUE      4201
           4183 LOAD_CONST             149 (1097333569)
           4186 LOAD_FAST                0 (DIVIDER)
           4189 COMPARE_OP               2 (==)
           4192 POP_JUMP_IF_TRUE      4204
           4195 JUMP_ABSOLUTE          211
        >> 4198 JUMP_FORWARD          4215 (to 8416)

====================
error opcode: 'int' object has no attribute '__getitem__'
--> hasjrel 4215 <--
====================

        >> 4201 JUMP_ABSOLUTE         3872
        >> 4204 JUMP_FORWARD          1533 (to 5740)

====================
error opcode: 'int' object has no attribute '__getitem__'
--> hasjrel 1533 <--
====================

           4207 UNARY_INVERT        
           4208 STORE_NAME           13387
====================
error opcode: 'int' object has no attribute '__getitem__'
--> hasname 13387 <--
====================

           4211 STOP_CODE           
           4212 FOR_ITER             32094 (to 36309)

====================
error opcode: 'int' object has no attribute '__getitem__'
--> hasjrel 32094 <--
====================

           4215 STOP_CODE           
           4216 STOP_CODE           
           4217 JUMP_ABSOLUTE         4241
        >> 4220 LOAD_CONST             161 (3030036581)
           4223 STORE_FAST               0 (DIVIDER)
           4226 JUMP_ABSOLUTE         4244
        >> 4229 LOAD_CONST             162 (701953038)
           4232 STORE_FAST               0 (DIVIDER)
           4235 JUMP_ABSOLUTE         4247
           4238 JUMP_FORWARD          2932 (to 7173)

====================
error opcode: 'int' object has no attribute '__getitem__'
--> hasjrel 2932 <--
====================

        >> 4241 JUMP_ABSOLUTE         3859
        >> 4244 JUMP_ABSOLUTE         3859
        >> 4247 JUMP_ABSOLUTE         3859
           4250 UNARY_POSITIVE      
           4251 BUILD_SET            27989
        >> 4254 JUMP_ABSOLUTE         4282
        >> 4257 LOAD_CONST               5 ('0xbaadf00d')
           4260 LOAD_CONST               6 (16)
           4263 CALL_FUNCTION            2
           4266 STORE_NAME               0 (a)
           4269 LOAD_NAME                0 (a)
           4272 JUMP_ABSOLUTE         4285
        >> 4275 POP_BLOCK           
           4276 JUMP_ABSOLUTE         4288
           4279 JUMP_ABSOLUTE         3632
        >> 4282 JUMP_FORWARD          3381 (to 7666)

====================
error opcode: 'int' object has no attribute '__getitem__'
--> hasjrel 3381 <--
====================

        >> 4285 JUMP_FORWARD          2942 (to 7230)

====================
error opcode: 'int' object has no attribute '__getitem__'
--> hasjrel 2942 <--
====================

        >> 4288 JUMP_ABSOLUTE           52
           4291 DELETE_FAST           3430
====================
error opcode: 'int' object has no attribute '__getitem__'
--> haslocal 3430 <--
====================

           4294 END_FINALLY         
           4295 LOAD_LOCALS         
           4296 MAKE_FUNCTION          124
           4299 STOP_CODE           
           4300 COMPARE_OP               2 (==)
           4303 POP_JUMP_IF_TRUE      4324
           4306 LOAD_CONST             128 (3607436366)
           4309 LOAD_FAST                0 (DIVIDER)
           4312 COMPARE_OP               2 (==)
           4315 POP_JUMP_IF_TRUE      4327
           4318 LOAD_CONST             141 (3211071570)
           4321 JUMP_ABSOLUTE         2470
        >> 4324 JUMP_ABSOLUTE         2784
        >> 4327 JUMP_FORWARD          2974 (to 7304)

====================
error opcode: 'int' object has no attribute '__getitem__'
--> hasjrel 2974 <--
====================

           4330 BINARY_LSHIFT       
           4331 SLICE+2             
           4332 STOP_CODE           
           4333 BREAK_LOOP          
           4334 COMPARE_OP            4209
====================
error opcode: 'int' object has no attribute '__getitem__'
--> hascompare 4209 <--
====================

           4337 <17>                
        >> 4338 LOAD_CONST             207 (4252175081)
           4341 STORE_FAST               0 (DIVIDER)
           4344 JUMP_ABSOLUTE         4371
        >> 4347 LOAD_CONST             208 (3353002622)
           4350 STORE_FAST               0 (DIVIDER)
           4353 JUMP_ABSOLUTE         4374
        >> 4356 LOAD_CONST             209 (4029948115)
           4359 STORE_FAST               0 (DIVIDER)
           4362 JUMP_ABSOLUTE         4377
           4365 JUMP_ABSOLUTE         1653
           4368 JUMP_ABSOLUTE         3859
        >> 4371 JUMP_ABSOLUTE         3859
        >> 4374 JUMP_ABSOLUTE         3859
        >> 4377 JUMP_ABSOLUTE         3859
           4380 ROT_THREE           
           4381 WITH_CLEANUP        
           4382 INPLACE_MODULO      
           4383 POP_BLOCK           
           4384 LOAD_DEREF           14449
           4387 <17>                
        >> 4388 LOAD_CONST               8 (1)
           4391 LOAD_CONST              26 (-1)
           4394 CALL_FUNCTION            3
           4397 GET_ITER            
           4398 CALL_FUNCTION            1
           4401 JUMP_ABSOLUTE         4411
        >> 4404 UNARY_INVERT        
           4405 JUMP_ABSOLUTE         1426
           4408 JUMP_ABSOLUTE         3201
        >> 4411 JUMP_FORWARD          2141 (to 6555)

====================
error opcode: 'int' object has no attribute '__getitem__'
--> hasjrel 2141 <--
====================

           4414 PRINT_NEWLINE       
           4415 CALL_FUNCTION        29722
           4418 STORE_SLICE+3       
           4419 BINARY_RSHIFT       
           4420 BINARY_MODULO       
           4421 SET_ADD              13956
           4424 STORE_NAME              24 (kwargs)
           4427 LOAD_NAME                0 (a)
           4430 JUMP_ABSOLUTE         4447
        >> 4433 LOAD_NAME                0 (a)
           4436 POP_TOP             
           4437 LOAD_NAME                0 (a)
           4440 BUILD_TUPLE              1
           4443 POP_TOP             
           4444 JUMP_ABSOLUTE          173
        >> 4447 JUMP_ABSOLUTE         1708
           4450 BINARY_MODULO       
           4451 IMPORT_STAR         
           4452 DELETE_SLICE+1      
           4453 RAISE_VARARGS        25887
        >> 4456 STORE_FAST               0 (DIVIDER)
           4459 JUMP_ABSOLUTE         4483
        >> 4462 LOAD_CONST              96 (1993617135)
           4465 STORE_FAST               0 (DIVIDER)
           4468 JUMP_ABSOLUTE         4486
        >> 4471 LOAD_CONST              97 (353174141)
           4474 STORE_FAST               0 (DIVIDER)
           4477 JUMP_ABSOLUTE         4489
           4480 JUMP_ABSOLUTE          907
        >> 4483 JUMP_ABSOLUTE         3859
        >> 4486 JUMP_ABSOLUTE         3859
        >> 4489 JUMP_ABSOLUTE         3859
           4492 INPLACE_OR          
           4493 COMPARE_OP           25202
====================
error opcode: 'int' object has no attribute '__getitem__'
--> hascompare 25202 <--
====================

        >> 4496 LOAD_CONST               8 (1)
           4499 BINARY_MODULO       
           4500 POP_TOP             
           4501 JUMP_ABSOLUTE         4520
        >> 4504 JUMP_FORWARD            16 (to 4523)

====================
error opcode: 'int' object has no attribute '__getitem__'
--> hasjrel 16 <--
====================

           4507 JUMP_ABSOLUTE         4526
        >> 4510 JUMP_ABSOLUTE         4529
        >> 4513 POP_TOP             
           4514 LOAD_CONST               8 (1)
           4517 JUMP_FORWARD          1682 (to 6202)

====================
error opcode: 'int' object has no attribute '__getitem__'
--> hasjrel 1682 <--
====================

        >> 4520 JUMP_FORWARD          3152 (to 7675)

====================
error opcode: 'int' object has no attribute '__getitem__'
--> hasjrel 3152 <--
====================

        >> 4523 JUMP_ABSOLUTE         4510
        >> 4526 JUMP_FORWARD          1650 (to 6179)

====================
error opcode: 'int' object has no attribute '__getitem__'
--> hasjrel 1650 <--
====================

        >> 4529 JUMP_FORWARD          1647 (to 6179)

====================
error opcode: 'int' object has no attribute '__getitem__'
--> hasjrel 1647 <--
====================

           4532 BINARY_OR           
           4533 BINARY_OR           
           4534 DELETE_ATTR          23625
====================
error opcode: 'int' object has no attribute '__getitem__'
--> hasname 23625 <--
====================

        >> 4537 JUMP_ABSOLUTE         4564
        >> 4540 LOAD_CONST             110 (2030276895)
           4543 STORE_FAST               0 (DIVIDER)
           4546 JUMP_ABSOLUTE         4567
        >> 4549 LOAD_CONST             111 (515513602)
           4552 STORE_FAST               0 (DIVIDER)
           4555 JUMP_ABSOLUTE         4570
        >> 4558 LOAD_CONST             112 (3872518049)
           4561 JUMP_ABSOLUTE         1831
        >> 4564 JUMP_ABSOLUTE         3859
        >> 4567 JUMP_ABSOLUTE         3859
        >> 4570 JUMP_ABSOLUTE         3859
           4573 ROT_TWO             
           4574 LOAD_DEREF           22662
           4577 IMPORT_NAME          25711
====================
error opcode: 'int' object has no attribute '__getitem__'
--> hasname 25711 <--
====================

           4580 <8>                 
           4581 STOP_CODE           
           4582 JUMP_ABSOLUTE         4607
        >> 4585 LOAD_NAME                0 (a)
           4588 LOAD_CONST               8 (1)
           4591 LOAD_CONST               9 (2)
           4594 DELETE_SLICE+3      
           4595 BUILD_MAP                1
           4598 JUMP_ABSOLUTE         4610
        >> 4601 LOAD_NAME               15 (False)
           4604 JUMP_ABSOLUTE         3728
        >> 4607 JUMP_FORWARD           591 (to 5201)

====================
error opcode: 'int' object has no attribute '__getitem__'
--> hasjrel 591 <--
====================

        >> 4610 JUMP_ABSOLUTE         2113
           4613 ROT_FOUR            
           4614 STOP_CODE           
           4615 JUMP_IF_FALSE_OR_POP 30833
        >> 4618 COMPARE_OP               2 (==)
           4621 POP_JUMP_IF_TRUE      4648
           4624 LOAD_CONST             169 (4173236901)
           4627 LOAD_FAST                0 (DIVIDER)
           4630 COMPARE_OP               2 (==)
           4633 POP_JUMP_IF_TRUE      4651
           4636 LOAD_CONST              50 (4101860005)
           4639 LOAD_FAST                0 (DIVIDER)
           4642 COMPARE_OP               2 (==)
           4645 JUMP_FORWARD          3445 (to 8093)

====================
error opcode: 'int' object has no attribute '__getitem__'
--> hasjrel 3445 <--
====================

        >> 4648 JUMP_ABSOLUTE          793
        >> 4651 JUMP_FORWARD          1982 (to 6636)

====================
error opcode: 'int' object has no attribute '__getitem__'
--> hasjrel 1982 <--
====================

           4654 STORE_GLOBAL         23164
====================
error opcode: 'int' object has no attribute '__getitem__'
--> hasname 23164 <--
====================

           4657 DELETE_NAME          27927
====================
error opcode: 'int' object has no attribute '__getitem__'
--> hasname 27927 <--
====================

        >> 4660 LOAD_CONST             205 (3585746886)
           4663 LOAD_FAST                0 (DIVIDER)
           4666 COMPARE_OP               2 (==)
           4669 POP_JUMP_IF_TRUE      4690
           4672 LOAD_CONST              85 (2977686067)
           4675 LOAD_FAST                0 (DIVIDER)
           4678 COMPARE_OP               2 (==)
           4681 POP_JUMP_IF_TRUE      4693
           4684 LOAD_CONST             153 (757045695)
           4687 JUMP_FORWARD          2406 (to 7096)

====================
error opcode: 'int' object has no attribute '__getitem__'
--> hasjrel 2406 <--
====================

        >> 4690 JUMP_FORWARD          2821 (to 7514)

====================
error opcode: 'int' object has no attribute '__getitem__'
--> hasjrel 2821 <--
====================

        >> 4693 JUMP_ABSOLUTE         2994
           4696 DELETE_NAME           7811
====================
error opcode: 'int' object has no attribute '__getitem__'
--> hasname 7811 <--
====================

           4699 CALL_FUNCTION_VAR_KW   643
           4702 STOP_CODE           
           4703 GET_ITER            
           4704 JUMP_ABSOLUTE         4721
        >> 4707 ROT_THREE           
           4708 ROT_TWO             
           4709 STORE_GLOBAL             1 (b)
           4712 STORE_GLOBAL             1 (b)
           4715 JUMP_ABSOLUTE         4724
           4718 JUMP_ABSOLUTE         1247
        >> 4721 JUMP_ABSOLUTE         4462
        >> 4724 JUMP_FORWARD          3119 (to 7846)

====================
error opcode: 'int' object has no attribute '__getitem__'
--> hasjrel 3119 <--
====================

           4727 IMPORT_FROM          21640
====================
error opcode: 'int' object has no attribute '__getitem__'
--> hasname 21640 <--
====================

           4730 SET_ADD                125
           4733 STOP_CODE           
           4734 JUMP_ABSOLUTE         4761
        >> 4737 LOAD_CONST              78 (2430228901)
           4740 STORE_FAST               0 (DIVIDER)
           4743 JUMP_ABSOLUTE         4764
        >> 4746 LOAD_CONST              79 (1977354003)
           4749 STORE_FAST               0 (DIVIDER)
           4752 JUMP_ABSOLUTE         4767
        >> 4755 LOAD_CONST              80 (7676377)
           4758 JUMP_FORWARD           526 (to 5287)

====================
error opcode: 'int' object has no attribute '__getitem__'
--> hasjrel 526 <--
====================

        >> 4761 JUMP_ABSOLUTE         3859
        >> 4764 JUMP_ABSOLUTE         3859
        >> 4767 JUMP_ABSOLUTE         3859
           4770 CONTINUE_LOOP        10314
           4773 STORE_DEREF          28482
        >> 4776 STORE_NAME               0 (a)
           4779 JUMP_ABSOLUTE         4807
        >> 4782 POP_TOP             
           4783 LOAD_CONST               2 (0)
           4786 JUMP_IF_TRUE_OR_POP   4810
           4789 JUMP_ABSOLUTE         4813
        >> 4792 LOAD_NAME                0 (a)
           4795 CALL_FUNCTION            1
           4798 LOAD_CONST               8 (1)
           4801 LOAD_CONST               9 (2)
           4804 JUMP_FORWARD          2494 (to 7301)

====================
error opcode: 'int' object has no attribute '__getitem__'
--> hasjrel 2494 <--
====================

        >> 4807 JUMP_ABSOLUTE         3179
        >> 4810 JUMP_ABSOLUTE         2055
        >> 4813 JUMP_ABSOLUTE         1928
           4816 GET_ITER            
           4817 INPLACE_RSHIFT      
           4818 DUP_TOP             
           4819 CALL_FUNCTION_VAR_KW 34109
        >> 4822 JUMP_ABSOLUTE         4855
        >> 4825 LOAD_CONST             201 (454425221)
           4828 STORE_FAST               0 (DIVIDER)
           4831 JUMP_ABSOLUTE         4858
        >> 4834 LOAD_CONST             202 (3391917192)
           4837 STORE_FAST               0 (DIVIDER)
           4840 JUMP_ABSOLUTE         4861
        >> 4843 LOAD_CONST             203 (2801322355)
           4846 STORE_FAST               0 (DIVIDER)
           4849 JUMP_ABSOLUTE         4864
           4852 JUMP_FORWARD          2811 (to 7666)

====================
error opcode: 'int' object has no attribute '__getitem__'
--> hasjrel 2811 <--
====================

        >> 4855 JUMP_ABSOLUTE         3859
        >> 4858 JUMP_ABSOLUTE         3859
        >> 4861 JUMP_ABSOLUTE         3859
        >> 4864 JUMP_ABSOLUTE         3859
           4867 DELETE_GLOBAL         7233
====================
error opcode: 'int' object has no attribute '__getitem__'
--> hasname 7233 <--
====================

           4870 INPLACE_FLOOR_DIVIDE
           4871 STORE_NAME            9073
====================
error opcode: 'int' object has no attribute '__getitem__'
--> hasname 9073 <--
====================

           4874 BINARY_POWER        
        >> 4875 LOAD_CONST              93 (39021427)
           4878 STORE_FAST               0 (DIVIDER)
           4881 JUMP_ABSOLUTE         4902
        >> 4884 LOAD_CONST              94 (1270056785)
           4887 STORE_FAST               0 (DIVIDER)
           4890 JUMP_ABSOLUTE         4905
        >> 4893 LOAD_CONST              95 (2469373957)
           4896 JUMP_ABSOLUTE         4456
           4899 JUMP_ABSOLUTE         3859
        >> 4902 JUMP_ABSOLUTE         3859
        >> 4905 JUMP_ABSOLUTE         3859
           4908 DELETE_SLICE+3      
           4909 STORE_MAP           
           4910 UNARY_INVERT        
           4911 LOAD_CONST           19315
====================
error opcode: 'int' object has no attribute '__getitem__'
--> hasconst 19315 <--
====================

           4914 BINARY_POWER        
           4915 LOAD_CONST             124 (1218866617)
           4918 LOAD_FAST                0 (DIVIDER)
           4921 COMPARE_OP               2 (==)
           4924 POP_JUMP_IF_TRUE      4942
           4927 LOAD_CONST             200 (3303908731)
           4930 LOAD_FAST                0 (DIVIDER)
           4933 COMPARE_OP               2 (==)
           4936 JUMP_FORWARD           627 (to 5566)

====================
error opcode: 'int' object has no attribute '__getitem__'
--> hasjrel 627 <--
====================

           4939 JUMP_FORWARD          3435 (to 8377)

====================
error opcode: 'int' object has no attribute '__getitem__'
--> hasjrel 3435 <--
====================

        >> 4942 JUMP_ABSOLUTE           95
           4945 STORE_MAP           
           4946 CALL_FUNCTION_KW     25454
           4949 JUMP_IF_FALSE_OR_POP 31875
           4952 STOP_CODE           
           4953 STOP_CODE           
           4954 COMPARE_OP               2 (==)
           4957 POP_JUMP_IF_TRUE      4978
           4960 LOAD_CONST              70 (3472840527)
           4963 LOAD_FAST                0 (DIVIDER)
           4966 COMPARE_OP               2 (==)
           4969 POP_JUMP_IF_TRUE      4981
           4972 LOAD_CONST              55 (473125748)
           4975 JUMP_ABSOLUTE         3060
        >> 4978 JUMP_ABSOLUTE         1263
        >> 4981 JUMP_FORWARD          2336 (to 7320)

====================
error opcode: 'int' object has no attribute '__getitem__'
--> hasjrel 2336 <--
====================

           4984 BINARY_SUBSCR       
           4985 IMPORT_FROM           3361
====================
error opcode: 'int' object has no attribute '__getitem__'
--> hasname 3361 <--
====================

           4988 STORE_SUBSCR        
           4989 DELETE_NAME          23687
====================
error opcode: 'int' object has no attribute '__getitem__'
--> hasname 23687 <--
====================

        >> 4992 LOAD_FAST                0 (DIVIDER)
           4995 COMPARE_OP               2 (==)
           4998 POP_JUMP_IF_TRUE      5025
           5001 LOAD_CONST             118 (935379986)
           5004 LOAD_FAST                0 (DIVIDER)
           5007 COMPARE_OP               2 (==)
           5010 POP_JUMP_IF_TRUE      5028
           5013 LOAD_CONST             190 (1304264836)
           5016 LOAD_FAST                0 (DIVIDER)
           5019 COMPARE_OP               2 (==)
           5022 JUMP_FORWARD          3650 (to 8675)

====================
error opcode: 'int' object has no attribute '__getitem__'
--> hasjrel 3650 <--
====================

        >> 5025 JUMP_FORWARD          1003 (to 6031)

====================
error opcode: 'int' object has no attribute '__getitem__'
--> hasjrel 1003 <--
====================

        >> 5028 JUMP_ABSOLUTE         4504
           5031 RETURN_VALUE        
           5032 DELETE_NAME           7298
====================
error opcode: 'int' object has no attribute '__getitem__'
--> hasname 7298 <--
====================

           5035 INPLACE_MODULO      
           5036 DELETE_SUBSCR       
           5037 UNARY_CONVERT       
           5038 DELETE_ATTR            358
====================
error opcode: 'int' object has no attribute '__getitem__'
--> hasname 358 <--
====================

           5041 JUMP_ABSOLUTE         5059
        >> 5044 POP_TOP             
           5045 LOAD_CONST              27 (None)
           5048 RETURN_VALUE        
        >> 5049 LOAD_NAME               24 (kwargs)
           5052 CALL_FUNCTION_KW         0
           5055 POP_TOP             
           5056 JUMP_FORWARD          1689 (to 6748)

====================
error opcode: 'int' object has no attribute '__getitem__'
--> hasjrel 1689 <--
====================

        >> 5059 JUMP_ABSOLUTE         3558
           5062 DUP_TOPX             29782
           5065 BINARY_MODULO       
           5066 INPLACE_MODULO      
           5067 BUILD_SET            23098
        >> 5070 LOAD_CONST               8 (1)
           5073 DELETE_SLICE+1      
           5074 LOAD_NAME                0 (a)
           5077 LOAD_CONST               9 (2)
           5080 DELETE_SLICE+2      
           5081 JUMP_ABSOLUTE         5093
        >> 5084 STORE_NAME               4 (i)
           5087 JUMP_ABSOLUTE         5096
           5090 JUMP_ABSOLUTE         2892
        >> 5093 JUMP_FORWARD           428 (to 5524)

====================
error opcode: 'int' object has no attribute '__getitem__'
--> hasjrel 428 <--
====================

        >> 5096 JUMP_ABSOLUTE         4462
           5099 LOAD_NAME             6253
====================
error opcode: 'int' object has no attribute '__getitem__'
--> hasname 6253 <--
====================

           5102 UNARY_NOT           
           5103 EXTENDED_ARG         24377
           5106 LOAD_CONST           1597597029L
====================
error opcode: 'long' object has no attribute '__getitem__'
--> hasconst 1597597029 <--
====================

           5109 ROT_TWO             
           5110 STOP_CODE           
           5111 JUMP_ABSOLUTE         5133
        >> 5114 LOAD_CONST               9 (2)
           5117 SLICE+2             
           5118 POP_TOP             
           5119 LOAD_NAME                3 (str)
           5122 JUMP_ABSOLUTE         5136
        >> 5125 UNARY_POSITIVE      
           5126 POP_TOP             
           5127 LOAD_NAME                0 (a)
           5130 JUMP_ABSOLUTE          618
        >> 5133 JUMP_FORWARD           226 (to 5362)

====================
error opcode: 'int' object has no attribute '__getitem__'
--> hasjrel 226 <--
====================

        >> 5136 JUMP_FORWARD          3152 (to 8291)

====================
error opcode: 'int' object has no attribute '__getitem__'
--> hasjrel 3152 <--
====================

           5139 ROT_TWO             
           5140 LOAD_FAST            24086
====================
error opcode: 'int' object has no attribute '__getitem__'
--> haslocal 24086 <--
====================

           5143 JUMP_IF_FALSE_OR_POP 31332
           5146 STOP_CODE           
           5147 STORE_FAST               0 (DIVIDER)
           5150 JUMP_ABSOLUTE         5171
        >> 5153 LOAD_CONST             123 (1220723663)
           5156 STORE_FAST               0 (DIVIDER)
           5159 JUMP_ABSOLUTE         5174
        >> 5162 LOAD_CONST             124 (1218866617)
           5165 STORE_FAST               0 (DIVIDER)
           5168 JUMP_ABSOLUTE         3318
        >> 5171 JUMP_ABSOLUTE         3859
        >> 5174 JUMP_ABSOLUTE         3859
           5177 INPLACE_POWER       
           5178 INPLACE_LSHIFT      
           5179 SETUP_LOOP           18234 (to 23416)

====================
error opcode: 'int' object has no attribute '__getitem__'
--> hasjrel 18234 <--
====================

           5182 INPLACE_LSHIFT      
           5183 SLICE+0             
           5184 BINARY_RSHIFT       
           5185 JUMP_IF_FALSE_OR_POP   125
           5188 STOP_CODE           
           5189 JUMP_ABSOLUTE         5213
        >> 5192 LOAD_CONST             177 (3784794503)
           5195 STORE_FAST               0 (DIVIDER)
           5198 JUMP_ABSOLUTE         5216
        >> 5201 LOAD_CONST             178 (1136472242)
           5204 STORE_FAST               0 (DIVIDER)
           5207 JUMP_ABSOLUTE         5219
           5210 JUMP_FORWARD          2008 (to 7221)

====================
error opcode: 'int' object has no attribute '__getitem__'
--> hasjrel 2008 <--
====================

        >> 5213 JUMP_ABSOLUTE         3859
        >> 5216 JUMP_ABSOLUTE         3859
        >> 5219 JUMP_ABSOLUTE         3859
           5222 INPLACE_XOR         
           5223 DELETE_SLICE+2      
           5224 BINARY_LSHIFT       
           5225 WITH_CLEANUP        
           5226 SETUP_LOOP           28467 (to 33696)

====================
error opcode: 'int' object has no attribute '__getitem__'
--> hasjrel 28467 <--
====================

           5229 CALL_FUNCTION_KW     28929
           5232 <139>                28180
           5235 BINARY_SUBSCR       
           5236 STOP_CODE           
           5237 JUMP_ABSOLUTE         5265
        >> 5240 JUMP_ABSOLUTE         5268
        >> 5243 SETUP_FINALLY           25 (to 5271)

====================
error opcode: 'int' object has no attribute '__getitem__'
--> hasjrel 25 <--
====================

           5246 JUMP_ABSOLUTE         5274
        >> 5249 JUMP_ABSOLUTE         5277
        >> 5252 BINARY_SUBSCR       
           5253 LOAD_CONST               8 (1)
           5256 JUMP_FORWARD          1750 (to 7009)

====================
error opcode: 'int' object has no attribute '__getitem__'
--> hasjrel 1750 <--
====================

           5259 JUMP_ABSOLUTE           61
           5262 JUMP_ABSOLUTE         5240
        >> 5265 JUMP_ABSOLUTE         4044
        >> 5268 JUMP_ABSOLUTE         2314
        >> 5271 JUMP_ABSOLUTE         5249
        >> 5274 JUMP_FORWARD          1393 (to 6670)

====================
error opcode: 'int' object has no attribute '__getitem__'
--> hasjrel 1393 <--
====================

        >> 5277 JUMP_ABSOLUTE         2104
           5280 CALL_FUNCTION_VAR_KW 23897
           5283 JUMP_IF_FALSE_OR_POP 19567
           5286 CALL_FUNCTION_VAR_KW   125
           5289 STOP_CODE           
           5290 JUMP_ABSOLUTE         5320
        >> 5293 LOAD_CONST              81 (1122223590)
           5296 STORE_FAST               0 (DIVIDER)
           5299 JUMP_ABSOLUTE         5323
        >> 5302 LOAD_CONST              82 (3913884456)
           5305 STORE_FAST               0 (DIVIDER)
           5308 JUMP_ABSOLUTE         5326
        >> 5311 LOAD_CONST              83 (4132012444)
           5314 STORE_FAST               0 (DIVIDER)
           5317 JUMP_ABSOLUTE          574
        >> 5320 JUMP_ABSOLUTE         3859
        >> 5323 JUMP_ABSOLUTE         3859
        >> 5326 JUMP_ABSOLUTE         3859
           5329 CONTINUE_LOOP        16957
           5332 STORE_DEREF          26737
           5335 INPLACE_AND         
           5336 BINARY_OR           
           5337 LOAD_CLOSURE           125
           5340 STOP_CODE           
           5341 JUMP_ABSOLUTE         5371
        >> 5344 LOAD_CONST             107 (4225593240)
           5347 STORE_FAST               0 (DIVIDER)
           5350 JUMP_ABSOLUTE         5374
        >> 5353 LOAD_CONST             108 (417535526)
           5356 STORE_FAST               0 (DIVIDER)
           5359 JUMP_ABSOLUTE         5377
        >> 5362 LOAD_CONST             109 (1255663200)
           5365 STORE_FAST               0 (DIVIDER)
           5368 JUMP_ABSOLUTE         4537
        >> 5371 JUMP_ABSOLUTE         3859
        >> 5374 JUMP_ABSOLUTE         3859
        >> 5377 JUMP_ABSOLUTE         3859
           5380 POP_TOP             
           5381 POP_BLOCK           
           5382 POP_JUMP_IF_TRUE     24363
           5385 JUMP_IF_TRUE_OR_POP  25690
           5388 <7>                 
           5389 STOP_CODE           
           5390 LOAD_CONST               6 (16)
           5393 CALL_FUNCTION            2
           5396 JUMP_ABSOLUTE         5416
        >> 5399 LOAD_CONST              20 ('aa')
           5402 LOAD_CONST              47 (())
           5405 LOAD_CONST              21 (<code object aa at 0x104bbdab0, file "ck.py", line 75>)
           5408 JUMP_ABSOLUTE         5419
        >> 5411 POP_TOP             
           5412 POP_TOP             
           5413 JUMP_ABSOLUTE         5230
        >> 5416 JUMP_ABSOLUTE          399
        >> 5419 JUMP_ABSOLUTE          752
           5422 BINARY_ADD          
           5423 STOP_CODE           
           5424 CALL_FUNCTION_VAR    12901
           5427 DELETE_SLICE+3      
           5428 BUILD_TUPLE          29019
           5431 LOAD_LOCALS         
           5432 BINARY_DIVIDE       
        >> 5433 LOAD_NAME               23 (args)
        >> 5436 LOAD_NAME               24 (kwargs)
           5439 CALL_FUNCTION_VAR_KW     0
           5442 JUMP_ABSOLUTE         5461
        >> 5445 POP_TOP             
           5446 SETUP_LOOP              15 (to 5464)

====================
error opcode: 'int' object has no attribute '__getitem__'
--> hasjrel 15 <--
====================

           5449 JUMP_ABSOLUTE         5467
        >> 5452 JUMP_ABSOLUTE         5470
           5455 JUMP_FORWARD          1880 (to 7338)

====================
error opcode: 'int' object has no attribute '__getitem__'
--> hasjrel 1880 <--
====================

           5458 JUMP_FORWARD          1200 (to 6661)

====================
error opcode: 'int' object has no attribute '__getitem__'
--> hasjrel 1200 <--
====================

        >> 5461 JUMP_ABSOLUTE         4884
        >> 5464 JUMP_ABSOLUTE         5452
        >> 5467 JUMP_ABSOLUTE          586
        >> 5470 JUMP_ABSOLUTE         1726
           5473 INPLACE_FLOOR_DIVIDE
           5474 CALL_FUNCTION_KW     24946
           5477 CALL_FUNCTION_VAR_KW 19553
           5480 CALL_FUNCTION_KW     25188
           5483 STOP_CODE           
           5484 LOAD_FAST                0 (DIVIDER)
           5487 COMPARE_OP               2 (==)
           5490 POP_JUMP_IF_TRUE      5508
           5493 LOAD_CONST             203 (2801322355)
           5496 LOAD_FAST                0 (DIVIDER)
           5499 COMPARE_OP               2 (==)
           5502 POP_JUMP_IF_TRUE      5511
           5505 JUMP_ABSOLUTE          129
        >> 5508 JUMP_ABSOLUTE         3862
        >> 5511 JUMP_FORWARD          2014 (to 7528)

====================
error opcode: 'int' object has no attribute '__getitem__'
--> hasjrel 2014 <--
====================

           5514 BINARY_SUBTRACT     
           5515 LOAD_GLOBAL          33671
====================
error opcode: 'int' object has no attribute '__getitem__'
--> hasname 33671 <--
====================

        >> 5518 STORE_FAST               0 (DIVIDER)
           5521 JUMP_ABSOLUTE         5551
        >> 5524 LOAD_CONST              66 (2791987114)
           5527 STORE_FAST               0 (DIVIDER)
           5530 JUMP_ABSOLUTE         5554
        >> 5533 LOAD_CONST              67 (663319258)
           5536 STORE_FAST               0 (DIVIDER)
           5539 JUMP_ABSOLUTE         5557
        >> 5542 LOAD_CONST              68 (1453245079)
           5545 STORE_FAST               0 (DIVIDER)
           5548 JUMP_FORWARD          1582 (to 7133)

====================
error opcode: 'int' object has no attribute '__getitem__'
--> hasjrel 1582 <--
====================

        >> 5551 JUMP_ABSOLUTE         3859
        >> 5554 JUMP_ABSOLUTE         3859
        >> 5557 JUMP_ABSOLUTE         3859
           5560 BINARY_RSHIFT       
           5561 SETUP_LOOP           18297 (to 23861)

====================
error opcode: 'int' object has no attribute '__getitem__'
--> hasjrel 18297 <--
====================

           5564 RETURN_VALUE        
           5565 FOR_ITER             55667 (to 61235)

====================
error opcode: 'int' object has no attribute '__getitem__'
--> hasjrel 55667 <--
====================

           5568 BINARY_DIVIDE       
           5569 LOAD_CONST             207 (4252175081)
           5572 LOAD_FAST                0 (DIVIDER)
           5575 COMPARE_OP               2 (==)
           5578 POP_JUMP_IF_TRUE      5596
           5581 LOAD_CONST             211 (3016791946)
           5584 LOAD_FAST                0 (DIVIDER)
           5587 COMPARE_OP               2 (==)
           5590 JUMP_FORWARD          1957 (to 7550)

====================
error opcode: 'int' object has no attribute '__getitem__'
--> hasjrel 1957 <--
====================

           5593 JUMP_FORWARD           898 (to 6494)

====================
error opcode: 'int' object has no attribute '__getitem__'
--> hasjrel 898 <--
====================

        >> 5596 JUMP_ABSOLUTE         5433
           5599 STORE_FAST           21095
====================
error opcode: 'int' object has no attribute '__getitem__'
--> haslocal 21095 <--
====================

           5602 PRINT_EXPR          
           5603 BINARY_MULTIPLY     
           5604 INPLACE_ADD         
           5605 BINARY_FLOOR_DIVIDE 
           5606 DELETE_SLICE+0      
           5607 BUILD_MAP              387
           5610 STOP_CODE           
           5611 JUMP_ABSOLUTE         5639
        >> 5614 LOAD_NAME                0 (a)
           5617 GET_ITER            
           5618 JUMP_ABSOLUTE         5642
        >> 5621 LOAD_GLOBAL              8 (aa)
           5624 DELETE_ATTR              0 (a)
           5627 LOAD_CONST              23 (<code object a at 0x104bbdb30, file "ck.py", line 85>)
           5630 MAKE_FUNCTION            0
           5633 JUMP_ABSOLUTE         5645
           5636 JUMP_ABSOLUTE         1510
        >> 5639 JUMP_ABSOLUTE         5192
        >> 5642 JUMP_FORWARD           727 (to 6372)

====================
error opcode: 'int' object has no attribute '__getitem__'
--> hasjrel 727 <--
====================

        >> 5645 JUMP_FORWARD           733 (to 6381)

====================
error opcode: 'int' object has no attribute '__getitem__'
--> hasjrel 733 <--
====================

           5648 JUMP_IF_TRUE_OR_POP  24416
           5651 RETURN_VALUE        
           5652 BUILD_SET              101
           5655 STOP_CODE           
           5656 LOAD_CONST               2 (0)
           5659 BINARY_SUBSCR       
           5660 JUMP_ABSOLUTE         5679
        >> 5663 LOAD_NAME                9 (xrange)
           5666 LOAD_CONST               8 (1)
           5669 LOAD_CONST              32 (999999)
           5672 CALL_FUNCTION            2
           5675 GET_ITER            
           5676 JUMP_ABSOLUTE         2686
        >> 5679 JUMP_ABSOLUTE         1311
           5682 SET_ADD              29747
           5685 INPLACE_DIVIDE      
           5686 BREAK_LOOP          
           5687 SETUP_LOOP             310 (to 6000)

====================
error opcode: 'int' object has no attribute '__getitem__'
--> hasjrel 310 <--
====================

           5690 JUMP_ABSOLUTE         5709
        >> 5693 POP_BLOCK           
           5694 JUMP_ABSOLUTE         5712
        >> 5697 LOAD_CONST              34 (<code object p at 0x104be00b0, file "ck.py", line 149>)
           5700 MAKE_FUNCTION            0
           5703 STORE_NAME              20 (p)
           5706 JUMP_FORWARD          3013 (to 8722)

====================
error opcode: 'int' object has no attribute '__getitem__'
--> hasjrel 3013 <--
====================

        >> 5709 JUMP_FORWARD           967 (to 6679)

====================
error opcode: 'int' object has no attribute '__getitem__'
--> hasjrel 967 <--
====================

        >> 5712 JUMP_ABSOLUTE         2663
           5715 PRINT_NEWLINE       
           5716 STORE_ATTR            6990
====================
error opcode: 'int' object has no attribute '__getitem__'
--> hasname 6990 <--
====================

           5719 UNARY_POSITIVE      
           5720 DUP_TOP             
           5721 CONTINUE_LOOP        30834
           5724 BINARY_MODULO       
           5725 JUMP_ABSOLUTE         5755
        >> 5728 LOAD_NAME                9 (xrange)
           5731 LOAD_CONST               2 (0)
           5734 LOAD_CONST              22 (99)
           5737 JUMP_ABSOLUTE         5758
        >> 5740 LOAD_NAME               15 (False)
           5743 JUMP_ABSOLUTE         5761
        >> 5746 STORE_NAME               0 (a)
           5749 JUMP_FORWARD          1208 (to 6960)

====================
error opcode: 'int' object has no attribute '__getitem__'
--> hasjrel 1208 <--
====================

           5752 JUMP_ABSOLUTE         4080
        >> 5755 JUMP_FORWARD           605 (to 6363)

====================
error opcode: 'int' object has no attribute '__getitem__'
--> hasjrel 605 <--
====================

        >> 5758 JUMP_ABSOLUTE         5302
        >> 5761 JUMP_ABSOLUTE         2055
           5764 INPLACE_LSHIFT      
           5765 INPLACE_LSHIFT      
           5766 PRINT_NEWLINE       
           5767 BUILD_SET            20613
           5770 DELETE_FAST          25733
====================
error opcode: 'int' object has no attribute '__getitem__'
--> haslocal 25733 <--
====================

           5773 DELETE_NAME          31744
====================
error opcode: 'int' object has no attribute '__getitem__'
--> hasname 31744 <--
====================

           5776 STOP_CODE           
           5777 STOP_CODE           
           5778 COMPARE_OP               2 (==)
           5781 POP_JUMP_IF_TRUE      5805
           5784 LOAD_CONST              83 (4132012444)
           5787 LOAD_FAST                0 (DIVIDER)
           5790 COMPARE_OP               2 (==)
           5793 POP_JUMP_IF_TRUE      5808
           5796 LOAD_CONST             188 (261538107)
           5799 LOAD_FAST                0 (DIVIDER)
           5802 JUMP_ABSOLUTE         3459
        >> 5805 JUMP_ABSOLUTE         1533
        >> 5808 JUMP_FORWARD           780 (to 6591)

====================
error opcode: 'int' object has no attribute '__getitem__'
--> hasjrel 780 <--
====================

           5811 STORE_ATTR           11066
====================
error opcode: 'int' object has no attribute '__getitem__'
--> hasname 11066 <--
====================

           5814 BUILD_SET              124
           5817 STOP_CODE           
           5818 COMPARE_OP               2 (==)
           5821 POP_JUMP_IF_TRUE      5842
           5824 LOAD_CONST              86 (620738832)
           5827 LOAD_FAST                0 (DIVIDER)
           5830 COMPARE_OP               2 (==)
           5833 POP_JUMP_IF_TRUE      5845
           5836 LOAD_CONST             213 (None)
           5839 JUMP_ABSOLUTE         2760
        >> 5842 JUMP_FORWARD           983 (to 6828)

====================
error opcode: 'int' object has no attribute '__getitem__'
--> hasjrel 983 <--
====================

        >> 5845 JUMP_ABSOLUTE         1247
           5848 SETUP_FINALLY        29257 (to 35108)

====================
error opcode: 'int' object has no attribute '__getitem__'
--> hasjrel 29257 <--
====================

           5851 DELETE_SUBSCR       
           5852 IMPORT_FROM          34893
====================
error opcode: 'int' object has no attribute '__getitem__'
--> hasname 34893 <--
====================

        >> 5855 LOAD_NAME                0 (a)
           5858 LOAD_CONST               8 (1)
           5861 DELETE_SUBSCR       
           5862 LOAD_NAME                0 (a)
           5865 JUMP_ABSOLUTE         5881
        >> 5868 LOAD_CONST               8 (1)
           5871 LOAD_CONST              43 (98)
           5874 CALL_FUNCTION            2
           5877 GET_ITER            
           5878 JUMP_ABSOLUTE         5608
        >> 5881 JUMP_FORWARD          1608 (to 7492)

====================
error opcode: 'int' object has no attribute '__getitem__'
--> hasjrel 1608 <--
====================

           5884 INPLACE_XOR         
           5885 POP_JUMP_IF_FALSE    34105
        >> 5888 COMPARE_OP               2 (==)
           5891 POP_JUMP_IF_TRUE      5921
           5894 LOAD_CONST             210 (3137633383)
           5897 LOAD_FAST                0 (DIVIDER)
           5900 COMPARE_OP               2 (==)
           5903 POP_JUMP_IF_TRUE      5924
           5906 LOAD_CONST             192 (3002923223)
           5909 LOAD_FAST                0 (DIVIDER)
           5912 COMPARE_OP               2 (==)
           5915 POP_JUMP_IF_TRUE      5927
           5918 JUMP_ABSOLUTE         1749
        >> 5921 JUMP_ABSOLUTE         5693
        >> 5924 JUMP_ABSOLUTE         5728
        >> 5927 JUMP_ABSOLUTE         4275
           5930 RETURN_VALUE        
           5931 DELETE_FAST          20550
====================
error opcode: 'int' object has no attribute '__getitem__'
--> haslocal 20550 <--
====================

           5934 BINARY_MULTIPLY     
           5935 INPLACE_ADD         
           5936 BUILD_LIST           36406
        >> 5939 LOAD_CONST              33 (<code object a at 0x104be0030, file "ck.py", line 145>)
           5942 MAKE_FUNCTION            0
           5945 STORE_NAME               0 (a)
           5948 JUMP_ABSOLUTE         5972
        >> 5951 LOAD_CONST               1 ('666')
           5954 STORE_GLOBAL             1 (b)
           5957 LOAD_GLOBAL              1 (b)
           5960 JUMP_ABSOLUTE         5975
        >> 5963 LOAD_CONST               8 (1)
           5966 LOAD_CONST               1 ('666')
           5969 JUMP_ABSOLUTE         5688
        >> 5972 JUMP_ABSOLUTE         3106
        >> 5975 JUMP_FORWARD          1496 (to 7474)

====================
error opcode: 'int' object has no attribute '__getitem__'
--> hasjrel 1496 <--
====================

           5978 JUMP_IF_FALSE_OR_POP 21251
           5981 PRINT_NEWLINE       
           5982 INPLACE_DIVIDE      
           5983 FOR_ITER             30577 (to 36563)

====================
error opcode: 'int' object has no attribute '__getitem__'
--> hasjrel 30577 <--
====================

           5986 BINARY_ADD          
        >> 5987 LOAD_NAME                0 (a)
           5990 DELETE_SLICE+0      
           5991 LOAD_NAME                0 (a)
           5994 JUMP_ABSOLUTE         6010
        >> 5997 INPLACE_LSHIFT      
           5998 STORE_NAME               0 (a)
           6001 LOAD_NAME                0 (a)
           6004 JUMP_ABSOLUTE         1197
           6007 JUMP_ABSOLUTE         2573
        >> 6010 JUMP_ABSOLUTE         4746
           6013 BINARY_FLOOR_DIVIDE 
           6014 DELETE_SLICE+1      
           6015 UNARY_NEGATIVE      
           6016 EXEC_STMT           
           6017 LOAD_LOCALS         
           6018 LOAD_ATTR            15197
====================
error opcode: 'int' object has no attribute '__getitem__'
--> hasname 15197 <--
====================

           6021 JUMP_FORWARD          5742 (to 11766)

====================
error opcode: 'int' object has no attribute '__getitem__'
--> hasjrel 5742 <--
====================

           6024 STOP_CODE           
           6025 JUMP_ABSOLUTE         6050
        >> 6028 JUMP_ABSOLUTE         6053
        >> 6031 LOAD_NAME                0 (a)
           6034 CALL_FUNCTION            0
           6037 POP_TOP             
           6038 LOAD_CONST              37 (<code object a at 0x104be0230, file "ck.py", line 194>)
           6041 MAKE_FUNCTION            0
           6044 JUMP_ABSOLUTE         5430
           6047 JUMP_ABSOLUTE         6028
        >> 6050 JUMP_ABSOLUTE          408
        >> 6053 JUMP_ABSOLUTE          916
           6056 STORE_DEREF          12930
           6059 UNPACK_SEQUENCE        101
           6062 STOP_CODE           
           6063 LOAD_CONST               8 (1)
           6066 INPLACE_OR          
           6067 JUMP_ABSOLUTE         6086
        >> 6070 BUILD_CLASS         
           6071 STORE_NAME               0 (a)
           6074 LOAD_CONST              18 (<code object a at 0x104bbd9b0, file "ck.py", line 69>)
           6077 MAKE_FUNCTION            0
           6080 JUMP_ABSOLUTE         6089
           6083 JUMP_FORWARD          2409 (to 8495)

====================
error opcode: 'int' object has no attribute '__getitem__'
--> hasjrel 2409 <--
====================

        >> 6086 JUMP_ABSOLUTE         5353
        >> 6089 JUMP_ABSOLUTE         3567
           6092 STORE_SLICE+3       
           6093 JUMP_ABSOLUTE        16005
           6096 CALL_FUNCTION_KW     32142
        >> 6099 LOAD_NAME                7 (True)
           6102 POP_JUMP_IF_FALSE     6129
           6105 JUMP_ABSOLUTE         6132
        >> 6108 STORE_NAME               0 (a)
           6111 DELETE_NAME              0 (a)
           6114 SETUP_LOOP              18 (to 6135)

====================
error opcode: 'int' object has no attribute '__getitem__'
--> hasjrel 18 <--
====================

           6117 JUMP_ABSOLUTE         6138
        >> 6120 JUMP_ABSOLUTE         6141
        >> 6123 STORE_NAME               4 (i)
           6126 JUMP_ABSOLUTE          442
        >> 6129 JUMP_ABSOLUTE         1564
        >> 6132 JUMP_FORWARD          1271 (to 7406)

====================
error opcode: 'int' object has no attribute '__getitem__'
--> hasjrel 1271 <--
====================

        >> 6135 JUMP_ABSOLUTE         6120
        >> 6138 JUMP_ABSOLUTE         1653
        >> 6141 JUMP_ABSOLUTE         5153
           6144 INPLACE_AND         
           6145 CALL_FUNCTION_VAR    29492
           6148 PRINT_ITEM          
           6149 EXTENDED_ARG         31844
        >> 6152 LOAD_CONST           2086928437L
====================
error opcode: 'long' object has no attribute '__getitem__'
--> hasconst 2086928437 <--
====================

           6155 STORE_FAST               0 (DIVIDER)
           6158 JUMP_ABSOLUTE         6185
        >> 6161 LOAD_CONST              54 (2106207243)
           6164 STORE_FAST               0 (DIVIDER)
           6167 JUMP_ABSOLUTE         6188
        >> 6170 LOAD_CONST              55 (473125748)
           6173 STORE_FAST               0 (DIVIDER)
           6176 JUMP_ABSOLUTE         6191
        >> 6179 LOAD_CONST              56 (3286049750)
           6182 JUMP_FORWARD           355 (to 6540)

====================
error opcode: 'int' object has no attribute '__getitem__'
--> hasjrel 355 <--
====================

        >> 6185 JUMP_ABSOLUTE         3859
        >> 6188 JUMP_ABSOLUTE         3859
        >> 6191 JUMP_ABSOLUTE         3859
           6194 CALL_FUNCTION_KW     13970
           6197 LOAD_CONST           28024
====================
error opcode: 'int' object has no attribute '__getitem__'
--> hasconst 28024 <--
====================

           6200 BINARY_DIVIDE       
           6201 LOAD_GLOBAL           2164
====================
error opcode: 'int' object has no attribute '__getitem__'
--> hasname 2164 <--
====================

           6204 STOP_CODE           
           6205 STORE_ATTR               0 (a)
           6208 JUMP_ABSOLUTE         6227
        >> 6211 LOAD_NAME                0 (a)
           6214 LOAD_CONST               8 (1)
           6217 INPLACE_MODULO      
           6218 JUMP_ABSOLUTE         6230
        >> 6221 LOAD_CONST              20 ('aa')
           6224 JUMP_ABSOLUTE         2354
        >> 6227 JUMP_ABSOLUTE         1302
        >> 6230 JUMP_FORWARD           475 (to 6708)

====================
error opcode: 'int' object has no attribute '__getitem__'
--> hasjrel 475 <--
====================

           6233 DUP_TOP             
           6234 UNARY_INVERT        
           6235 UNARY_INVERT        
           6236 BREAK_LOOP          
           6237 STORE_FAST           21060
====================
error opcode: 'int' object has no attribute '__getitem__'
--> haslocal 21060 <--
====================

           6240 CALL_FUNCTION_VAR_KW   124
           6243 STOP_CODE           
           6244 COMPARE_OP               2 (==)
           6247 POP_JUMP_IF_TRUE      6271
           6250 LOAD_CONST             157 (3462530290)
           6253 LOAD_FAST                0 (DIVIDER)
           6256 COMPARE_OP               2 (==)
           6259 POP_JUMP_IF_TRUE      6274
           6262 LOAD_CONST             121 (3333063914)
           6265 LOAD_FAST                0 (DIVIDER)
           6268 JUMP_ABSOLUTE         4165
        >> 6271 JUMP_ABSOLUTE         5987
        >> 6274 JUMP_ABSOLUTE         2276
           6277 DUP_TOPX             20302
           6280 INPLACE_ADD         
           6281 DELETE_SLICE+0      
           6282 SLICE+2             
           6283 MAP_ADD              28260
           6286 STOP_CODE           
           6287 LOAD_FAST                0 (DIVIDER)
           6290 COMPARE_OP               2 (==)
           6293 POP_JUMP_IF_TRUE      6311
           6296 LOAD_CONST             204 (2517988253)
           6299 LOAD_FAST                0 (DIVIDER)
           6302 COMPARE_OP               2 (==)
           6305 POP_JUMP_IF_TRUE      6314
           6308 JUMP_FORWARD          2322 (to 8633)

====================
error opcode: 'int' object has no attribute '__getitem__'
--> hasjrel 2322 <--
====================

        >> 6311 JUMP_FORWARD          2202 (to 8516)

====================
error opcode: 'int' object has no attribute '__getitem__'
--> hasjrel 2202 <--
====================

        >> 6314 JUMP_ABSOLUTE         5049
           6317 COMPARE_OP           25160
====================
error opcode: 'int' object has no attribute '__getitem__'
--> hascompare 25160 <--
====================

           6320 CALL_FUNCTION_VAR_KW 27411
           6323 JUMP_ABSOLUTE        33683
           6326 POP_TOP             
           6327 STOP_CODE           
           6328 STORE_NAME               0 (a)
           6331 LOAD_NAME                0 (a)
           6334 JUMP_ABSOLUTE         6353
        >> 6337 LOAD_NAME               18 (c)
           6340 LOAD_CONST               3 (3)
           6343 SLICE+2             
           6344 STORE_NAME              18 (c)
           6347 LOAD_NAME                0 (a)
           6350 JUMP_ABSOLUTE         4254
        >> 6353 JUMP_ABSOLUTE         1837
           6356 DELETE_ATTR          23649
====================
error opcode: 'int' object has no attribute '__getitem__'
--> hasname 23649 <--
====================

           6359 CONTINUE_LOOP        63857
           6362 BINARY_SUBTRACT     
        >> 6363 LOAD_CONST             119 (1878337018)
           6366 STORE_FAST               0 (DIVIDER)
           6369 JUMP_ABSOLUTE         6396
        >> 6372 LOAD_CONST             120 (3866484190)
           6375 STORE_FAST               0 (DIVIDER)
           6378 JUMP_ABSOLUTE         6399
        >> 6381 LOAD_CONST             121 (3333063914)
           6384 STORE_FAST               0 (DIVIDER)
           6387 JUMP_ABSOLUTE         6402
           6390 JUMP_ABSOLUTE         5144
           6393 JUMP_ABSOLUTE         3859
        >> 6396 JUMP_ABSOLUTE         3859
        >> 6399 JUMP_ABSOLUTE         3859
        >> 6402 JUMP_ABSOLUTE         3859
           6405 INPLACE_MULTIPLY    
           6406 PRINT_NEWLINE       
           6407 PRINT_ITEM_TO       
           6408 BUILD_TUPLE            612
           6411 STOP_CODE           
           6412 JUMP_IF_FALSE_OR_POP  6434
           6415 JUMP_ABSOLUTE         6437
        >> 6418 POP_TOP             
           6419 LOAD_CONST              44 (<code object <dictcomp> at 0x104be04b0, file "ck.py", line 214>)
           6422 MAKE_FUNCTION            0
           6425 LOAD_NAME                9 (xrange)
           6428 LOAD_CONST              43 (98)
           6431 JUMP_ABSOLUTE         5984
        >> 6434 JUMP_ABSOLUTE         1032
        >> 6437 JUMP_ABSOLUTE         3115
           6440 INPLACE_MULTIPLY    
           6441 JUMP_ABSOLUTE        23296
           6444 INPLACE_POWER       
           6445 SLICE+2             
           6446 LOAD_GLOBAL            281
====================
error opcode: 'int' object has no attribute '__getitem__'
--> hasname 281 <--
====================

           6449 LOAD_CONST              38 (<code object f at 0x104be0330, file "ck.py", line 198>)
           6452 MAKE_FUNCTION            0
           6455 JUMP_ABSOLUTE         6471
        >> 6458 STORE_SUBSCR        
           6459 SETUP_LOOP              12 (to 6474)

====================
error opcode: 'int' object has no attribute '__getitem__'
--> hasjrel 12 <--
====================

           6462 JUMP_ABSOLUTE         6477
        >> 6465 JUMP_ABSOLUTE         6480
           6468 JUMP_FORWARD          1589 (to 8060)

====================
error opcode: 'int' object has no attribute '__getitem__'
--> hasjrel 1589 <--
====================

        >> 6471 JUMP_ABSOLUTE         2654
        >> 6474 JUMP_ABSOLUTE         6465
        >> 6477 JUMP_ABSOLUTE         6161
        >> 6480 JUMP_ABSOLUTE         2663
           6483 PRINT_NEWLINE_TO    
           6484 BINARY_LSHIFT       
           6485 STORE_SLICE+2       
           6486 RAISE_VARARGS         6942
           6489 POP_TOP             
           6490 COMPARE_OP           30577
====================
error opcode: 'int' object has no attribute '__getitem__'
--> hascompare 30577 <--
====================

           6493 BINARY_SUBSCR       
        >> 6494 LOAD_NAME                0 (a)
           6497 LOAD_CONST               8 (1)
           6500 INPLACE_DIVIDE      
           6501 STORE_NAME               0 (a)
           6504 JUMP_ABSOLUTE         6522
        >> 6507 FOR_ITER                15 (to 6525)

====================
error opcode: 'int' object has no attribute '__getitem__'
--> hasjrel 15 <--
====================

           6510 JUMP_ABSOLUTE         6528
        >> 6513 JUMP_ABSOLUTE         6531
           6516 JUMP_ABSOLUTE         5070
           6519 JUMP_FORWARD           866 (to 7388)

====================
error opcode: 'int' object has no attribute '__getitem__'
--> hasjrel 866 <--
====================

        >> 6522 JUMP_FORWARD          2085 (to 8610)

====================
error opcode: 'int' object has no attribute '__getitem__'
--> hasjrel 2085 <--
====================

        >> 6525 JUMP_ABSOLUTE         6513
        >> 6528 JUMP_ABSOLUTE         4737
        >> 6531 JUMP_ABSOLUTE         4893
           6534 BINARY_LSHIFT       
           6535 MAP_ADD               3883
           6538 NOP                 
           6539 JUMP_IF_TRUE_OR_POP    125
           6542 STOP_CODE           
           6543 JUMP_ABSOLUTE         6570
        >> 6546 LOAD_CONST              57 (323657835)
           6549 STORE_FAST               0 (DIVIDER)
           6552 JUMP_ABSOLUTE         6573
        >> 6555 LOAD_CONST              58 (2907760793)
           6558 STORE_FAST               0 (DIVIDER)
           6561 JUMP_ABSOLUTE         6576
        >> 6564 LOAD_CONST              59 (2957893970)
           6567 JUMP_FORWARD           132 (to 6702)

====================
error opcode: 'int' object has no attribute '__getitem__'
--> hasjrel 132 <--
====================

        >> 6570 JUMP_ABSOLUTE         3859
        >> 6573 JUMP_ABSOLUTE         3859
        >> 6576 JUMP_ABSOLUTE         3859
           6579 BINARY_TRUE_DIVIDE  
           6580 MAKE_FUNCTION         6504
           6583 INPLACE_MULTIPLY    
           6584 UNARY_NEGATIVE      
           6585 SETUP_LOOP           10339 (to 16927)

====================
error opcode: 'int' object has no attribute '__getitem__'
--> hasjrel 10339 <--
====================

           6588 JUMP_ABSOLUTE         6607
        >> 6591 BINARY_SUBSCR       
           6592 LOAD_CONST               8 (1)
           6595 INPLACE_ADD         
           6596 ROT_THREE           
           6597 STORE_SUBSCR        
           6598 JUMP_ABSOLUTE         6610
        >> 6601 LOAD_NAME                7 (True)
           6604 JUMP_ABSOLUTE         5722
        >> 6607 JUMP_ABSOLUTE         4558
        >> 6610 JUMP_FORWARD          1242 (to 7855)

====================
error opcode: 'int' object has no attribute '__getitem__'
--> hasjrel 1242 <--
====================

           6613 CALL_FUNCTION        33611
           6616 INPLACE_ADD         
           6617 MAKE_FUNCTION        36221
           6620 SETUP_LOOP            4954 (to 11577)

====================
error opcode: 'int' object has no attribute '__getitem__'
--> hasjrel 4954 <--
====================

           6623 STOP_CODE           
           6624 LOAD_CONST              26 (-1)
           6627 LOAD_CONST              27 (None)
           6630 IMPORT_NAME             13 (time)
           6633 JUMP_ABSOLUTE         6651
        >> 6636 STORE_NAME               0 (a)
           6639 LOAD_CONST              19 (<code object a at 0x104bbda30, file "ck.py", line 71>)
           6642 MAKE_FUNCTION            0
           6645 STORE_NAME               0 (a)
           6648 JUMP_ABSOLUTE          256
        >> 6651 JUMP_ABSOLUTE         4035
           6654 UNPACK_SEQUENCE       1027
           6657 DELETE_NAME          30569
====================
error opcode: 'int' object has no attribute '__getitem__'
--> hasname 30569 <--
====================

           6660 DELETE_NAME          25956
====================
error opcode: 'int' object has no attribute '__getitem__'
--> hasname 25956 <--
====================

           6663 STOP_CODE           
           6664 STORE_FAST               0 (DIVIDER)
           6667 JUMP_ABSOLUTE         6688
        >> 6670 LOAD_CONST             102 (834809003)
           6673 STORE_FAST               0 (DIVIDER)
           6676 JUMP_ABSOLUTE         6691
        >> 6679 LOAD_CONST             103 (3797321274)
           6682 STORE_FAST               0 (DIVIDER)
           6685 JUMP_ABSOLUTE         2642
        >> 6688 JUMP_ABSOLUTE         3859
        >> 6691 JUMP_ABSOLUTE         3859
           6694 BINARY_FLOOR_DIVIDE 
           6695 IMPORT_NAME          37739
====================
error opcode: 'int' object has no attribute '__getitem__'
--> hasname 37739 <--
====================

           6698 INPLACE_SUBTRACT    
           6699 UNARY_NOT           
           6700 BINARY_MULTIPLY     
           6701 MAKE_FUNCTION          125
           6704 STOP_CODE           
           6705 JUMP_ABSOLUTE         6732
        >> 6708 LOAD_CONST              60 (3062359377)
           6711 STORE_FAST               0 (DIVIDER)
           6714 JUMP_ABSOLUTE         6735
        >> 6717 LOAD_CONST              61 (3289164634)
           6720 STORE_FAST               0 (DIVIDER)
           6723 JUMP_ABSOLUTE         6738
        >> 6726 LOAD_CONST              62 (737006728)
           6729 JUMP_ABSOLUTE         1287
        >> 6732 JUMP_ABSOLUTE         3859
        >> 6735 JUMP_ABSOLUTE         3859
        >> 6738 JUMP_ABSOLUTE         3859
           6741 STORE_ATTR           16240
====================
error opcode: 'int' object has no attribute '__getitem__'
--> hasname 16240 <--
====================

           6744 STORE_SUBSCR        
           6745 POP_BLOCK           
           6746 STORE_ATTR           25977
====================
error opcode: 'int' object has no attribute '__getitem__'
--> hasname 25977 <--
====================

           6749 STOP_CODE           
           6750 STOP_CODE           
           6751 JUMP_ABSOLUTE         6776
        >> 6754 LOAD_CONST              16 ('a')
           6757 LOAD_CONST              46 (())
           6760 LOAD_CONST              17 (<code object a at 0x104bbdcb0, file "ck.py", line 67>)
           6763 MAKE_FUNCTION            0
           6766 CALL_FUNCTION            0
           6769 JUMP_ABSOLUTE         6779
        >> 6772 SLICE+3             
           6773 JUMP_ABSOLUTE         3240
        >> 6776 JUMP_ABSOLUTE         4338
        >> 6779 JUMP_ABSOLUTE         2064
           6782 INPLACE_RSHIFT      
           6783 LOAD_ATTR            19476
====================
error opcode: 'int' object has no attribute '__getitem__'
--> hasname 19476 <--
====================

           6786 BUILD_SLICE          27526
           6789 ROT_TWO             
           6790 STOP_CODE           
           6791 POP_JUMP_IF_TRUE      6815
           6794 LOAD_CONST              79 (1977354003)
           6797 LOAD_FAST                0 (DIVIDER)
           6800 COMPARE_OP               2 (==)
           6803 POP_JUMP_IF_TRUE      6818
           6806 LOAD_CONST             117 (1750546855)
           6809 LOAD_FAST                0 (DIVIDER)
           6812 JUMP_FORWARD            53 (to 6868)

====================
error opcode: 'int' object has no attribute '__getitem__'
--> hasjrel 53 <--
====================

        >> 6815 JUMP_ABSOLUTE         5084
        >> 6818 JUMP_ABSOLUTE         5070
           6821 POP_TOP             
           6822 UNARY_NEGATIVE      
           6823 STORE_SLICE+3       
           6824 LOAD_FAST            49777
====================
error opcode: 'int' object has no attribute '__getitem__'
--> haslocal 49777 <--
====================

           6827 BINARY_FLOOR_DIVIDE 
        >> 6828 LOAD_NAME                7 (True)
           6831 POP_JUMP_IF_TRUE      6853
           6834 JUMP_ABSOLUTE         6856
        >> 6837 LOAD_CONST               4 ('abc')
           6840 BINARY_ADD          
           6841 STORE_NAME               0 (a)
           6844 LOAD_NAME                2 (int)
           6847 JUMP_ABSOLUTE         4385
           6850 JUMP_ABSOLUTE         1855
        >> 6853 JUMP_ABSOLUTE         6179
        >> 6856 JUMP_ABSOLUTE          417
           6859 IMPORT_NAME          24344
====================
error opcode: 'int' object has no attribute '__getitem__'
--> hasname 24344 <--
====================

           6862 STORE_SLICE+1       
           6863 SETUP_WITH            5954 (to 12820)

====================
error opcode: 'int' object has no attribute '__getitem__'
--> hasjrel 5954 <--
====================

           6866 FOR_ITER             27488 (to 34357)

====================
error opcode: 'int' object has no attribute '__getitem__'
--> hasjrel 27488 <--
====================

           6869 ROT_TWO             
           6870 STOP_CODE           
           6871 POP_JUMP_IF_TRUE      6895
           6874 LOAD_CONST             135 (2591964641)
           6877 LOAD_FAST                0 (DIVIDER)
           6880 COMPARE_OP               2 (==)
           6883 POP_JUMP_IF_TRUE      6898
           6886 LOAD_CONST             184 (2390829607)
           6889 LOAD_FAST                0 (DIVIDER)
           6892 JUMP_ABSOLUTE          349
        >> 6895 JUMP_ABSOLUTE          274
        >> 6898 JUMP_ABSOLUTE         6507
           6901 BUILD_CLASS         
           6902 BINARY_MULTIPLY     
           6903 STORE_ATTR            3091
====================
error opcode: 'int' object has no attribute '__getitem__'
--> hasname 3091 <--
====================

           6906 SETUP_FINALLY        32067 (to 38976)

====================
error opcode: 'int' object has no attribute '__getitem__'
--> hasjrel 32067 <--
====================

        >> 6909 COMPARE_OP               2 (==)
           6912 POP_JUMP_IF_TRUE      6942
           6915 LOAD_CONST              78 (2430228901)
           6918 LOAD_FAST                0 (DIVIDER)
           6921 COMPARE_OP               2 (==)
           6924 POP_JUMP_IF_TRUE      6945
           6927 LOAD_CONST              92 (2311562147)
           6930 LOAD_FAST                0 (DIVIDER)
           6933 COMPARE_OP               2 (==)
           6936 POP_JUMP_IF_TRUE      6948
           6939 JUMP_ABSOLUTE         4660
        >> 6942 JUMP_ABSOLUTE         2200
        >> 6945 JUMP_ABSOLUTE         6621
        >> 6948 JUMP_ABSOLUTE         3741
           6951 PRINT_ITEM          
           6952 DELETE_NAME          23409
====================
error opcode: 'int' object has no attribute '__getitem__'
--> hasname 23409 <--
====================

           6955 SETUP_WITH            3845 (to 10803)

====================
error opcode: 'int' object has no attribute '__getitem__'
--> hasjrel 3845 <--
====================

           6958 DELETE_SUBSCR       
           6959 CALL_FUNCTION_VAR_KW  7032
           6962 STOP_CODE           
           6963 JUMP_ABSOLUTE         6993
        >> 6966 JUMP_ABSOLUTE         6996
        >> 6969 LOAD_NAME                3 (str)
           6972 LOAD_NAME               14 (OO0OO00O0OO0OO00O)
           6975 CALL_FUNCTION            0
           6978 JUMP_ABSOLUTE         6999
        >> 6981 STORE_NAME               0 (a)
           6984 LOAD_NAME                0 (a)
           6987 JUMP_ABSOLUTE         4579
           6990 JUMP_ABSOLUTE         6966
        >> 6993 JUMP_ABSOLUTE         6546
        >> 6996 JUMP_ABSOLUTE           52
        >> 6999 JUMP_ABSOLUTE         5533
           7002 LOAD_CONST           22360
====================
error opcode: 'int' object has no attribute '__getitem__'
--> hasconst 22360 <--
====================

           7005 BINARY_MODULO       
           7006 STORE_SLICE+1       
           7007 CONTINUE_LOOP        16488
           7010 JUMP_ABSOLUTE         7034
        >> 7013 STORE_NAME               0 (a)
           7016 LOAD_CONST               2 (0)
           7019 LOAD_CONST               8 (1)
           7022 BUILD_LIST               2
           7025 STORE_NAME               0 (a)
           7028 JUMP_ABSOLUTE         7037
           7031 JUMP_FORWARD          1372 (to 8406)

====================
error opcode: 'int' object has no attribute '__getitem__'
--> hasjrel 1372 <--
====================

        >> 7034 JUMP_ABSOLUTE         2582
        >> 7037 JUMP_ABSOLUTE          959
           7040 MAP_ADD               6661
           7043 BINARY_SUBTRACT     
           7044 STORE_SLICE+2       
           7045 CALL_FUNCTION_VAR_KW 34866
        >> 7048 JUMP_ABSOLUTE         7075
        >> 7051 LOAD_NAME               25 (u)
           7054 LOAD_GLOBAL              1 (b)
           7057 CALL_FUNCTION            1
           7060 JUMP_ABSOLUTE         7078
        >> 7063 FOR_ITER                15 (to 7081)

====================
error opcode: 'int' object has no attribute '__getitem__'
--> hasjrel 15 <--
====================

           7066 JUMP_ABSOLUTE         7084
        >> 7069 JUMP_ABSOLUTE         7087
           7072 JUMP_ABSOLUTE           95
        >> 7075 JUMP_ABSOLUTE         5153
        >> 7078 JUMP_ABSOLUTE         6564
        >> 7081 JUMP_ABSOLUTE         7069
        >> 7084 JUMP_ABSOLUTE          743
        >> 7087 JUMP_ABSOLUTE         1041
           7090 INPLACE_POWER       
           7091 GET_ITER            
           7092 INPLACE_DIVIDE      
           7093 JUMP_IF_FALSE_OR_POP 36667
        >> 7096 LOAD_FAST                0 (DIVIDER)
           7099 COMPARE_OP               2 (==)
           7102 POP_JUMP_IF_TRUE      7123
           7105 LOAD_CONST             102 (834809003)
           7108 LOAD_FAST                0 (DIVIDER)
           7111 COMPARE_OP               2 (==)
           7114 POP_JUMP_IF_TRUE      7126
           7117 LOAD_CONST             143 (876477147)
           7120 JUMP_FORWARD          1721 (to 8844)

====================
error opcode: 'int' object has no attribute '__getitem__'
--> hasjrel 1721 <--
====================

        >> 7123 JUMP_ABSOLUTE         2689
        >> 7126 JUMP_FORWARD          1811 (to 8940)

====================
error opcode: 'int' object has no attribute '__getitem__'
--> hasjrel 1811 <--
====================

           7129 STORE_GLOBAL         19273
====================
error opcode: 'int' object has no attribute '__getitem__'
--> hasname 19273 <--
====================

           7132 SETUP_EXCEPT         63601 (to 70736)

====================
error opcode: 'int' object has no attribute '__getitem__'
--> hasjrel 63601 <--
====================

           7135 BINARY_TRUE_DIVIDE  
        >> 7136 LOAD_CONST              69 (3161245959)
           7139 STORE_FAST               0 (DIVIDER)
           7142 JUMP_ABSOLUTE         7163
        >> 7145 LOAD_CONST              70 (3472840527)
           7148 STORE_FAST               0 (DIVIDER)
           7151 JUMP_ABSOLUTE         7166
        >> 7154 LOAD_CONST              71 (1137319345)
           7157 JUMP_FORWARD           756 (to 7916)

====================
error opcode: 'int' object has no attribute '__getitem__'
--> hasjrel 756 <--
====================

           7160 JUMP_ABSOLUTE         3859
        >> 7163 JUMP_ABSOLUTE         3859
        >> 7166 JUMP_ABSOLUTE         3859
           7169 BINARY_XOR          
           7170 LIST_APPEND          32317
        >> 7173 LOAD_CONST             163 (2253539484)
           7176 STORE_FAST               0 (DIVIDER)
           7179 JUMP_ABSOLUTE         7206
        >> 7182 LOAD_CONST             164 (1160711162)
           7185 STORE_FAST               0 (DIVIDER)
           7188 JUMP_ABSOLUTE         7209
        >> 7191 LOAD_CONST             165 (2763014243)
           7194 STORE_FAST               0 (DIVIDER)
           7197 JUMP_ABSOLUTE         7212
        >> 7200 LOAD_CONST             166 (194859120)
           7203 JUMP_ABSOLUTE         3543
        >> 7206 JUMP_ABSOLUTE         3859
        >> 7209 JUMP_ABSOLUTE         3859
        >> 7212 JUMP_ABSOLUTE         3859
           7215 SETUP_WITH           29010 (to 36228)

====================
error opcode: 'int' object has no attribute '__getitem__'
--> hasjrel 29010 <--
====================

           7218 DELETE_ATTR          29001
====================
error opcode: 'int' object has no attribute '__getitem__'
--> hasname 29001 <--
====================

        >> 7221 LOAD_CONST             179 (3620421833)
           7224 STORE_FAST               0 (DIVIDER)
           7227 JUMP_ABSOLUTE         7248
        >> 7230 LOAD_CONST             180 (707514728)
           7233 STORE_FAST               0 (DIVIDER)
           7236 JUMP_ABSOLUTE         7251
        >> 7239 LOAD_CONST             181 (3869867632)
           7242 STORE_FAST               0 (DIVIDER)
           7245 JUMP_ABSOLUTE         2092
        >> 7248 JUMP_ABSOLUTE         3859
        >> 7251 JUMP_ABSOLUTE         3859
           7254 BUILD_TUPLE          16416
           7257 BUILD_LIST             125
           7260 STOP_CODE           
           7261 JUMP_ABSOLUTE         7285
        >> 7264 LOAD_CONST             135 (2591964641)
           7267 STORE_FAST               0 (DIVIDER)
           7270 JUMP_ABSOLUTE         7288
        >> 7273 LOAD_CONST             136 (1159132494)
           7276 STORE_FAST               0 (DIVIDER)
           7279 JUMP_ABSOLUTE         7291
           7282 JUMP_ABSOLUTE         4122
        >> 7285 JUMP_ABSOLUTE         3859
        >> 7288 JUMP_ABSOLUTE         3859
        >> 7291 JUMP_ABSOLUTE         3859
           7294 STORE_SLICE+2       
           7295 INPLACE_OR          
           7296 INPLACE_XOR         
           7297 LOAD_CONST           17418
====================
error opcode: 'int' object has no attribute '__getitem__'
--> hasconst 17418 <--
====================

           7300 DUP_TOPX             40561
           7303 INPLACE_FLOOR_DIVIDE
        >> 7304 COMPARE_OP               2 (==)
           7307 POP_TOP             
           7308 LOAD_CONST              26 (-1)
           7311 LOAD_CONST              27 (None)
           7314 IMPORT_NAME             11 (sys)
           7317 JUMP_ABSOLUTE         7329
        >> 7320 LOAD_CONST              40 ('1')
           7323 JUMP_ABSOLUTE         4423
           7326 JUMP_ABSOLUTE         1671
        >> 7329 JUMP_ABSOLUTE          761
           7332 FOR_ITER             32087 (to 39422)

====================
error opcode: 'int' object has no attribute '__getitem__'
--> hasjrel 32087 <--
====================

           7335 DUP_TOP             
           7336 BINARY_DIVIDE       
           7337 MAKE_FUNCTION          319
           7340 LOAD_NAME                0 (a)
           7343 LOAD_CONST               2 (0)
           7346 JUMP_ABSOLUTE         7364
        >> 7349 LOAD_NAME                7 (True)
           7352 STORE_NAME               0 (a)
           7355 SETUP_LOOP               9 (to 7367)

====================
error opcode: 'int' object has no attribute '__getitem__'
--> hasjrel 9 <--
====================

           7358 JUMP_ABSOLUTE         7370
           7361 JUMP_ABSOLUTE         2768
        >> 7364 JUMP_ABSOLUTE         6170
        >> 7367 JUMP_ABSOLUTE         2768
        >> 7370 JUMP_FORWARD          1219 (to 8592)

====================
error opcode: 'int' object has no attribute '__getitem__'
--> hasjrel 1219 <--
====================

           7373 CALL_FUNCTION        34180
           7376 INPLACE_AND         
           7377 BINARY_TRUE_DIVIDE  
           7378 LOAD_ATTR            49764
====================
error opcode: 'int' object has no attribute '__getitem__'
--> hasname 49764 <--
====================

           7381 STOP_CODE           
           7382 STORE_FAST               0 (DIVIDER)
           7385 JUMP_ABSOLUTE         7412
        >> 7388 LOAD_CONST             195 (3125336848)
           7391 STORE_FAST               0 (DIVIDER)
           7394 JUMP_ABSOLUTE         7415
        >> 7397 LOAD_CONST             196 (3700268313)
           7400 STORE_FAST               0 (DIVIDER)
           7403 JUMP_ABSOLUTE         7418
        >> 7406 LOAD_CONST             197 (3063339773)
           7409 JUMP_ABSOLUTE           46
        >> 7412 JUMP_ABSOLUTE         3859
        >> 7415 JUMP_ABSOLUTE         3859
        >> 7418 JUMP_ABSOLUTE         3859
           7421 MAKE_CLOSURE          4953
           7424 BREAK_LOOP          
           7425 LOAD_CLOSURE         29542
           7428 SLICE+0             
           7429 INPLACE_TRUE_DIVIDE 
           7430 LOAD_CONST             123 (1220723663)
           7433 LOAD_FAST                0 (DIVIDER)
           7436 COMPARE_OP               2 (==)
           7439 POP_JUMP_IF_TRUE      7457
           7442 LOAD_CONST             158 (2617511990)
           7445 LOAD_FAST                0 (DIVIDER)
           7448 COMPARE_OP               2 (==)
           7451 JUMP_ABSOLUTE         2390
           7454 JUMP_ABSOLUTE         7013
        >> 7457 JUMP_ABSOLUTE          623
           7460 PRINT_ITEM          
           7461 END_FINALLY         
           7462 EXEC_STMT           
           7463 BINARY_MULTIPLY     
           7464 DELETE_FAST          17478
====================
error opcode: 'int' object has no attribute '__getitem__'
--> haslocal 17478 <--
====================

           7467 SETUP_FINALLY          125 (to 7595)

====================
error opcode: 'int' object has no attribute '__getitem__'
--> hasjrel 125 <--
====================

           7470 STOP_CODE           
           7471 JUMP_ABSOLUTE         7498
        >> 7474 LOAD_CONST             146 (3573687990)
           7477 STORE_FAST               0 (DIVIDER)
           7480 JUMP_ABSOLUTE         7501
        >> 7483 LOAD_CONST             147 (4205344010)
           7486 STORE_FAST               0 (DIVIDER)
           7489 JUMP_ABSOLUTE         7504
        >> 7492 LOAD_CONST             148 (1418979794)
           7495 JUMP_ABSOLUTE         1922
        >> 7498 JUMP_ABSOLUTE         3859
        >> 7501 JUMP_ABSOLUTE         3859
        >> 7504 JUMP_ABSOLUTE         3859
           7507 BUILD_SET            25961
           7510 POP_JUMP_IF_TRUE     28529
           7513 INPLACE_TRUE_DIVIDE 
        >> 7514 LOAD_NAME                0 (a)
        >> 7517 LOAD_CONST               8 (1)
           7520 BINARY_ADD          
           7521 POP_TOP             
           7522 LOAD_NAME                0 (a)
           7525 JUMP_ABSOLUTE         7538
        >> 7528 POP_BLOCK           
           7529 JUMP_ABSOLUTE         7541
           7532 JUMP_FORWARD           657 (to 8192)

====================
error opcode: 'int' object has no attribute '__getitem__'
--> hasjrel 657 <--
====================

           7535 JUMP_FORWARD           744 (to 8282)

====================
error opcode: 'int' object has no attribute '__getitem__'
--> hasjrel 744 <--
====================

        >> 7538 JUMP_ABSOLUTE         5542
        >> 7541 JUMP_ABSOLUTE         4549
           7544 DUP_TOPX             26174
           7547 DELETE_SUBSCR       
           7548 WITH_CLEANUP        
           7549 SETUP_LOOP           39283 (to 46835)

====================
error opcode: 'int' object has no attribute '__getitem__'
--> hasjrel 39283 <--
====================

           7552 INPLACE_TRUE_DIVIDE 
           7553 LOAD_CONST              64 (2387599675)
           7556 LOAD_FAST                0 (DIVIDER)
           7559 COMPARE_OP               2 (==)
           7562 POP_JUMP_IF_TRUE      7580
           7565 LOAD_CONST              75 (847064203)
           7568 LOAD_FAST                0 (DIVIDER)
           7571 COMPARE_OP               2 (==)
           7574 JUMP_ABSOLUTE          658
           7577 JUMP_FORWARD           631 (to 8211)

====================
error opcode: 'int' object has no attribute '__getitem__'
--> hasjrel 631 <--
====================

        >> 7580 JUMP_ABSOLUTE         5621
           7583 STORE_SLICE+1       
           7584 BINARY_ADD          
           7585 BUILD_SLICE           5409
           7588 UNARY_NOT           
           7589 BUILD_SET               90
           7592 STOP_CODE           
           7593 JUMP_ABSOLUTE         7615
        >> 7596 STORE_GLOBAL             1 (b)
           7599 LOAD_NAME                0 (a)
           7602 LOAD_CONST               2 (0)
           7605 LOAD_CONST               3 (3)
           7608 SLICE+3             
           7609 JUMP_ABSOLUTE         7618
           7612 JUMP_ABSOLUTE         6409
        >> 7615 JUMP_ABSOLUTE         7483
        >> 7618 JUMP_ABSOLUTE         1946
           7621 RETURN_VALUE        
           7622 DELETE_GLOBAL        15985
====================
error opcode: 'int' object has no attribute '__getitem__'
--> hasname 15985 <--
====================

           7625 JUMP_ABSOLUTE          369
           7628 LOAD_NAME                0 (a)
           7631 LOAD_CONST               8 (1)
           7634 INPLACE_FLOOR_DIVIDE
           7635 JUMP_ABSOLUTE         7648
        >> 7638 BREAK_LOOP          
           7639 JUMP_ABSOLUTE         7651
           7642 JUMP_ABSOLUTE         7654
           7645 JUMP_ABSOLUTE         5855
        >> 7648 JUMP_ABSOLUTE         4834
        >> 7651 JUMP_ABSOLUTE         6546
        >> 7654 JUMP_ABSOLUTE         4080
           7657 UNARY_CONVERT       
           7658 CALL_FUNCTION_VAR    27413
           7661 BINARY_FLOOR_DIVIDE 
           7662 STORE_NAME           27707
====================
error opcode: 'int' object has no attribute '__getitem__'
--> hasname 27707 <--
====================

           7665 JUMP_FORWARD         52324 (to 59992)

====================
error opcode: 'int' object has no attribute '__getitem__'
--> hasjrel 52324 <--
====================

           7668 STOP_CODE           
           7669 STORE_FAST               0 (DIVIDER)
           7672 JUMP_ABSOLUTE         7693
        >> 7675 LOAD_CONST             205 (3585746886)
           7678 STORE_FAST               0 (DIVIDER)
           7681 JUMP_ABSOLUTE         7696
        >> 7684 LOAD_CONST             206 (154196644)
           7687 STORE_FAST               0 (DIVIDER)
           7690 JUMP_ABSOLUTE         4335
        >> 7693 JUMP_ABSOLUTE         3859
        >> 7696 JUMP_ABSOLUTE         3859
           7699 JUMP_ABSOLUTE        29515
           7702 END_FINALLY         
           7703 DUP_TOP             
           7704 IMPORT_STAR         
           7705 BUILD_SET              619
           7708 STOP_CODE           
           7709 POP_JUMP_IF_TRUE      7736
           7712 LOAD_CONST              87 (2942560905)
           7715 LOAD_FAST                0 (DIVIDER)
           7718 COMPARE_OP               2 (==)
           7721 POP_JUMP_IF_TRUE      7739
           7724 LOAD_CONST             176 (1015718548)
           7727 LOAD_FAST                0 (DIVIDER)
           7730 COMPARE_OP               2 (==)
           7733 JUMP_ABSOLUTE         3979
        >> 7736 JUMP_ABSOLUTE         6837
        >> 7739 JUMP_ABSOLUTE         4782
           7742 BINARY_POWER        
           7743 ROT_FOUR            
           7744 BINARY_MULTIPLY     
           7745 EXTENDED_ARG         42084
           7748 STOP_CODE           
           7749 LOAD_FAST            2758017024L
====================
error opcode: 'long' object has no attribute '__getitem__'
--> haslocal 2758017024 <--
====================

           7752 COMPARE_OP               2 (==)
           7755 POP_JUMP_IF_TRUE      7776
           7758 LOAD_CONST             183 (3328796971)
           7761 LOAD_FAST                0 (DIVIDER)
           7764 COMPARE_OP               2 (==)
           7767 POP_JUMP_IF_TRUE      7779
           7770 LOAD_CONST             112 (3872518049)
           7773 JUMP_ABSOLUTE         6241
        >> 7776 JUMP_ABSOLUTE         2982
        >> 7779 JUMP_ABSOLUTE         1091
           7782 JUMP_IF_FALSE_OR_POP 13866
           7785 UNPACK_SEQUENCE        619
           7788 STOP_CODE           
           7789 POP_JUMP_IF_TRUE      7813
           7792 LOAD_CONST             113 (2841491265)
           7795 LOAD_FAST                0 (DIVIDER)
           7798 COMPARE_OP               2 (==)
           7801 POP_JUMP_IF_TRUE      7816
           7804 LOAD_CONST              73 (1057120410)
           7807 LOAD_FAST                0 (DIVIDER)
           7810 JUMP_ABSOLUTE            9
        >> 7813 JUMP_ABSOLUTE          703
        >> 7816 JUMP_ABSOLUTE         1523
           7819 SETUP_FINALLY        25428 (to 33250)

====================
error opcode: 'int' object has no attribute '__getitem__'
--> hasjrel 25428 <--
====================

           7822 UNARY_INVERT        
           7823 MAKE_CLOSURE         15973
           7826 UNARY_NEGATIVE      
           7827 MAP_ADD              44388
           7830 STOP_CODE           
           7831 STORE_FAST               0 (DIVIDER)
           7834 JUMP_ABSOLUTE         7861
        >> 7837 LOAD_CONST             174 (764527121)
           7840 STORE_FAST               0 (DIVIDER)
           7843 JUMP_ABSOLUTE         7864
        >> 7846 LOAD_CONST             175 (289120676)
           7849 STORE_FAST               0 (DIVIDER)
           7852 JUMP_ABSOLUTE         7867
        >> 7855 LOAD_CONST             176 (1015718548)
           7858 JUMP_ABSOLUTE         5186
        >> 7861 JUMP_ABSOLUTE         3859
        >> 7864 JUMP_ABSOLUTE         3859
        >> 7867 JUMP_ABSOLUTE         3859
           7870 JUMP_ABSOLUTE        18716
           7873 STORE_SUBSCR        
           7874 LOAD_NAME             5654
====================
error opcode: 'int' object has no attribute '__getitem__'
--> hasname 5654 <--
====================

           7877 UNARY_NEGATIVE      
           7878 DUP_TOPX             30564
           7881 STOP_CODE           
           7882 LOAD_FAST                0 (DIVIDER)
           7885 COMPARE_OP               2 (==)
           7888 POP_JUMP_IF_TRUE      7906
           7891 LOAD_CONST              57 (323657835)
           7894 LOAD_FAST                0 (DIVIDER)
           7897 COMPARE_OP               2 (==)
           7900 POP_JUMP_IF_TRUE      7909
           7903 JUMP_ABSOLUTE         6284
        >> 7906 JUMP_ABSOLUTE         7638
        >> 7909 JUMP_ABSOLUTE         6601
           7912 BINARY_OR           
           7913 SETUP_LOOP           30465 (to 38381)

====================
error opcode: 'int' object has no attribute '__getitem__'
--> hasjrel 30465 <--
====================

        >> 7916 STORE_FAST               0 (DIVIDER)
           7919 JUMP_ABSOLUTE         7943
        >> 7922 LOAD_CONST              72 (319899592)
           7925 STORE_FAST               0 (DIVIDER)
           7928 JUMP_ABSOLUTE         7946
        >> 7931 LOAD_CONST              73 (1057120410)
           7934 STORE_FAST               0 (DIVIDER)
           7937 JUMP_ABSOLUTE         7949
           7940 JUMP_ABSOLUTE         3152
        >> 7943 JUMP_ABSOLUTE         3859
        >> 7946 JUMP_ABSOLUTE         3859
        >> 7949 JUMP_ABSOLUTE         3859
           7952 DELETE_SLICE+2      
           7953 STORE_ATTR           36690
====================
error opcode: 'int' object has no attribute '__getitem__'
--> hasname 36690 <--
====================

           7956 SETUP_FINALLY        13939 (to 21898)

====================
error opcode: 'int' object has no attribute '__getitem__'
--> hasjrel 13939 <--
====================

           7959 SLICE+1             
           7960 LOAD_CONST             127 (3833384562)
           7963 LOAD_FAST                0 (DIVIDER)
           7966 COMPARE_OP               2 (==)
           7969 POP_JUMP_IF_TRUE      7993
           7972 LOAD_CONST              81 (1122223590)
           7975 LOAD_FAST                0 (DIVIDER)
           7978 COMPARE_OP               2 (==)
           7981 POP_JUMP_IF_TRUE      7996
           7984 LOAD_CONST              71 (1137319345)
           7987 JUMP_FORWARD           809 (to 8799)

====================
error opcode: 'int' object has no attribute '__getitem__'
--> hasjrel 809 <--
====================

           7990 JUMP_ABSOLUTE         1395
        >> 7993 JUMP_ABSOLUTE         4601
        >> 7996 JUMP_ABSOLUTE         3838
           7999 INPLACE_RSHIFT      
           8000 INPLACE_OR          
           8001 IMPORT_NAME           3340
====================
error opcode: 'int' object has no attribute '__getitem__'
--> hasname 3340 <--
====================

           8004 BUILD_LIST           33646
           8007 STOP_CODE           
           8008 STOP_CODE           
           8009 BUILD_CLASS         
           8010 STORE_GLOBAL             8 (aa)
           8013 LOAD_CONST               8 (1)
           8016 JUMP_ABSOLUTE         8037
        >> 8019 FOR_ITER                18 (to 8040)

====================
error opcode: 'int' object has no attribute '__getitem__'
--> hasjrel 18 <--
====================

           8022 JUMP_ABSOLUTE         8043
        >> 8025 JUMP_ABSOLUTE         8046
        >> 8028 SETUP_EXCEPT            18 (to 8049)

====================
error opcode: 'int' object has no attribute '__getitem__'
--> hasjrel 18 <--
====================

           8031 JUMP_ABSOLUTE         8052
           8034 JUMP_ABSOLUTE         3590
        >> 8037 JUMP_ABSOLUTE         4071
        >> 8040 JUMP_ABSOLUTE         8025
        >> 8043 JUMP_ABSOLUTE         7173
        >> 8046 JUMP_ABSOLUTE         3161
        >> 8049 JUMP_ABSOLUTE         3590
        >> 8052 JUMP_ABSOLUTE         3339
           8055 INPLACE_XOR         
           8056 INPLACE_XOR         
           8057 WITH_CLEANUP        
           8058 LOAD_FAST              390
====================
error opcode: 'int' object has no attribute '__getitem__'
--> haslocal 390 <--
====================

           8061 LOAD_NAME                0 (a)
           8064 LOAD_CONST               2 (0)
           8067 BINARY_SUBSCR       
           8068 LOAD_CONST               8 (1)
           8071 JUMP_ABSOLUTE         8081
        >> 8074 LOAD_CONST               2 (0)
           8077 BINARY_SUBSCR       
           8078 JUMP_ABSOLUTE         1381
        >> 8081 JUMP_ABSOLUTE         1717
           8084 BUILD_CLASS         
           8085 DUP_TOPX              5123
           8088 DELETE_SLICE+0      
           8089 IMPORT_NAME          22805
====================
error opcode: 'int' object has no attribute '__getitem__'
--> hasname 22805 <--
====================

           8092 LOAD_DEREF           48755
           8095 SLICE+1             
           8096 LOAD_CONST             181 (3869867632)
           8099 LOAD_FAST                0 (DIVIDER)
           8102 COMPARE_OP               2 (==)
           8105 POP_JUMP_IF_TRUE      8129
           8108 LOAD_CONST             154 (3033067667)
           8111 LOAD_FAST                0 (DIVIDER)
           8114 COMPARE_OP               2 (==)
           8117 POP_JUMP_IF_TRUE      8132
           8120 LOAD_CONST              99 (409037964)
           8123 JUMP_ABSOLUTE         2017
           8126 JUMP_ABSOLUTE         5411
        >> 8129 JUMP_ABSOLUTE         5243
        >> 8132 JUMP_ABSOLUTE         3632
           8135 BUILD_SLICE            874
           8138 BINARY_MULTIPLY     
           8139 BINARY_SUBTRACT     
           8140 INPLACE_TRUE_DIVIDE 
           8141 DELETE_SLICE+3      
           8142 MAKE_FUNCTION        29537
           8145 <241>                25631
           8148 STORE_ATTR           31744
====================
error opcode: 'int' object has no attribute '__getitem__'
--> hasname 31744 <--
====================

           8151 STOP_CODE           
           8152 STOP_CODE           
           8153 COMPARE_OP               2 (==)
           8156 POP_JUMP_IF_TRUE      8180
           8159 LOAD_CONST             142 (2115624883)
           8162 LOAD_FAST                0 (DIVIDER)
           8165 COMPARE_OP               2 (==)
           8168 POP_JUMP_IF_TRUE      8183
           8171 LOAD_CONST             206 (154196644)
           8174 JUMP_FORWARD           366 (to 8543)

====================
error opcode: 'int' object has no attribute '__getitem__'
--> hasjrel 366 <--
====================

           8177 JUMP_ABSOLUTE         2286
        >> 8180 JUMP_ABSOLUTE         3289
        >> 8183 JUMP_ABSOLUTE          459
           8186 DELETE_ATTR           6711
====================
error opcode: 'int' object has no attribute '__getitem__'
--> hasname 6711 <--
====================

           8189 INPLACE_AND         
           8190 NOP                 
           8191 IMPORT_NAME           3674
====================
error opcode: 'int' object has no attribute '__getitem__'
--> hasname 3674 <--
====================

           8194 STOP_CODE           
           8195 JUMP_ABSOLUTE         8221
           8198 JUMP_ABSOLUTE         8224
        >> 8201 LOAD_NAME                0 (a)
           8204 ROT_TWO             
           8205 STORE_NAME               0 (a)
           8208 JUMP_ABSOLUTE         8227
        >> 8211 CALL_FUNCTION            1
           8214 LOAD_CONST               8 (1)
           8217 SLICE+1             
           8218 JUMP_ABSOLUTE         5040
        >> 8221 JUMP_ABSOLUTE         7264
        >> 8224 JUMP_ABSOLUTE         4893
        >> 8227 JUMP_ABSOLUTE         5293
           8230 MAP_ADD              26501
           8233 ROT_FOUR            
           8234 BINARY_FLOOR_DIVIDE 
           8235 IMPORT_FROM            524
====================
error opcode: 'int' object has no attribute '__getitem__'
--> hasname 524 <--
====================

           8238 CONTINUE_LOOP           90
           8241 STOP_CODE           
           8242 LOAD_NAME                0 (a)
           8245 LOAD_CONST               8 (1)
           8248 INPLACE_XOR         
           8249 JUMP_ABSOLUTE         8263
        >> 8252 LOAD_CONST               8 (1)
           8255 BINARY_OR           
           8256 POP_TOP             
           8257 LOAD_NAME                0 (a)
           8260 JUMP_ABSOLUTE         2724
        >> 8263 JUMP_ABSOLUTE         4220
           8266 PRINT_NEWLINE       
           8267 MAP_ADD              32076
           8270 INPLACE_TRUE_DIVIDE 
           8271 LOAD_LOCALS         
           8272 STORE_GLOBAL         32868
====================
error opcode: 'int' object has no attribute '__getitem__'
--> hasname 32868 <--
====================

           8275 STOP_CODE           
           8276 STORE_FAST               0 (DIVIDER)
           8279 JUMP_ABSOLUTE         8303
        >> 8282 LOAD_CONST             129 (1766343454)
           8285 STORE_FAST               0 (DIVIDER)
           8288 JUMP_ABSOLUTE         8306
        >> 8291 LOAD_CONST             130 (1498650410)
           8294 STORE_FAST               0 (DIVIDER)
           8297 JUMP_ABSOLUTE         8309
           8300 JUMP_ABSOLUTE         1699
        >> 8303 JUMP_ABSOLUTE         3859
        >> 8306 JUMP_ABSOLUTE         3859
        >> 8309 JUMP_ABSOLUTE         3859
           8312 UNARY_NEGATIVE      
           8313 POP_TOP             
           8314 END_FINALLY         
           8315 JUMP_IF_FALSE_OR_POP 24658
           8318 STORE_DEREF            619
           8321 STOP_CODE           
           8322 POP_JUMP_IF_TRUE      8352
           8325 LOAD_CONST              69 (3161245959)
           8328 LOAD_FAST                0 (DIVIDER)
           8331 COMPARE_OP               2 (==)
           8334 POP_JUMP_IF_TRUE      8355
           8337 LOAD_CONST             202 (3391917192)
           8340 LOAD_FAST                0 (DIVIDER)
           8343 COMPARE_OP               2 (==)
           8346 POP_JUMP_IF_TRUE      8358
           8349 JUMP_ABSOLUTE          312
        >> 8352 JUMP_ABSOLUTE         7338
        >> 8355 JUMP_ABSOLUTE         5855
        >> 8358 JUMP_ABSOLUTE         2363
           8361 CALL_FUNCTION         5658
           8364 SETUP_LOOP           23881 (to 32248)

====================
error opcode: 'int' object has no attribute '__getitem__'
--> hasjrel 23881 <--
====================

        >> 8367 LOAD_NAME                0 (a)
           8370 CALL_FUNCTION            0
           8373 POP_TOP             
           8374 JUMP_ABSOLUTE         8396
        >> 8377 POP_TOP             
           8378 LOAD_CONST              29 (<code object r at 0x104bbde30, file "ck.py", line 110>)
           8381 MAKE_FUNCTION            0
           8384 STORE_NAME              16 (r)
           8387 LOAD_CONST              30 (<code object a at 0x104bbdeb0, file "ck.py", line 115>)
           8390 JUMP_ABSOLUTE         8399
           8393 JUMP_ABSOLUTE          703
        >> 8396 JUMP_ABSOLUTE         4875
        >> 8399 JUMP_ABSOLUTE         2564
           8402 CALL_FUNCTION_VAR    31753
           8405 STORE_ATTR            5989
====================
error opcode: 'int' object has no attribute '__getitem__'
--> hasname 5989 <--
====================

           8408 STOP_CODE           
           8409 CALL_FUNCTION_VAR        0
           8412 POP_TOP             
           8413 JUMP_ABSOLUTE         8437
        >> 8416 STORE_NAME               0 (a)
           8419 LOAD_CONST              24 (<code object a at 0x104bbdc30, file "ck.py", line 88>)
           8422 MAKE_FUNCTION            0
           8425 STORE_NAME               0 (a)
           8428 LOAD_CONST               8 (1)
           8431 JUMP_ABSOLUTE         8440
           8434 JUMP_ABSOLUTE         6621
        >> 8437 JUMP_ABSOLUTE         7684
        >> 8440 JUMP_ABSOLUTE         4356
           8443 BINARY_MODULO       
           8444 INPLACE_MODULO      
           8445 DELETE_SLICE+0      
           8446 BINARY_DIVIDE       
           8447 CALL_FUNCTION_VAR_KW 15716
           8450 STOP_CODE           
           8451 LOAD_FAST                0 (DIVIDER)
           8454 COMPARE_OP               2 (==)
           8457 POP_JUMP_IF_TRUE      8481
           8460 LOAD_CONST             132 (3022458678)
           8463 LOAD_FAST                0 (DIVIDER)
           8466 COMPARE_OP               2 (==)
           8469 POP_JUMP_IF_TRUE      8484
           8472 LOAD_CONST             150 (156827783)
           8475 LOAD_FAST                0 (DIVIDER)
           8478 JUMP_ABSOLUTE         2938
        >> 8481 JUMP_ABSOLUTE         3247
        >> 8484 JUMP_ABSOLUTE         8406
           8487 RETURN_VALUE        
           8488 INPLACE_DIVIDE      
           8489 BUILD_MAP            33655
           8492 STORE_SLICE+3       
           8493 STORE_SLICE+3       
           8494 SETUP_FINALLY         6237 (to 14734)

====================
error opcode: 'int' object has no attribute '__getitem__'
--> hasjrel 6237 <--
====================

           8497 STOP_CODE           
           8498 JUMP_ABSOLUTE         8525
        >> 8501 JUMP_ABSOLUTE         8528
        >> 8504 LOAD_CONST               0 (<code object a at 0x104bbd930, file "ck.py", line 1>)
           8507 MAKE_FUNCTION            0
           8510 STORE_NAME               0 (a)
           8513 JUMP_ABSOLUTE         8531
        >> 8516 FOR_ITER                15 (to 8534)

====================
error opcode: 'int' object has no attribute '__getitem__'
--> hasjrel 15 <--
====================

           8519 JUMP_ABSOLUTE         2270
           8522 JUMP_ABSOLUTE         8501
        >> 8525 JUMP_ABSOLUTE         4089
        >> 8528 JUMP_ABSOLUTE          595
        >> 8531 JUMP_ABSOLUTE         7191
        >> 8534 JUMP_ABSOLUTE         2273
           8537 BINARY_MULTIPLY     
           8538 BINARY_MODULO       
           8539 LOAD_NAME             2932
====================
error opcode: 'int' object has no attribute '__getitem__'
--> hasname 2932 <--
====================

           8542 DELETE_GLOBAL          124
====================
error opcode: 'int' object has no attribute '__getitem__'
--> hasname 124 <--
====================

           8545 STOP_CODE           
           8546 COMPARE_OP               2 (==)
           8549 POP_JUMP_IF_TRUE      8576
           8552 LOAD_CONST             108 (417535526)
           8555 LOAD_FAST                0 (DIVIDER)
           8558 COMPARE_OP               2 (==)
           8561 POP_JUMP_IF_TRUE      8579
           8564 LOAD_CONST             177 (3784794503)
           8567 LOAD_FAST                0 (DIVIDER)
           8570 COMPARE_OP               2 (==)
           8573 JUMP_ABSOLUTE         1108
        >> 8576 JUMP_ABSOLUTE         6337
        >> 8579 JUMP_ABSOLUTE         5746
           8582 MAKE_FUNCTION        16389
           8585 DUP_TOPX              3390
           8588 EXTENDED_ARG         43121
           8591 SLICE+3             
        >> 8592 LOAD_CONST           2825977999L
====================
error opcode: 'long' object has no attribute '__getitem__'
--> hasconst 2825977999 <--
====================

           8595 STORE_FAST               0 (DIVIDER)
           8598 JUMP_ABSOLUTE         8619
        >> 8601 LOAD_CONST             144 (2578110378)
           8604 STORE_FAST               0 (DIVIDER)
           8607 JUMP_ABSOLUTE         8622
        >> 8610 LOAD_CONST             145 (111410995)
           8613 JUMP_ABSOLUTE         7468
           8616 JUMP_ABSOLUTE         3859
        >> 8619 JUMP_ABSOLUTE         3859
        >> 8622 JUMP_ABSOLUTE         3859
           8625 EXEC_STMT           
           8626 END_FINALLY         
           8627 STORE_GLOBAL         13847
====================
error opcode: 'int' object has no attribute '__getitem__'
--> hasname 13847 <--
====================

           8630 ROT_FOUR            
           8631 DELETE_GLOBAL        25733
====================
error opcode: 'int' object has no attribute '__getitem__'
--> hasname 25733 <--
====================

           8634 CALL_FUNCTION        31744
           8637 STOP_CODE           
           8638 STOP_CODE           
           8639 COMPARE_OP               2 (==)
           8642 POP_JUMP_IF_TRUE      8660
           8645 LOAD_CONST             122 (219186335)
           8648 LOAD_FAST                0 (DIVIDER)
           8651 COMPARE_OP               2 (==)
           8654 POP_JUMP_IF_TRUE      8663
           8657 JUMP_ABSOLUTE          489
        >> 8660 JUMP_ABSOLUTE         1510
        >> 8663 JUMP_ABSOLUTE          635
           8666 DUP_TOPX             26645
           8669 YIELD_VALUE         
           8670 BINARY_FLOOR_DIVIDE 
           8671 COMPARE_OP           14622
====================
error opcode: 'int' object has no attribute '__getitem__'
--> hascompare 14622 <--
====================

           8674 CALL_FUNCTION         1139
           8677 <34>                
           8678 LOAD_CONST              68 (1453245079)
           8681 LOAD_FAST                0 (DIVIDER)
           8684 COMPARE_OP               2 (==)
           8687 POP_JUMP_IF_TRUE      8711
           8690 LOAD_CONST              94 (1270056785)
           8693 LOAD_FAST                0 (DIVIDER)
           8696 COMPARE_OP               2 (==)
           8699 POP_JUMP_IF_TRUE      8714
           8702 LOAD_CONST              58 (2907760793)
           8705 JUMP_ABSOLUTE         4951
           8708 JUMP_ABSOLUTE         8060
        >> 8711 JUMP_FORWARD            27 (to 8741)

====================
error opcode: 'int' object has no attribute '__getitem__'
--> hasjrel 27 <--
====================

        >> 8714 JUMP_ABSOLUTE         5445
           8717 MAKE_FUNCTION        33824
           8720 UNARY_NOT           
           8721 DELETE_NAME           9060
====================
error opcode: 'int' object has no attribute '__getitem__'
--> hasname 9060 <--
====================

           8724 STOP_CODE           
           8725 MAKE_FUNCTION            0
           8728 JUMP_ABSOLUTE         8747
        >> 8731 BUILD_LIST               0
           8734 POP_TOP             
           8735 LOAD_CONST               8 (1)
           8738 JUMP_ABSOLUTE         8750
        >> 8741 LOAD_CONST               8 (1)
           8744 JUMP_FORWARD           185 (to 8932)

====================
error opcode: 'int' object has no attribute '__getitem__'
--> hasjrel 185 <--
====================

        >> 8747 JUMP_ABSOLUTE          968
        >> 8750 JUMP_ABSOLUTE         3330
           8753 JUMP_IF_TRUE_OR_POP  15666
           8756 DUP_TOPX               619
           8759 STOP_CODE           
           8760 POP_JUMP_IF_TRUE      8784
           8763 LOAD_CONST             212 (3190570824)
           8766 LOAD_FAST                0 (DIVIDER)
           8769 COMPARE_OP               2 (==)
           8772 POP_JUMP_IF_TRUE      8787
           8775 LOAD_CONST             208 (3353002622)
           8778 LOAD_FAST                0 (DIVIDER)
           8781 JUMP_ABSOLUTE         8319
        >> 8784 JUMP_ABSOLUTE         3737
        >> 8787 JUMP_ABSOLUTE         6772
           8790 BUILD_SLICE          28285
           8793 SLICE+1             
           8794 SET_ADD              20295
           8797 DELETE_SLICE+3      
           8798 JUMP_ABSOLUTE          124
           8801 STOP_CODE           
           8802 COMPARE_OP               2 (==)
           8805 POP_JUMP_IF_TRUE      8829
           8808 LOAD_CONST              82 (3913884456)
           8811 LOAD_FAST                0 (DIVIDER)
           8814 COMPARE_OP               2 (==)
           8817 POP_JUMP_IF_TRUE      8832
           8820 LOAD_CONST             156 (1412035677)
           8823 LOAD_FAST                0 (DIVIDER)
           8826 JUMP_ABSOLUTE         7786
        >> 8829 JUMP_ABSOLUTE         3593
        >> 8832 JUMP_ABSOLUTE         4700
           8835 STORE_SLICE+2       
           8836 INPLACE_MULTIPLY    
           8837 JUMP_IF_TRUE_OR_POP  23609
           8840 STORE_SUBSCR        
           8841 DELETE_FAST          27737
====================
error opcode: 'int' object has no attribute '__getitem__'
--> haslocal 27737 <--
====================

        >> 8844 LOAD_FAST                0 (DIVIDER)
           8847 COMPARE_OP               2 (==)
           8850 POP_JUMP_IF_TRUE      8877
           8853 LOAD_CONST              77 (3571241703)
           8856 LOAD_FAST                0 (DIVIDER)
           8859 COMPARE_OP               2 (==)
           8862 POP_JUMP_IF_TRUE      8880
           8865 LOAD_CONST              54 (2106207243)
           8868 LOAD_FAST                0 (DIVIDER)
           8871 COMPARE_OP               2 (==)
           8874 JUMP_ABSOLUTE         3937
        >> 8877 JUMP_ABSOLUTE         1204
        >> 8880 JUMP_ABSOLUTE         3779
           8883 BINARY_ADD          
           8884 DELETE_ATTR           2918
====================
error opcode: 'int' object has no attribute '__getitem__'
--> hasname 2918 <--
====================

           8887 LOAD_LOCALS         
           8888 BINARY_DIVIDE       
           8889 EXEC_STMT           
           8890 FOR_ITER             36964 (to 45857)

====================
error opcode: 'int' object has no attribute '__getitem__'
--> hasjrel 36964 <--
====================

           8893 STOP_CODE           
           8894 LOAD_FAST                0 (DIVIDER)
           8897 COMPARE_OP               2 (==)
           8900 POP_JUMP_IF_TRUE      8918
           8903 LOAD_CONST             130 (1498650410)
           8906 LOAD_FAST                0 (DIVIDER)
           8909 COMPARE_OP               2 (==)
           8912 POP_JUMP_IF_TRUE      8921
           8915 JUMP_ABSOLUTE         8448
        >> 8918 JUMP_ABSOLUTE         2375
        >> 8921 JUMP_ABSOLUTE         4792
           8924 ROT_THREE           
           8925 BINARY_TRUE_DIVIDE  
           8926 JUMP_IF_TRUE_OR_POP  36173
           8929 CALL_FUNCTION_KW     25934
        >> 8932 BINARY_SUBTRACT     
           8933 POP_TOP             
           8934 LOAD_NAME                3 (str)
           8937 JUMP_ABSOLUTE         8953
        >> 8940 SETUP_EXCEPT            13 (to 8956)

====================
error opcode: 'int' object has no attribute '__getitem__'
--> hasjrel 13 <--
====================

           8943 JUMP_ABSOLUTE         8959
        >> 8946 JUMP_ABSOLUTE         8962
        >> 8949 INPLACE_AND         
           8950 JUMP_ABSOLUTE         8239
        >> 8953 JUMP_ABSOLUTE         4131
        >> 8956 JUMP_ABSOLUTE         8946
        >> 8959 JUMP_ABSOLUTE         2332
        >> 8962 JUMP_ABSOLUTE          577
           8965 STORE_MAP           
           8966 INPLACE_AND         
           8967 POP_JUMP_IF_TRUE     29552
           8970 <36>                
           8971 <35>                
           8972 LOAD_CONST             171 (2908258129)
           8975 LOAD_FAST                0 (DIVIDER)
           8978 COMPARE_OP               2 (==)
           8981 POP_JUMP_IF_TRUE      8999
           8984 LOAD_CONST              60 (3062359377)
           8987 LOAD_FAST                0 (DIVIDER)
           8990 COMPARE_OP               2 (==)
           8993 JUMP_ABSOLUTE         7957
           8996 JUMP_ABSOLUTE         5951
        >> 8999 JUMP_ABSOLUTE         3293
           9002 LOAD_GLOBAL          15170
====================
error opcode: 'int' object has no attribute '__getitem__'
--> hasname 15170 <--
====================

           9005 DELETE_FAST          28005
====================
error opcode: 'int' object has no attribute '__getitem__'
--> haslocal 28005 <--
====================

